Workbook

Sheet Persons
A1: WissKI ID | B1: Identifier | C1: Service | D1: Descriptive name | E1: Name in source (orig) | F1: Name in source (transl) | G1: Gender assignment | H1: Ethnicity | I1: Social role (C2) | J1: Legal role (C12) | K1: Language skill | L1: Religion | M1: Authority | N1: Authority group | O1: Based on | P1: Source text/publication | Q1: Source text/reference | R1: Source text/excerpt | S1: ID string
A2: https://r11.eu/rdf/resource/6f21cc33-baa9-417f-bd99-1cfd796e5ebc | B2: Aaron 101 | C2: https://pbw2016.kdl.kcl.ac.uk/ | D2: Aaron, brother of Alousianos | S2: =_xlfn.CONCAT(B2, " / ", D2) -> Aaron 101 / Aaron, brother of Alousianos
A3: https://r11.eu/rdf/resource/37ade4c7-baf2-4bec-b978-9220da8a0c0a | B3: Ioannes 110 | C3: https://pbw2016.kdl.kcl.ac.uk/ | D3: Ioannes Skylitzes, historian | S3: =_xlfn.CONCAT(B3, " / ", D3) -> Ioannes 110 / Ioannes Skylitzes, historian
A4: https://r11.eu/rdf/resource/7231f2c2-e72b-4cd6-abe4-a96c96c18a0b | B4: Ioannes 6007 | C4: https://pbw2016.kdl.kcl.ac.uk/ | D4: Ioannes Zonaras | S4: =_xlfn.CONCAT(B4, " / ", D4) -> Ioannes 6007 / Ioannes Zonaras
A5: https://r11.eu/rdf/resource/3dee6940-7654-4203-abe6-3002701f4978 | B5: Aristakes 101 | C5: https://pbw2016.kdl.kcl.ac.uk/ | D5: Aristakes Lastivertc'i / of Lastivert, Armenian historian | S5: =_xlfn.CONCAT(B5, " / ", D5) -> Aristakes 101 / Aristakes Lastivertc'i / of Lastivert, Armenian historian
A6: https://r11.eu/rdf/resource/3730d2a8-0994-47d8-b122-dedb83652e00 | B6: Eustathios 105 | C6: https://pbw2016.kdl.kcl.ac.uk/ | D6: Eustathios Boilas | S6: =_xlfn.CONCAT(B6, " / ", D6) -> Eustathios 105 / Eustathios Boilas
A7: https://r11.eu/rdf/resource/0f7afd6a-cdd8-4a6e-b7bf-19bff9fd2c82 | B7: Alousianos 101 | C7: https://pbw2016.kdl.kcl.ac.uk/ | D7: Alousianos, son of Ioannes/John Vladislav | S7: =_xlfn.CONCAT(B7, " / ", D7) -> Alousianos 101 / Alousianos, son of Ioannes/John Vladislav
A8: https://r11.eu/rdf/resource/308b9a54-9f9d-42a3-81e1-bf435a40f664 | B8: Vladislav 101 | C8: https://pbw2016.kdl.kcl.ac.uk/ | D8: John Vladislav, ruler of Bulgaria | S8: =_xlfn.CONCAT(B8, " / ", D8) -> Vladislav 101 / John Vladislav, ruler of Bulgaria
A9: https://r11.eu/rdf/resource/90f6f7c6-10a3-404d-92d2-e1ba435ef3b8 | B9: Prousianos 101 | C9: https://pbw2016.kdl.kcl.ac.uk/ | D9: Prousianos, son of John Vladislav of Bulgaria | S9: =_xlfn.CONCAT(B9, " / ", D9) -> Prousianos 101 / Prousianos, son of John Vladislav of Bulgaria
A10: https://r11.eu/rdf/resource/35235889-599a-4f10-aa14-bae77a13c5e8 | B10: Aikaterine 101 | C10: https://pbw2016.kdl.kcl.ac.uk/ | D10: Aikaterine of Bulgaria, wife of Isaakios I Komnenos | S10: =_xlfn.CONCAT(B10, " / ", D10) -> Aikaterine 101 / Aikaterine of Bulgaria, wife of Isaakios I Komnenos
A11: https://r11.eu/rdf/resource/cfb62a1d-e5a5-4741-a3a3-327ae2a937d2 | B11: Theodoros 173 | C11: https://pbw2016.kdl.kcl.ac.uk/ | D11: Theodoros, governor of Taron, son of Aaron | S11: =_xlfn.CONCAT(B11, " / ", D11) -> Theodoros 173 / Theodoros, governor of Taron, son of Aaron
A12: https://r11.eu/rdf/resource/823d2106-62ab-4715-a407-d972c998ae1d | B12: Tatranes 101 | C12: https://pbw2016.kdl.kcl.ac.uk/ | D12: Tatranes, Pecheneg deserter to Alexios I | S12: =_xlfn.CONCAT(B12, " / ", D12) -> Tatranes 101 / Tatranes, Pecheneg deserter to Alexios I
A13: https://r11.eu/rdf/resource/a4705735-c9ee-4b64-acad-6b71dc07e6dd | B13: Anna 62 | C13: https://pbw2016.kdl.kcl.ac.uk/ | D13: Anna Komnene, daughter of Alexios I and historian | S13: =_xlfn.CONCAT(B13, " / ", D13) -> Anna 62 / Anna Komnene, daughter of Alexios I and historian
... A193: https://r11.eu/rdf/resource/d90ed912-779d-4f91-b6a9-e7ebd795154b | B193: Andronikos 62 | C193: https://pbw2016.kdl.kcl.ac.uk/ | D193: Andronikos Doukas, brother of Michael VII | S193: =_xlfn.CONCAT(B193, " / ", D193) -> Andronikos 62 / Andronikos Doukas, brother of Michael VII
A194: https://r11.eu/rdf/resource/e7265cc7-4659-47c5-871b-2b8f62024b95 | B194: Konstantios 61 | C194: https://pbw2016.kdl.kcl.ac.uk/ | D194: Konstantios Doukas, brother of Michael VII | S194: =_xlfn.CONCAT(B194," / ",D194) -> Konstantios 61 / Konstantios Doukas, brother of Michael VII
A195: https://r11.eu/rdf/resource/e25a4a6c-a2bc-400b-8f34-450a4798e105 | B195: Michael 121 | C195: https://pbw2016.kdl.kcl.ac.uk/ | D195: Michael Doukas, brother of Eirene Doukaina | S195: =_xlfn.CONCAT(B195," / ",D195) -> Michael 121 / Michael Doukas, brother of Eirene Doukaina
A196: https://r11.eu/rdf/resource/3cdc803e-2edc-4039-b78d-a072dada8149 | B196: Konstantinos 61 | C196: https://pbw2016.kdl.kcl.ac.uk/ | D196: Konstantinos Doukas, son of Kaisar Ioannes | S196: =_xlfn.CONCAT(B196," / ",D196) -> Konstantinos 61 / Konstantinos Doukas, son of Kaisar Ioannes
A197: https://r11.eu/rdf/resource/e2b7aa9a-e6d6-4e45-9327-72ed0e127a5d | B197: Maria 62 | C197: https://pbw2016.kdl.kcl.ac.uk/ | D197: Maria of Bulgaria, wife of Andronikos Doukas | S197: =_xlfn.CONCAT(B197," / ",D197) -> Maria 62 / Maria of Bulgaria, wife of Andronikos Doukas
A198: https://r11.eu/rdf/resource/ae1e9870-d548-47a7-aa48-da4016e3b0fc | B198: Anna 63 | C198: https://pbw2016.kdl.kcl.ac.uk/ | D198: Anna Doukaina, sister of Eirene Doukaina and wife of Georgios Palaiologos | S198: =_xlfn.CONCAT(B198," / ",D198) -> Anna 63 / Anna Doukaina, sister of Eirene Doukaina and wife of Georgios Palaiologos
A199: https://r11.eu/rdf/resource/7da8d452-e91d-4180-83f7-611f4505d743 | B199: Theodora 5001 | C199: https://pbw2016.kdl.kcl.ac.uk/ | D199: Theodora, sister of Eirene Doukaina | S199: =_xlfn.CONCAT(B199," / ",D199) -> Theodora 5001 / Theodora, sister of Eirene Doukaina
A200: https://r11.eu/rdf/resource/267571d2-9f5a-4863-a9b2-514200c83038 | B200: Eirene 20117 | C200: https://pbw2016.kdl.kcl.ac.uk/ | D200: Eirene Pegonitissa, wife of Ioannes the kaisar | S200: =_xlfn.CONCAT(B200," / ",D200) -> Eirene 20117 / Eirene Pegonitissa, wife of Ioannes the kaisar
A201: https://r11.eu/rdf/resource/2df16e85-b7c6-46b0-b003-7c3a21321a87 | B201: Andronikos 2102 | C201: https://pbw2016.kdl.kcl.ac.uk/ | D201: Andronikos Doukas, father of kaisar Ioannes Doukas | S201: =_xlfn.CONCAT(B201," / ",D201) -> Andronikos 2102 / Andronikos Doukas, father of kaisar Ioannes Doukas
A202: https://r11.eu/rdf/resource/0e6dca10-7f56-4685-a4f5-81508fd1322f | B202: Eustathios 20147 | C202: https://pbw2016.kdl.kcl.ac.uk/ | D202: Eustathios, metropolitan of Thessalonike | S202: =_xlfn.CONCAT(B202," / ",D202) -> Eustathios 20147 / Eustathios, metropolitan of Thessalonike
A203: https://r11.eu/rdf/resource/01eac7db-b871-4344-97ac-8cd94522bf02 | B203: Konstantinos 10 | C203: https://pbw2016.kdl.kcl.ac.uk/ | D203: Emperor Konstantinos X Doukas | S203: =_xlfn.CONCAT(B203," / ",D203) -> Konstantinos 10 / Emperor Konstantinos X Doukas
A204: https://r11.eu/rdf/resource/73aedb3b-e80c-4165-add8-371ca549009c | B204: Eudokia 1 | C204: https://pbw2016.kdl.kcl.ac.uk/ | D204: Empress Eudokia Makrembolitissa | S204: =_xlfn.CONCAT(B204," / ",D204) -> Eudokia 1 / Empress Eudokia Makrembolitissa
A205: https://r11.eu/rdf/resource/526e6f40-2894-4975-a749-5fca39b3f047 | B205: Romanos 4 | C205: https://pbw2016.kdl.kcl.ac.uk/ | D205: Emperor Romanos IV Diogenes | S205: =_xlfn.CONCAT(B205," / ",D205) -> Romanos 4 / Emperor Romanos IV Diogenes
... A1025: https://r11.eu/rdf/resource/f5652096-4109-403c-a711-4b04b6952b73 | B1025: Maria 169 | C1025: https://pbw2016.kdl.kcl.ac.uk/ | D1025: Maria (?), wife of Manuel Komnenos Erotikos | S1025: =_xlfn.CONCAT(B1025," / ",D1025) -> Maria 169 / Maria (?), wife of Manuel Komnenos Erotikos
A1026: https://r11.eu/rdf/resource/f5404d43-c47b-46dc-8ea8-cfd9f0d074fd | B1026: Anonyma 5004 | C1026: https://pbw2016.kdl.kcl.ac.uk/ | D1026: daughter of Manuel Komnenos Erotikos, wife of Michael Dokeianos (?) | S1026: =_xlfn.CONCAT(B1026, " / ", D1026) -> Anonyma 5004 / daughter of Manuel Komnenos Erotikos, wife of Michael Dokeianos (?)
A1027: https://r11.eu/rdf/resource/940e7fe9-6842-433f-a0f0-54efe9832621 | B1027: Barkyaruq 101 | C1027: https://pbw2016.kdl.kcl.ac.uk/ | D1027: Barkyaruq, Seljuq sultan | S1027: =_xlfn.CONCAT(B1027, " / ", D1027) -> Barkyaruq 101 / Barkyaruq, Seljuq sultan
A1028: https://r11.eu/rdf/resource/6a250e11-7116-4668-8056-eccb6b70ebcd | B1028: Malik-Shah 51 | C1028: https://pbw2016.kdl.kcl.ac.uk/ | D1028: Malik-Shah, Seljuk sultan | S1028: =_xlfn.CONCAT(B1028, " / ", D1028) -> Malik-Shah 51 / Malik-Shah, Seljuk sultan
A1029: https://r11.eu/rdf/resource/146017c2-72b6-4d42-8447-9392cecb9307 | B1029: Anonyma 271 | C1029: https://pbw2016.kdl.kcl.ac.uk/ | D1029: freed concubine of sultan Malik-Shah, mother of sultans Muhammad and Sanjar | S1029: =_xlfn.CONCAT(B1029, " / ", D1029) -> Anonyma 271 / freed concubine of sultan Malik-Shah, mother of sultans Muhammad and Sanjar
A1030: https://r11.eu/rdf/resource/e56b3cfd-7b15-4ad4-b52b-9704975a378b | B1030: Muhammad 104 | C1030: https://pbw2016.kdl.kcl.ac.uk/ | D1030: Muhammad ibn Malik-Shah, Seljuq sultan | S1030: =_xlfn.CONCAT(B1030, " / ", D1030) -> Muhammad 104 / Muhammad ibn Malik-Shah, Seljuq sultan
A1031: https://r11.eu/rdf/resource/be22579c-dc0f-4c37-a086-d0043519f865 | B1031: Mawdud 101 | C1031: https://pbw2016.kdl.kcl.ac.uk/ | D1031: Mawdud ibn Isma'il, ruler of part of Azerbayjan | S1031: =_xlfn.CONCAT(B1031, " / ", D1031) -> Mawdud 101 / Mawdud ibn Isma'il, ruler of part of Azerbayjan
A1032: https://r11.eu/rdf/resource/10dc7378-0fa2-472f-93b3-efb63742b6ff | B1032: Ioannes 64 | C1032: https://pbw2016.kdl.kcl.ac.uk/ | D1032: Ioannes the protovestiarios | S1032: =_xlfn.CONCAT(B1032, " / ", D1032) -> Ioannes 64 / Ioannes the protovestiarios
A1033: https://r11.eu/rdf/resource/e2c6794d-f5df-4b66-8805-139a6bde44d9 | B1033: Abu Usama 101 | C1033: https://pbw2016.kdl.kcl.ac.uk/ | D1033: Abu Usama, the cadi of Aleppo | S1033: =_xlfn.CONCAT(B1033, " / ", D1033) -> Abu Usama 101 / Abu Usama, the cadi of Aleppo
A1034: https://r11.eu/rdf/resource/b44432cd-23df-4b42-ac07-899386c87ecc | B1034: Ioannes 66 | C1034: https://pbw2016.kdl.kcl.ac.uk/ | D1034: Ioannes Italos | S1034: =_xlfn.CONCAT(B1034, " / ", D1034) -> Ioannes 66 / Ioannes Italos
A1035: https://r11.eu/rdf/resource/d08f68bc-9180-4026-b7d6-27c5ff000745 | B1035: Niketas 104 | C1035: https://pbw2016.kdl.kcl.ac.uk/ | D1035: Niketas, brother of Michael IV | S1035: =_xlfn.CONCAT(B1035, " / ", D1035) -> Niketas 104 / Niketas, brother of Michael IV
A1036: https://r11.eu/rdf/resource/f8f366b0-2274-4683-a5ca-950f00319146 | B1036: Konstantinos 64 | C1036: https://pbw2016.kdl.kcl.ac.uk/ | D1036: Konstantinos, brother of Michael IV | S1036: =_xlfn.CONCAT(B1036, " / ", D1036) -> Konstantinos 64 / Konstantinos, brother of Michael IV
A1037: https://r11.eu/rdf/resource/a96538c3-da8c-4f2b-a55e-0976e61511c2 | B1037: Maria 104 | C1037: https://pbw2016.kdl.kcl.ac.uk/ | D1037: Maria, sister of Michael IV, mother of Michael V | S1037: =_xlfn.CONCAT(B1037, " / ", D1037) -> Maria 104 / Maria, sister of Michael IV, mother of Michael V
... A1089: https://r11.eu/rdf/resource/e327693f-b666-41c1-a6a3-188d8d731039 | B1089: Ioannes 154 | C1089: https://pbw2016.kdl.kcl.ac.uk/ | D1089: Ioannes, tax-payer at chorion of Dobrobikeia | S1089: =_xlfn.CONCAT(B1089, " / ", D1089) -> Ioannes 154 / Ioannes, tax-payer at chorion of Dobrobikeia
A1090: https://r11.eu/rdf/resource/13275921-d862-499a-bc06-22451e590cbf | B1090: Ivan 101 | C1090: https://pbw2016.kdl.kcl.ac.uk/ | D1090: Ivan, father of tax-payer at chorion of Dobrobikeia | S1090: =_xlfn.CONCAT(B1090," / ",D1090) -> Ivan 101 / Ivan, father of tax-payer at chorion of Dobrobikeia
A1091: https://r11.eu/rdf/resource/9be368b2-f1df-4ba8-8a51-5a9da060df25 | B1091: Theodora 103 | C1091: https://pbw2016.kdl.kcl.ac.uk/ | D1091: Theodora, wife of tax-payer at Dobrobikeia | S1091: =_xlfn.CONCAT(B1091," / ",D1091) -> Theodora 103 / Theodora, wife of tax-payer at Dobrobikeia
A1092: https://r11.eu/rdf/resource/e9b59d73-4767-4bb6-8ffa-98e28acc6275 | B1092: Kyriakos 104 | C1092: https://pbw2016.kdl.kcl.ac.uk/ | D1092: Kyriakos Belaites, father of tax-payer at Dobrobikeia | S1092: =_xlfn.CONCAT(B1092," / ",D1092) -> Kyriakos 104 / Kyriakos Belaites, father of tax-payer at Dobrobikeia
A1093: https://r11.eu/rdf/resource/89959fda-92bb-4a82-8407-2d450706cac6 | B1093: Ioannes 157 | C1093: https://pbw2016.kdl.kcl.ac.uk/ | D1093: Ioannes, hegoumenos of Lavra | S1093: =_xlfn.CONCAT(B1093," / ",D1093) -> Ioannes 157 / Ioannes, hegoumenos of Lavra
A1094: https://r11.eu/rdf/resource/e3d929af-47a4-4ee7-8b1f-3ab522fbe8af | B1094: Ioannes 159 | C1094: https://pbw2016.kdl.kcl.ac.uk/ | D1094: Ioannes, hegoumenos of Phakenou on Athos | S1094: =_xlfn.CONCAT(B1094," / ",D1094) -> Ioannes 159 / Ioannes, hegoumenos of Phakenou on Athos
A1095: https://r11.eu/rdf/resource/86e2f2ae-def3-42f2-a25e-19d5c91ede57 | B1095: Ioannes 161 | C1095: https://pbw2016.kdl.kcl.ac.uk/ | D1095: Ioannes, nomikos of Hierissos | S1095: =_xlfn.CONCAT(B1095," / ",D1095) -> Ioannes 161 / Ioannes, nomikos of Hierissos
A1096: https://r11.eu/rdf/resource/95ac8ec9-e7d4-4426-b0f5-0536b95c1aa5 | B1096: Ioannes 163 | C1096: https://pbw2016.kdl.kcl.ac.uk/ | D1096: Ioannes, paroikos of Iveron | S1096: =_xlfn.CONCAT(B1096," / ",D1096) -> Ioannes 163 / Ioannes, paroikos of Iveron
A1097: https://r11.eu/rdf/resource/5761b5db-1ba5-40cb-a344-5b3435f44590 | B1097: Ioannes 168 | C1097: https://pbw2016.kdl.kcl.ac.uk/ | D1097: Ioannes Kommatares, guard at Dobista | S1097: =_xlfn.CONCAT(B1097," / ",D1097) -> Ioannes 168 / Ioannes Kommatares, guard at Dobista
A1098: https://r11.eu/rdf/resource/ca8b9fb8-a96f-456b-8b7b-1cbd1f1a62ca | B1098: Ioannes 171 | C1098: https://pbw2016.kdl.kcl.ac.uk/ | D1098: Ioannes Iatropolos, chartoularios of the oikonomeion of Hagia Sophia | S1098: =_xlfn.CONCAT(B1098," / ",D1098) -> Ioannes 171 / Ioannes Iatropolos, chartoularios of the oikonomeion of Hagia Sophia
A1099: https://r11.eu/rdf/resource/e9845aec-8e9b-4dca-a82d-6c5d10a4bf9f | B1099: Ioannes 172 | C1099: https://pbw2016.kdl.kcl.ac.uk/ | D1099: Ioannes, metropolitan of Sardis [1071] | S1099: =_xlfn.CONCAT(B1099," / ",D1099) -> Ioannes 172 / Ioannes, metropolitan of Sardis [1071]
A1100: https://r11.eu/rdf/resource/290f7185-1cd1-49c9-8ec6-344811a4a51b | B1100: Ioannes 499 | C1100: https://pbw2016.kdl.kcl.ac.uk/ | D1100: Ioannes, metropolitan of Sardis [1082] | S1100: =_xlfn.CONCAT(B1100," / ",D1100) -> Ioannes 499 / Ioannes, metropolitan of Sardis [1082]
A1101: https://r11.eu/rdf/resource/fe359160-6327-4de1-b38c-aad4116fc936 | B1101: Ioannes 173 | C1101: https://pbw2016.kdl.kcl.ac.uk/ | D1101: Ioannes, paetares and monk at Iveron | S1101: =_xlfn.CONCAT(B1101," / ",D1101) -> Ioannes 173 / Ioannes, paetares and monk at Iveron
... A2747: https://r11.eu/rdf/resource/96bb2a52-848f-49f6-b051-26514778a685 | B2747: Michael 229 | C2747: https://pbw2016.kdl.kcl.ac.uk/ | D2747: Michael Mauropous, hypatos and | S2747: =_xlfn.CONCAT(B2747," / ",D2747) -> Michael 229 / Michael Mauropous, hypatos and
A2748: witness to Patmos doc." | S2748: =_xlfn.CONCAT(B2748," / ",D2748) -> /
A2749: https://r11.eu/rdf/resource/8d45785f-b2b6-4f9a-995e-44b786a55555 | B2749: Michael 231 | C2749: https://pbw2016.kdl.kcl.ac.uk/ | D2749: Michael, presbyter of see of Leros | S2749: =_xlfn.CONCAT(B2749," / ",D2749) -> Michael 231 / Michael, presbyter of see of Leros
A2750: https://r11.eu/rdf/resource/f9f4c7a6-df8b-42bd-85da-c89059c77533 | B2750: Michael 232 | C2750: https://pbw2016.kdl.kcl.ac.uk/ | D2750: Michael, subdeacon of Hagia Sophia | S2750: =_xlfn.CONCAT(B2750," / ",D2750) -> Michael 232 / Michael, subdeacon of Hagia Sophia
A2751: https://r11.eu/rdf/resource/57de8e44-6666-4dc2-9d04-1578095907f4 | B2751: Michael 233 | C2751: https://pbw2016.kdl.kcl.ac.uk/ | D2751: Michael, oikonomos of see of Leros | S2751: =_xlfn.CONCAT(B2751," / ",D2751) -> Michael 233 / Michael, oikonomos of see of Leros
A2752: https://r11.eu/rdf/resource/96e2e59d-1730-4bec-a18b-f731867738b5 | B2752: Michael 238 | C2752: https://pbw2016.kdl.kcl.ac.uk/ | D2752: Michael Alopos, krites of the velon and of the hippodrome | S2752: =_xlfn.CONCAT(B2752," / ",D2752) -> Michael 238 / Michael Alopos, krites of the velon and of the hippodrome
A2753: https://r11.eu/rdf/resource/53461253-93a0-4d3f-a313-ca43ba4f2dd9 | B2753: Michael 242 | C2753: https://pbw2016.kdl.kcl.ac.uk/ | D2753: Michael Machetares, vestarches | S2753: =_xlfn.CONCAT(B2753," / ",D2753) -> Michael 242 / Michael Machetares, vestarches
A2754: https://r11.eu/rdf/resource/917cb831-028e-4c27-8d1c-1730e1bdc8bd | B2754: Michael 243 | C2754: https://pbw2016.kdl.kcl.ac.uk/ | D2754: Michael Laktoutoutzes, imperial notarios of sekreton of Myrelaion | S2754: =_xlfn.CONCAT(B2754," / ",D2754) -> Michael 243 / Michael Laktoutoutzes, imperial notarios of sekreton of Myrelaion
A2755: https://r11.eu/rdf/resource/a0471352-d2b4-401c-ae3c-c80f4a758530 | B2755: Michael 244 | C2755: https://pbw2016.kdl.kcl.ac.uk/ | D2755: Michael, deacon and mesokellarites of sekreton of Myrelaion | S2755: =_xlfn.CONCAT(B2755," / ",D2755) -> Michael 244 / Michael, deacon and mesokellarites of sekreton of Myrelaion
A2756: https://r11.eu/rdf/resource/9ac8966c-4674-4327-99df-f18431999f8a | B2756: Michael 245 | C2756: https://pbw2016.kdl.kcl.ac.uk/ | D2756: Michael Romanikos, imperial notarios of sekreton of the oikeiaka | S2756: =_xlfn.CONCAT(B2756," / ",D2756) -> Michael 245 / Michael Romanikos, imperial notarios of sekreton of the oikeiaka
A2757: https://r11.eu/rdf/resource/622979cf-d4d0-4a6e-b611-36575f0048d9 | B2757: Moschos 103 | C2757: https://pbw2016.kdl.kcl.ac.uk/ | D2757: Moschos, son of paroikos Strategos at Olynthos (Meander valley) | S2757: =_xlfn.CONCAT(B2757," / ",D2757) -> Moschos 103 / Moschos, son of paroikos Strategos at Olynthos (Meander valley)
A2758: https://r11.eu/rdf/resource/85921fc9-c127-44e3-b434-e3b04f1596a6 | B2758: Moschos 104 | C2758: https://pbw2016.kdl.kcl.ac.uk/ | D2758: Moschos, presbyter at Baris (Meander valley) | S2758: =_xlfn.CONCAT(B2758," / ",D2758) -> Moschos 104 / Moschos, presbyter at Baris (Meander valley)
A2759: https://r11.eu/rdf/resource/389fd072-114e-4fd4-9dab-5a774226c964 | B2759: Neophytos 105 | C2759: https://pbw2016.kdl.kcl.ac.uk/ | D2759: Neophytos, associate of Christodoulos of Patmos on Kos | S2759: =_xlfn.CONCAT(B2759," / ",D2759) -> Neophytos 105 / Neophytos, associate of Christodoulos of Patmos on Kos
A2760: https://r11.eu/rdf/resource/d44ac48c-0d96-44f9-bf0d-044e736d373c | B2760: Nikephoros 146 | C2760: https://pbw2016.kdl.kcl.ac.uk/ | D2760: Nikephoros, son of paroikos Theocharistine at Baris (Meander valley) | S2760: =_xlfn.CONCAT(B2760," / ",D2760) -> Nikephoros 146 / Nikephoros, son of paroikos Theocharistine at Baris (Meander valley)
... A10049: https://r11.eu/rdf/resource/3dd4a7b3-3f1e-445b-bd0f-1c4206363ae6 | B10049: Konstantinos 305 | C10049: https://pbw2016.kdl.kcl.ac.uk/ | D10049: Konstantinos, Constantinopolitan seal-maker | S10049: =_xlfn.CONCAT(B10049," / ",D10049) -> Konstantinos 305 / Konstantinos, Constantinopolitan seal-maker
A10050: https://r11.eu/rdf/resource/bdb52c65-cb46-47da-9908-0069df614346 | B10050: Ioannes 509 | C10050: https://pbw2016.kdl.kcl.ac.uk/ | D10050: Ioannes Triphyles, correspondent of Tzetzes | S10050: =_xlfn.CONCAT(B10050, " / ", D10050) -> Ioannes 509 / Ioannes Triphyles, correspondent of Tzetzes
A10051: https://r11.eu/rdf/resource/332d3ed1-191e-4cdb-913a-94c436baf12a | B10051: Merel 101 | C10051: https://pbw2016.kdl.kcl.ac.uk/ | D10051: Merel (?), famous father of four famous Arab chieftains | S10051: =_xlfn.CONCAT(B10051, " / ", D10051) -> Merel 101 / Merel (?), famous father of four famous Arab chieftains
A10052: https://r11.eu/rdf/resource/e893a744-115b-4092-8542-3d7f2c7ef55c | B10052: Anonyma 260 | C10052: https://pbw2016.kdl.kcl.ac.uk/ | D10052: elderly woman who was starving | S10052: =_xlfn.CONCAT(B10052, " / ", D10052) -> Anonyma 260 / elderly woman who was starving
A10053: https://r11.eu/rdf/resource/6165fb70-923d-48ff-9633-58afb4f6bfe8 | B10053: Atropius 101 | C10053: https://pbw2016.kdl.kcl.ac.uk/ | D10053: Atropius, Norman messenger sent by Tancred to Bohemond | S10053: =_xlfn.CONCAT(B10053, " / ", D10053) -> Atropius 101 / Atropius, Norman messenger sent by Tancred to Bohemond
A10054: https://r11.eu/rdf/resource/f1dc0afa-e51e-4b31-a43d-e4da8829cd5a | B10054: Garinus 101 | C10054: https://pbw2016.kdl.kcl.ac.uk/ | D10054: Garinus, Norman messenger from Tancred to Bohemond | S10054: =_xlfn.CONCAT(B10054, " / ", D10054) -> Garinus 101 / Garinus, Norman messenger from Tancred to Bohemond
A10055: https://r11.eu/rdf/resource/45302955-1c43-40bc-94de-e7e7822c0496 | B10055: Anonymus 1020 | C10055: https://pbw2016.kdl.kcl.ac.uk/ | D10055: messenger of Alexios I who tried to recall Bohemond (and Tancred) | S10055: =_xlfn.CONCAT(B10055, " / ", D10055) -> Anonymus 1020 / messenger of Alexios I who tried to recall Bohemond (and Tancred)
A10056: https://r11.eu/rdf/resource/83f41ac6-e8a1-496d-9bb7-aa493f0f5c1a | B10056: Ursinus 101 | C10056: https://pbw2016.kdl.kcl.ac.uk/ | D10056: Ursinus (Oshin?), ruler of Adana | S10056: =_xlfn.CONCAT(B10056, " / ", D10056) -> Ursinus 101 / Ursinus (Oshin?), ruler of Adana
A10057: https://r11.eu/rdf/resource/055547b1-bbb9-46b7-95de-1405d06cff4e | B10057: Garnier 101 | C10057: https://pbw2016.kdl.kcl.ac.uk/ | D10057: Garnier Marchio | S10057: =_xlfn.CONCAT(B10057, " / ", D10057) -> Garnier 101 / Garnier Marchio
A10058: https://r11.eu/rdf/resource/2de3df04-3721-4187-87f7-19810fa35d38 | B10058: Anonymus 1021 | C10058: https://pbw2016.kdl.kcl.ac.uk/ | D10058: young squire of Tancred, during the siege of Antioch | S10058: =_xlfn.CONCAT(B10058, " / ", D10058) -> Anonymus 1021 / young squire of Tancred, during the siege of Antioch
A10059: https://r11.eu/rdf/resource/eb8a3db5-48cf-4380-ae0b-8c2b99de9699 | B10059: Anonymus 1022 | C10059: https://pbw2016.kdl.kcl.ac.uk/ | D10059: herald of Alexios I, active in provisioning crusaders outside Antioch | S10059: =_xlfn.CONCAT(B10059, " / ", D10059) -> Anonymus 1022 / herald of Alexios I, active in provisioning crusaders outside Antioch
A10060: https://r11.eu/rdf/resource/0fa8b980-de7f-4dfa-96e9-3c1b91545392 | B10060: Anonymus 1023 | C10060: https://pbw2016.kdl.kcl.ac.uk/ | D10060: hermit who met Tancred outside Jerusalem | S10060: =_xlfn.CONCAT(B10060, " / ", D10060) -> Anonymus 1023 / hermit who met Tancred outside Jerusalem
A10061: https://r11.eu/rdf/resource/57c6f65d-87da-4db1-97b6-f35896a63a9b | B10061: Florina 101 | C10061: https://pbw2016.kdl.kcl.ac.uk/ | D10061: Florina of Burgundy, in the company of Sven of Denmark | S10061: =_xlfn.CONCAT(B10061, " / ", D10061) -> Florina 101 / Florina of Burgundy, in the company of Sven of Denmark
... A10113: https://r11.eu/rdf/resource/c7bba4ab-8558-4de4-b74b-f20188c7db72 | B10113: Qaraja 101 | C10113: https://pbw2016.kdl.kcl.ac.uk/ | D10113: Qaraja, ruler of Harran | S10113: =_xlfn.CONCAT(B10113, " / ", D10113) -> Qaraja 101 / Qaraja, ruler of Harran
A10114: https://r11.eu/rdf/resource/e37d8a6d-4aff-44a5-82a7-9fa3c41c828e | B10114: Jawuli 101 | C10114: https://pbw2016.kdl.kcl.ac.uk/ | D10114: Jawuli, Turkish mamluk, head of the army of Harran | S10114: =_xlfn.CONCAT(B10114," / ",D10114) -> Jawuli 101 / Jawuli, Turkish mamluk, head of the army of Harran
A10115: https://r11.eu/rdf/resource/68ec58bb-33ed-4b54-89d0-eb39da3822ce | B10115: Muhammad 110 | C10115: https://pbw2016.kdl.kcl.ac.uk/ | D10115: Muhammad al-Isfahani, deputy ruler of Harran | S10115: =_xlfn.CONCAT(B10115," / ",D10115) -> Muhammad 110 / Muhammad al-Isfahani, deputy ruler of Harran
A10116: https://r11.eu/rdf/resource/e0596a69-0be5-4ed6-9efd-f3431884bee1 | B10116: Romanos 110 | C10116: https://pbw2016.kdl.kcl.ac.uk/ | D10116: Romanos Argyros/Argyropoulos, grandfather of Romanos III | S10116: =_xlfn.CONCAT(B10116," / ",D10116) -> Romanos 110 / Romanos Argyros/Argyropoulos, grandfather of Romanos III
A10117: https://r11.eu/rdf/resource/da14b69b-e888-4208-be0c-a9578954a72f | B10117: Neophytos 107 | C10117: https://pbw2016.kdl.kcl.ac.uk/ | D10117: Neophytos, hegoumenos of Docheiariou on Athos | S10117: =_xlfn.CONCAT(B10117," / ",D10117) -> Neophytos 107 / Neophytos, hegoumenos of Docheiariou on Athos
A10118: https://r11.eu/rdf/resource/13804242-bcad-4e00-a68a-e47c29e565ff | B10118: 9970194 | C10118: https://viaf.org/ | D10118: Thurn, Hans | S10118: =_xlfn.CONCAT(B10118," / ",D10118) -> 9970194 / Thurn, Hans
A10119: https://r11.eu/rdf/resource/c2a2692e-8e03-469f-ab54-daebf6d4c0da | B10119: 316793603 | C10119: https://viaf.org/ | D10119: Papacostas, Tassos | S10119: =_xlfn.CONCAT(B10119," / ",D10119) -> 316793603 / Papacostas, Tassos
A10120: https://r11.eu/rdf/resource/035c4a4d-025c-4f09-9611-04e63fd03460 | B10120: 56683038 | C10120: https://viaf.org/ | D10120: Büttner-Wobst, Theodor | S10120: =_xlfn.CONCAT(B10120," / ",D10120) -> 56683038 / Büttner-Wobst, Theodor
A10121: https://r11.eu/rdf/resource/eeccfdd8-bd1e-4183-98fa-7caa62ab0052 | B10121: 34477027 | C10121: https://viaf.org/ | D10121: Whitby, Mary | S10121: =_xlfn.CONCAT(B10121," / ",D10121) -> 34477027 / Whitby, Mary
A10122: https://r11.eu/rdf/resource/08bccd16-7f12-4c1f-a2f5-3aeef485c037 | B10122: 41837536 | C10122: https://viaf.org/ | D10122: Canard, Marius | S10122: =_xlfn.CONCAT(B10122," / ",D10122) -> 41837536 / Canard, Marius
A10123: https://r11.eu/rdf/resource/7dd36a52-7b84-4c2e-a872-df0d3510578c | B10123: 34489376 | C10123: https://viaf.org/ | D10123: Pērpērean, Hayk | S10123: =_xlfn.CONCAT(B10123," / ",D10123) -> 34489376 / Pērpērean, Hayk
A10124: https://r11.eu/rdf/resource/50312c78-fe04-4281-ab82-24b2ce602ac3 | B10124: 316505144 | C10124: https://viaf.org/ | D10124: Andrews, Tara Lee | S10124: =_xlfn.CONCAT(B10124," / ",D10124) -> 316505144 / Andrews, Tara Lee
A10125: https://r11.eu/rdf/resource/de2ea6f5-4f54-4f90-91a8-7585a1329218 | B10125: 97996834 | C10125: https://viaf.org/ | D10125: Lemerle, Paul | S10125: =_xlfn.CONCAT(B10125," / ",D10125) -> 97996834 / Lemerle, Paul
A10126: https://r11.eu/rdf/resource/dd1d061e-4064-4034-a252-102c9f3803dc | B10126: 73866641 | C10126: https://viaf.org/ | D10126: Jeffreys, Michael J. | S10126: =_xlfn.CONCAT(B10126," / ",D10126) -> 73866641 / Jeffreys, Michael J.
A10127: https://r11.eu/rdf/resource/a5f30890-1766-40bb-a1be-933ab0f2aaff | B10127: 253347413 | C10127: https://viaf.org/ | D10127: Karágiṓrgou, ́Olga | S10127: =_xlfn.CONCAT(B10127," / ",D10127) -> 253347413 / Karágiṓrgou, ́Olga
A10128: https://r11.eu/rdf/resource/7964c0c3-8452-4a1c-b0a5-22c06ab0f6a7 | B10128: 46774901 | C10128: https://viaf.org/ | D10128: Reinsch, Diether Roderich | S10128: =_xlfn.CONCAT(B10128," / ",D10128) -> 46774901 / Reinsch, Diether Roderich
A10129: https://r11.eu/rdf/resource/9cb14a2e-a0d7-4072-8fbb-606cbb23a2e6 | B10129: 51705268 | C10129: https://viaf.org/ | D10129: Kambylis, Athanasios | S10129: =_xlfn.CONCAT(B10129," / ",D10129) -> 51705268 / Kambylis, Athanasios
... A10153: https://r11.eu/rdf/resource/0ec222fe-2577-4f77-9387-6de787dafcb1 | B10153: 42986884 | C10153: https://viaf.org/ | D10153: Troupeau, Gérard | S10153: =_xlfn.CONCAT(B10153," / ",D10153) -> 42986884 / Troupeau, Gérard
A10154: https://r11.eu/rdf/resource/fc9993ce-9d20-4328-97ec-331ca7995374 | B10154: 236145542536996640148 | C10154: https://viaf.org/ | D10154: Osti, Letizia | S10154: =_xlfn.CONCAT(B10154," / ",D10154) -> 236145542536996640148 / Osti, Letizia
A10155: https://r11.eu/rdf/resource/7a0b3d4a-6db8-4e6d-a065-d4fc83b3c896 | B10155: 78568758 | C10155: https://viaf.org/ | D10155: Munt, Harry | S10155: =_xlfn.CONCAT(B10155," / ",D10155) -> 78568758 / Munt, Harry
A10156: https://r11.eu/rdf/resource/5aa7f333-553e-4f84-8b0c-79f8986d02b8 | B10156: 51691081 | C10156: https://viaf.org/ | D10156: Huygens, R.B.C. | S10156: =_xlfn.CONCAT(B10156," / ",D10156) -> 51691081 / Huygens, R.B.C.
...

Sheet Author groups
A1: WissKI ID | B1: Group identifier | C1: Group member
A2: https://r11.eu/rdf/resource/f13bc456-2d72-449a-9595-5acbdf8a4ba4 | B2: Athanasios, hegoumenos of Bouleuteria on Athos; Theodosios, monk and presbyter on Athos | C2: Athanasios 104 / Athanasios, hegoumenos of Bouleuteria on Athos
A3: https://r11.eu/rdf/resource/f13bc456-2d72-449a-9595-5acbdf8a4ba4 | B3: Athanasios, hegoumenos of Bouleuteria on Athos; Theodosios, monk and presbyter on Athos | C3: Theodosios 113 / Theodosios, monk and presbyter on Athos
A4: https://r11.eu/rdf/resource/9754a82b-f2bd-42ec-80e8-bef54e40def9 | B4: Athanasios, hegoumenos of Vatopedi on Athos; Georgios III Hagiorites/Mt'ac'mindeli, hegoumenos of Iveron; Ioannes, hegoumenos of Zygos on Athos; Neophytos, hegoumenos of Lavra on Athos; Theophylaktos, protos of Mount Athos | C4: Athanasios 102 / Athanasios, hegoumenos of Vatopedi on Athos
A5: https://r11.eu/rdf/resource/9754a82b-f2bd-42ec-80e8-bef54e40def9 | B5: Athanasios, hegoumenos of Vatopedi on Athos; Georgios III Hagiorites/Mt'ac'mindeli, hegoumenos of Iveron; Ioannes, hegoumenos of Zygos on Athos; Neophytos, hegoumenos of Lavra on Athos; Theophylaktos, protos of Mount Athos | C5: Georgios 132 / Georgios III Hagiorites/Mt'ac'mindeli, hegoumenos of Iveron
A6: https://r11.eu/rdf/resource/92acb860-00df-4ddb-b69f-7c8cc4a7e776 | B6: Athanasios, hegoumenos of Vatopedi on Athos; Georgios III Hagiorites/Mt'ac'mindeli, hegoumenos of Iveron; Ioannes, hegoumenos of Zygos on Athos; Neophytos, hegoumenos of Lavra on Athos; Theophylaktos, protos of Mount Athos | C6: Ioannes 158 / Ioannes, hegoumenos of Zygos on Athos
A7: https://r11.eu/rdf/resource/92acb860-00df-4ddb-b69f-7c8cc4a7e776 | B7: Athanasios, hegoumenos of Vatopedi on Athos; Georgios III Hagiorites/Mt'ac'mindeli, hegoumenos of Iveron; Ioannes, hegoumenos of Zygos on Athos; Neophytos, hegoumenos of Lavra on Athos; Theophylaktos, protos of Mount Athos | C7: Neophytos 113 / Neophytos, hegoumenos of Lavra on Athos
A8: https://r11.eu/rdf/resource/9ff45a88-b859-468c-9115-7663e3b5d0b1 | B8: Athanasios, hegoumenos of Vatopedi on Athos; Georgios III Hagiorites/Mt'ac'mindeli, hegoumenos of Iveron; Ioannes, hegoumenos of Zygos on Athos; Neophytos, hegoumenos of Lavra on Athos; Theophylaktos, protos of Mount Athos | C8: Theophylaktos 117 / Theophylaktos, protos of Mount Athos
A9: https://r11.eu/rdf/resource/9ff45a88-b859-468c-9115-7663e3b5d0b1 | B9: Bartholomaios, monk and scribe at Esphigmenou on Athos; Theoktistos, hegoumenos of Esphigmenou and protos of Athos | C9: Theoktistos 107 / Theoktistos, hegoumenos of Esphigmenou and protos of Athos
A10: https://r11.eu/rdf/resource/3e963f4e-4672-4b9b-a488-88ca46aec3de | B10: Bartholomaios, monk and scribe at Esphigmenou on Athos; Theoktistos, hegoumenos of Esphigmenou and protos of Athos | C10: Bartholomaios 108 / Bartholomaios, monk and scribe at Esphigmenou on Athos
A11: https://r11.eu/rdf/resource/3e963f4e-4672-4b9b-a488-88ca46aec3de | B11: Bollig, I; de Lagarde, P | C11: 42584340 / Bollig, I
A12: https://r11.eu/rdf/resource/3e963f4e-4672-4b9b-a488-88ca46aec3de | B12: Bollig, I; de Lagarde, P | C12: 71399627 / de Lagarde, P
... A65: https://r11.eu/rdf/resource/b4d4c2b8-6a91-406e-9b2f-73d0d06bb33b | B65: Kale, wife of Symbatios Pakourianos; Eleutherios, notarios attached to the Hagioi Tessarakonta | C65: Eleutherios 101 / Eleutherios, notarios attached to the Hagioi Tessarakonta
B66: Kale, wife of Symbatios Pakourianos; Ioannes Phorites, notary at Constantinople | C66: Kale 102 / Kale, wife of Symbatios Pakourianos
B67: Kale, wife of Symbatios Pakourianos; Ioannes Phorites, notary at Constantinople | C67: Ioannes 190 / Ioannes Phorites, notary at Constantinople
A68: https://r11.eu/rdf/resource/b4d4c2b8-6a91-406e-9b2f-73d0d06bb33b | B68: Kurtz, Eduard; Drexl, Franz | C68: 59840374 / Kurtz, Eduard
A69: https://r11.eu/rdf/resource/b4d4c2b8-6a91-406e-9b2f-73d0d06bb33b | B69: Kurtz, Eduard; Drexl, Franz | C69: 35433472 / Drexl, Franz
A70: https://r11.eu/rdf/resource/72721472-d75a-4706-8735-541ed4a35362 | B70: Lefort, Jacques; Oikonomidès, Nicolas; Papachryssanthou, Denise; Kravari, Vassiliki; Métrévéli, Hélène | C70: 93206983 / Papachryssanthou, Denise
A71: https://r11.eu/rdf/resource/72721472-d75a-4706-8735-541ed4a35362 | B71: Lefort, Jacques; Oikonomidès, Nicolas; Papachryssanthou, Denise; Kravari, Vassiliki; Métrévéli, Hélène | C71: 71393851 / Lefort, Jacques
A72: https://r11.eu/rdf/resource/50f2406f-2cf5-4646-86dc-36aa01937a68 | B72: Lefort, Jacques; Oikonomidès, Nicolas; Papachryssanthou, Denise; Kravari, Vassiliki; Métrévéli, Hélène | C72: 14774616 / Oikonomidès, Nicolas
A73: https://r11.eu/rdf/resource/50f2406f-2cf5-4646-86dc-36aa01937a68 | B73: Lefort, Jacques; Oikonomidès, Nicolas; Papachryssanthou, Denise; Kravari, Vassiliki; Métrévéli, Hélène | C73: 31154757 / Kravari, Vassiliki
A74: https://r11.eu/rdf/resource/110d79e2-b7a2-4512-b242-1044d822495f | B74: Lefort, Jacques; Oikonomidès, Nicolas; Papachryssanthou, Denise; Kravari, Vassiliki; Métrévéli, Hélène | C74: 59302266 / Métrévéli, Hélène
A75: https://r11.eu/rdf/resource/110d79e2-b7a2-4512-b242-1044d822495f | B75: Lefort, Jacques; Oikonomidès, Nicolas; Papachryssanthou, Denise; Métrévéli, Hélène | C75: 93206983 / Papachryssanthou, Denise
A76: https://r11.eu/rdf/resource/44d70e9b-9b7d-47bc-86ab-10c04ccfb2af | B76: Lefort, Jacques; Oikonomidès, Nicolas; Papachryssanthou, Denise; Métrévéli, Hélène | C76: 71393851 / Lefort, Jacques
A77: https://r11.eu/rdf/resource/44d70e9b-9b7d-47bc-86ab-10c04ccfb2af | B77: Lefort, Jacques; Oikonomidès, Nicolas; Papachryssanthou, Denise; Métrévéli, Hélène | C77: 14774616 / Oikonomidès, Nicolas
A78: https://r11.eu/rdf/resource/797349c0-5e45-481b-bce9-92b2720a1b16 | B78: Lefort, Jacques; Oikonomidès, Nicolas; Papachryssanthou, Denise; Métrévéli, Hélène | C78: 59302266 / Métrévéli, Hélène
A79: https://r11.eu/rdf/resource/797349c0-5e45-481b-bce9-92b2720a1b16 | B79: Lemerle, Paul; Dagron, Gilbert; Ćirković, Sima M. | C79: 97996834 / Lemerle, Paul
... A149: https://r11.eu/rdf/resource/6527d8610385c | B149: Theodoulos, bishop of Ezoba; Leon Tzainos, protopapas of Ezoba bishopric; Ioannes, nomikos of Chrysopolis | C149: Leon 126 / Leon Tzainos, protopapas of Ezoba bishopric
B150: Theodoulos, bishop of Ezoba; Leon Tzainos, protopapas of Ezoba bishopric; Ioannes, nomikos of Chrysopolis | C150: Ioannes 183 / Ioannes, nomikos of Chrysopolis
B151: Theoktistos, hegoumenos of Esphigmenou and protos of Athos; Iakobos, monk and presbyter on Athos | C151: Theoktistos 107 / Theoktistos, hegoumenos of Esphigmenou and protos of Athos
B152: Theoktistos, hegoumenos of Esphigmenou and protos of Athos; Iakobos, monk and presbyter on Athos | C152: Iakobos 106 / Iakobos, monk and presbyter on Athos
B153: Vranoúsīs, Léandros I.; Nystazopoúlou-Pelekídou, María | C153: 51818933 / Vranoúsīs, Léandros I.
B154: Vranoúsīs, Léandros I.; Nystazopoúlou-Pelekídou, María | C154: 44710829 / Nystazopoúlou-Pelekídou, María
B155: Whitby, Mary; Jeffreys, Michael J.; Karágiṓrgou, ́Olga | C155: 34477027 / Whitby, Mary
B156: Whitby, Mary; Jeffreys, Michael J.; Karágiṓrgou, ́Olga | C156: 73866641 / Jeffreys, Michael J.
B157: Whitby, Mary; Jeffreys, Michael J.; Karágiṓrgou, ́Olga | C157: 253347413 / Karágiṓrgou, ́Olga
B158: Živojinović, Mirjana; Kravari, Vassiliki; Giros, Christophe | C158: 31154757 / Kravari, Vassiliki
B159: Živojinović, Mirjana; Kravari, Vassiliki; Giros, Christophe | C159: 24760554 / Giros, Christophe
B160: Živojinović, Mirjana; Kravari, Vassiliki; Giros, Christophe | C160: 14898912 / Živojinović, Mirjana
B161: ̓Orlándos, ̓Anastásios K.; Vranoúsīs, Léandros I. | C161: 100182818 / ̓Orlándos, ̓Anastásios K.
... B181: Kaldellis, Anthony; Polémīs, Dīmī́trios I. | C181: 15182978 / Polémīs, Dīmī́trios I.

Sheet Actor groups
A1: Group identifier | B1: Group member | C1: Authority | D1: Authority group | E1: Based on | F1: Source text/publication | G1: Source text/reference | H1: Source text/excerpt
A2: Armenian attackers of Berkri | B2: T3 Gandzi / Ganji, Armenian išxan | C2: T2 Mattheos / Matthew of Edessa | F2: Chronicle of Matthew | G2: I.65 | H2: Գանձի և ամենայն զօրքն իւր անցին ի քաղաքին Բերկրի

Sheet Places
A1: PBW key | B1: Reference name | C1: Pleiades ID | D1: Geonames ID | E1: Wikidata ID | F1: Location coordinates | G1: Place type | H1: Earliest existence | I1: Latest existence | J1: Succeeds place | K1: Incorporates place | L1: Had population group | M1: Authority | N1: Authority group | O1: Based on | P1: Source text/publication | Q1: Source text/reference | R1: Source text/excerpt
A2: 10518 | B2: 'Arqa (Syria) | C2: https://pleiades.stoa.org/places/668198 | M2: 44335536 / Roueché, Charlotte
A3: 8938 | B3: Abchasia | D3: https://www.geonames.org/6643410 | M3: 44335536 / Roueché, Charlotte
A4: 9674 | B4: Abroba (Bulgaria) | D4: https://www.geonames.org/725520 | M4: 44335536 / Roueché, Charlotte
A5: 8966 | B5: Abydos | C5: https://pleiades.stoa.org/places/501325 | M5: 44335536 / Roueché, Charlotte
A6: 10946 | B6: Acerenza | C6: https://pleiades.stoa.org/places/442436 | M6: 44335536 / Roueché, Charlotte
A7: 10244 | B7: Acheloos | D7: https://www.geonames.org/736832 | M7: 44335536 / Roueché, Charlotte
A8: 9850 | B8: Achyraous | D8: https://www.geonames.org/322165 | M8: 44335536 / Roueché, Charlotte
A9: 10383 | B9: Acre | C9: https://pleiades.stoa.org/places/678010 | M9: 44335536 / Roueché, Charlotte
A10: 11282 | B10: Acre: Church of the Holy Cross | C10: https://pleiades.stoa.org/places/678010 | M10: 44335536 / Roueché, Charlotte
A11: 11065 | B11: Adada | C11: https://pleiades.stoa.org/places/638733 | M11: 44335536 / Roueché, Charlotte
A12: 9262 | B12: Adana | C12: https://pleiades.stoa.org/places/648548 | M12: 44335536 / Roueché, Charlotte
A13: 9978 | B13: Adramyttion | C13: https://pleiades.stoa.org/places/550403 | M13: 44335536 / Roueché, Charlotte
A14: 10000 | B14: Adraneia | C14: https://pleiades.stoa.org/places/609395 | M14: 44335536 / Roueché, Charlotte
A15: 10356 | B15: Adrianople (Lykaonia) | C15: https://pleiades.stoa.org/places/638852 | M15: 44335536 / Roueché, Charlotte
A16: 9452 | B16: Adrianople (Thrace) | C16: https://pleiades.stoa.org/places/5014275 | M16: 44335536 / Roueché, Charlotte
A17: 11416 | B17: Adrianople (Thrace): bridge over three rivers | C17: https://pleiades.stoa.org/places/5014275 | M17: 44335536 / Roueché, Charlotte
A18: 11344 | B18: Adrianople (Thrace): House of Silvestros | C18: https://pleiades.stoa.org/places/5014275 | M18: 44335536 / Roueché, Charlotte
A19: 9541 | B19: Adrianople (Thrace): Theometor | C19: https://pleiades.stoa.org/places/5014275 | M19: 44335536 / Roueché, Charlotte
A20: 9870 | B20: Aegean Sea | C20: https://pleiades.stoa.org/places/560221 | D20: https://www.geonames.org/265695 | M20: 44335536 / Roueché, Charlotte
A21: 11422 | B21: Aeironesion (Sazan island) | C21: https://pleiades.stoa.org/places/481981 | M21: 44335536 / Roueché, Charlotte
A22: 9558 | B22: Aetos (Macedonia) | D22: https://www.geonames.org/736989 | M22: 44335536 / Roueché, Charlotte
A23: 10030 | B23: Agrai | C23: https://pleiades.stoa.org/places/638735 | M23: 44335536 / Roueché, Charlotte
A24: 11421 | B24: Aigina | C24: https://pleiades.stoa.org/places/579844 | M24: 44335536 / Roueché, Charlotte
A25: 9160 | B25: Ainos | C25: https://pleiades.stoa.org/places/501337 | M25: 44335536 / Roueché, Charlotte
A26: 9979 | B26: Akmoneia | C26: https://pleiades.stoa.org/places/609293 | M26: 44335536 / Roueché, Charlotte
A27: 10445 | B27: Akrasos | C27: https://pleiades.stoa.org/places/554181 | M27: 44335536 / Roueché, Charlotte
A28: 11420 | B28: Akrokorinthos | C28: https://pleiades.stoa.org/places/570059 | M28: 44335536 / Roueché, Charlotte
A29: 11535 | B29: Akrokos (Phrygia) | C29: https://pleiades.stoa.org/places/609296 | M29: 44335536 / Roueché, Charlotte
A30: 11554 | B30: Akronios (Phrygia) | C30: https://pleiades.stoa.org/places/612330 | M30: 44335536 / Roueché, Charlotte
A31: 10549 | B31: al-Arish | C31: https://pleiades.stoa.org/places/688016 | M31: 44335536 / Roueché, Charlotte
A32: 11750 | B32: al-Haditha (Iraq) | D32: https://www.geonames.org/96309 | M32: 44335536 / Roueché, Charlotte
A33: 11744 | B33: al-Hilla | C33: https://pleiades.stoa.org/places/434655355 | M33: 44335536 / Roueché, Charlotte
A34: 9966 | B34: Alabanda | C34: https://pleiades.stoa.org/places/599479 | M34: 44335536 / Roueché, Charlotte
A35: 10686 | B35: Albania (Caucasus) | C35: https://pleiades.stoa.org/places/863731 | M35: 44335536 / Roueché, Charlotte
A36: 11563 | B36: Albano (not far from Rome) | D36: https://www.geonames.org/3183356 | M36: 44335536 / Roueché, Charlotte
A37: 10512 | B37: Albara (Syria) | D37: https://www.geonames.org/173999 | M37: 44335536 / Roueché, Charlotte
A38: 11284 | B38: Aleppo | C38: https://pleiades.stoa.org/places/658409 | M38: 44335536 / Roueché, Charlotte
A39: 11576 | B39: Aleppo: Great Mosque | C39: https://pleiades.stoa.org/places/658409 | D39: https://www.geonames.org/7745901 | M39: 44335536 / Roueché, Charlotte
A40: 11286 | B40: Aleppo: Palace | C40: https://pleiades.stoa.org/places/658409 | M40: 44335536 / Roueché, Charlotte
A41: 9377 | B41: Alexandretta | C41: https://pleiades.stoa.org/places/658371 | M41: 44335536 / Roueché, Charlotte
A42: 8968 | B42: Alexandria | C42: https://pleiades.stoa.org/places/727070 | M42: 44335536 / Roueché, Charlotte
A43: 11542 | B43: Alexiopolis (near Philippopolis) | C43: https://pleiades.stoa.org/places/216792 | M43: 44335536 / Roueché, Charlotte
A44: 9880 | B44: Alia | C44: https://pleiades.stoa.org/places/462090 | M44: 44335536 / Roueché, Charlotte
A45: 10127 | B45: Amalfi | C45: https://pleiades.stoa.org/places/432670 | M45: 44335536 / Roueché, Charlotte
A46: 9140 | B46: Amaseia | C46: https://pleiades.stoa.org/places/857018 | M46: 44335536 / Roueché, Charlotte
A47: 9281 | B47: Amaseia: Marmarote | C47: https://pleiades.stoa.org/places/857018 | M47: 44335536 / Roueché, Charlotte
A48: 9184 | B48: Amastris | C48: https://pleiades.stoa.org/places/599489 | M48: 44335536 / Roueché, Charlotte
A49: 9967 | B49: Amazon | C49: https://pleiades.stoa.org/places/599489 | M49: 44335536 / Roueché, Charlotte
A50: 10250 | B50: Amida | C50: https://pleiades.stoa.org/places/874298 | M50: 44335536 / Roueché, Charlotte
A51: 11142 | B51: Amiens | C51: https://pleiades.stoa.org/places/109321 | M51: 44335536 / Roueché, Charlotte
A52: 9825 | B52: Amisos | C52: https://pleiades.stoa.org/places/857024 | D52: https://www.geonames.org/740264 | M52: 44335536 / Roueché, Charlotte
A53: 9122 | B53: Amorion | C53: https://pleiades.stoa.org/places/609302 | M53: 44335536 / Roueché, Charlotte
A54: 9562 | B54: Amphipolis (Macedonia) | C54: https://pleiades.stoa.org/places/501347 | M54: 44335536 / Roueché, Charlotte
A55: 11749 | B55: Anah (Iraq) | C55: https://pleiades.stoa.org/places/893936 | M55: 44335536 / Roueché, Charlotte
A56: 10841 | B56: Anaia | C56: https://pleiades.stoa.org/places/599490 | M56: 44335536 / Roueché, Charlotte
A57: 8970 | B57: Anakouphia | C57: https://pleiades.stoa.org/places/857358 | M57: 44335536 / Roueché, Charlotte
A58: 11039 | B58: Anakoupia | C58: https://pleiades.stoa.org/places/857358 | M58: 44335536 / Roueché, Charlotte
A59: 9433 | B59: Anaplous (on Bosporos) | C59: https://pleiades.stoa.org/places/520958 | M59: 44335536 / Roueché, Charlotte
B60: Anatolikon | E60: https://www.wikidata.org/wiki/Q488230 | G60: Theme | M60: 60972463 / Papaioannou, Stratis | P60: Epistulae. Edited by S. Papaioannou. Berlin-Boston: De Gruyter (2019), p. 707
A61: 9760 | B61: Anazarbos | C61: https://pleiades.stoa.org/places/658378 | M61: 44335536 / Roueché, Charlotte
A62: 11688 | B62: Anbar | C62: https://pleiades.stoa.org/places/894043 | M62: 44335536 / Roueché, Charlotte
A63: 9296 | B63: Anchialos | C63: https://pleiades.stoa.org/places/216702 | M63: 44335536 / Roueché, Charlotte
A64: 10303 | B64: Ancona | C64: https://pleiades.stoa.org/places/413014 | M64: 44335536 / Roueché, Charlotte
A65: 11609 | B65: Andechs (Bavaria) | D65: https://www.geonames.org/2956253 | M65: 44335536 / Roueché, Charlotte
A66: 11568 | B66: Andida | C66: https://pleiades.stoa.org/places/40039 | M66: 44335536 / Roueché, Charlotte
A67: 9857 | B67: Andrapa | C67: https://pleiades.stoa.org/places/857028 | M67: 44335536 / Roueché, Charlotte
A68: 10323 | B68: Andria | D68: https://www.geonames.org/3183072 | M68: 44335536 / Roueché, Charlotte
A69: 9961 | B69: Andros | C69: https://pleiades.stoa.org/places/589693 | M69: 44335536 / Roueché, Charlotte
A70: 9031 | B70: Ani | C70: https://pleiades.stoa.org/places/874322 | M70: 44335536 / Roueché, Charlotte
A71: 9466 | B71: Ani: Acropolis | C71: https://pleiades.stoa.org/places/874322 | M71: 44335536 / Roueché, Charlotte
A72: 8960 | B72: Ankyra | C72: https://pleiades.stoa.org/places/619103 | M72: 44335536 / Roueché, Charlotte
A73: 9197 | B73: Ankyra (Phrygia) | C73: https://pleiades.stoa.org/places/609305 | M73: 44335536 / Roueché, Charlotte
A74: 11406 | B74: Antandros | C74: https://pleiades.stoa.org/places/550433 | M74: 44335536 / Roueché, Charlotte
A75: 11467 | B75: Antartus | C75: https://pleiades.stoa.org/places/668190 | M75: 44335536 / Roueché, Charlotte
A76: 9472 | B76: Antioch (on the Orontes) | C76: https://pleiades.stoa.org/places/658381 | M76: 44335536 / Roueché, Charlotte
A77: 10462 | B77: Antioch (Pisidia) | C77: https://pleiades.stoa.org/places/609307 | M77: 44335536 / Roueché, Charlotte
A78: 11620 | B78: Antioch on the Meander | C78: https://pleiades.stoa.org/places/638748 | M78: 44335536 / Roueché, Charlotte
A79: 9540 | B79: Antioch: Acropolis | C79: https://pleiades.stoa.org/places/658381 | M79: 44335536 / Roueché, Charlotte
A80: 11586 | B80: Antioch: Bab Faris (Knight's Gate) | C80: https://pleiades.stoa.org/places/658381 | M80: 44335536 / Roueché, Charlotte
... A115: 9041 | B115: Arkadioupolis (Thrace) | C115: https://pleiades.stoa.org/places/511185 | M115: 44335536 / Roueché, Charlotte
A116: 11583 | B116: Armanaz | D116: https://www.geonames.org/172988 | M116: 44335536 / Roueché, Charlotte
A117: 8954 | B117: Armenia | C117: https://pleiades.stoa.org/places/874350 | M117: 44335536 / Roueché, Charlotte
B118: Armeniakon | E118: k | M118: Michael 61 / Michael Psellos (named Konstantinos till tonsure in 1054) | P118: Epistulae. Edited by S. Papaioannou. Berlin-Boston: De Gruyter (2019), pp. 423-434 | Q118: p. 423, l. 14 | R118: ὁπηνίκα τὸν Ἀρμενιακὸν ὁ ὁμώνυμός
A119: 11600 | B119: Arras | C119: https://pleiades.stoa.org/places/109194 | M119: 44335536 / Roueché, Charlotte
A120: 10085 | B120: Arsinoe (Cyprus) | C120: https://pleiades.stoa.org/places/707484 | M120: 44335536 / Roueché, Charlotte
A121: 10531 | B121: Arsuf | C121: https://pleiades.stoa.org/places/678025 | M121: 44335536 / Roueché, Charlotte
A122: 11131 | B122: Arta | C122: https://pleiades.stoa.org/places/530794 | M122: 44335536 / Roueché, Charlotte
A123: 10657 | B123: Artzike (lake Van) | D123: https://www.geonames.org/315530 | M123: 44335536 / Roueché, Charlotte
A124: 9062 | B124: Artzn | D124: https://www.geonames.org/309513 | M124: 44335536 / Roueché, Charlotte
A125: 10562 | B125: Arzghan | D125: https://www.geonames.org/172876 | M125: 44335536 / Roueché, Charlotte
A126: 10945 | B126: Ascoli | C126: https://pleiades.stoa.org/places/413036 | M126: 44335536 / Roueché, Charlotte
A127: 9510 | B127: Askalon | C127: https://pleiades.stoa.org/places/687839 | M127: 44335536 / Roueché, Charlotte
A128: 9196 | B128: Asmosaton | C128: https://pleiades.stoa.org/places/874354 | M128: 44335536 / Roueché, Charlotte
A129: 9968 | B129: Aspendos | C129: https://pleiades.stoa.org/places/638776 | M129: 44335536 / Roueché, Charlotte
A130: 9982 | B130: Assos | C130: https://pleiades.stoa.org/places/550463 | M130: 44335536 / Roueché, Charlotte
A131: 10550 | B131: Atharib | D131: https://www.geonames.org/174030 | M131: 44335536 / Roueché, Charlotte
A132: 8953 | B132: Athens | C132: https://pleiades.stoa.org/places/579885 | M132: 44335536 / Roueché, Charlotte
A133: 9559 | B133: Athos, Mount | C133: https://pleiades.stoa.org/places/501365 | M133: 44335536 / Roueché, Charlotte
A134: 10163 | B134: Athos: Akindynou | C134: https://pleiades.stoa.org/places/501365 | M134: 44335536 / Roueché, Charlotte
...

Sheet Text publications
A1: Text identifier | B1: Text name | C1: Creation date | D1: Author | E1: Author group | F1: Edition | G1: Editor | H1: Editor group | I1: Authority | J1: Authority group | K1: Source text/publication | L1: Source text/reference | M1: Source text/excerpt
A2: Albert of Aachen | B2: Historia Hierosolymitana | D2: Albert 26101 / Albert of Aachen | F2: Historia Ierosolimitana, History of the Journey to Jerusalem, Oxford 2007 | G2: 93497875 / Edgington, Susan B. | I2: Albert 26101 / Albert of Aachen | K2: Albert of Aachen | L2: I.1
A3: Alexios Stoudites | B3: The Decrees of Alexios Stoudites | D3: Alexios 11 / Alexios Stoudites, patriarch of Constantinople | F3: Erlasse des Patriarchen von Konstantinopel Alexios Studites, Kiel: Festschrift der Universität Kiel, 1911 | G3: 37668465 / Ficker, Gerhard | I3: 37668465 / Ficker, Gerhard | K3: Alexios Stoudites | L3: title, p. 4
A4: Anna Komnene | B4: Alexias | D4: Anna 62 / Anna Komnene, daughter of Alexios I and historian | F4: Annae Comnenae Alexias, Corpus fontium historiae Byzantinae 40/1, Berlin – New York 2001 | H4: Reinsch, Diether Roderich; Kambylis, Athanasios | I4: Anna 62 / Anna Komnene, daughter of Alexios I and historian | K4: Anna Komnene | L4: 6.17-21
A5: Annales Barenses | B5: Annales Barenses | F5: Annales Barenses, Monumenta Germaniae historica, Scriptores V, Hanover 1844, 52-56 | G5: 54236315 / Pertz, Georg Heinrich | I5: 54236315 / Pertz, Georg Heinrich | K5: Annales Barenses
A6: Anonymus Barensis | B6: Anonymus Barensis | D6: 13129565 / Anonymus Barensis | F6: Anonymi Barensis Chronicon, Rerum Italicarum scriptores V, Milan 1724, 147-156 | G6: 68933348 / Muratori, Lodovico Antonio | I6: 68933348 / Muratori, Lodovico Antonio | K6: Anonymus Barensis
A7: Aristakes | B7: Patmutʿiwn | D7: Aristakes 101 / Aristakes Lastivertc'i / of Lastivert, Armenian historian | F7: Récit des malheurs de la nation arménienne, Brussels 1973 | H7: Canard, Marius; Pērpērean, Hayk | I7: Aristakes 101 / Aristakes Lastivertc'i / of Lastivert, Armenian historian | K7: Aristakes | L7: 142.1-145.30 (129-132)
A8: Attaleiates: Diataxis | B8: Diataxis | D8: Michael 202 / Michael Attaleiates | F8: “La diataxis de Michel Attaliate”, Revue des études byzantines 39 (1981) 5-143 | G8: 231073465 / Gautier, Paul | I8: Michael 202 / Michael Attaleiates | K8: Attaleiates: Diataxis | L8: 17.1, 83.1087-90
A9: Attaleiates: History | B9: Attaliatae Historia | D9: Michael 202 / Michael Attaleiates | F9: Michaelis Attaliatae Historia, Corpus scriptorum historiae Byzantinae 3, Bonn 1853 | H9: Brunet de Presle, Wladimir; Bekker, Immanuel | I9: Michael 202 / Michael Attaleiates | K9: Attaleiates: History | L9: 322.10-19 / 229.17-24
A10: Basilakios, Orationes et epistulae | B10: Basilacae Orationes et epistolae | D10: Nikephoros 17003 / Nikephoros Basilakios, writer involved in doctrinal disputes | F10: Nicephori Basilacae Orationes et epistolae, Leipzig 1984 | G10: 27081575 / Garzya, Antonio | I10: Nikephoros 17003 / Nikephoros Basilakios, writer involved in doctrinal disputes | K10: Basilakios, Orationes et epistulae | L10: 1.1-9.22
A11: Boilas | B11: Testament of Boilas | D11: Eustathios 105 / Eustathios Boilas | F11: “Le testament d’Eustathios Boïlas (Avril 1059)”, Cinq études sur le XIe siècle byzantin, Paris (1977) 15-63 | G11: 97996834 / Lemerle, Paul | I11: Eustathios 105 / Eustathios Boilas | K11: Boilas | L11: 29.283-284
A12: Bryennios | B12: Hyle historias | D12: Nikephoros 117 / Nikephoros Bryennios, kaisar, husband of Anna Komnene | F12: Nicéphore Bryennios: Histoire. Introduction, texte, traduction et notes, Brussels 1975 | G12: 231073465 / Gautier, Paul | I12: Nikephoros 117 / Nikephoros Bryennios, kaisar, husband of Anna Komnene | K12: Bryennios | L12: 71.26-73.11
A13: Christophoros of Mitylene | B13: Poems | D13: Christophoros 13102 / Christophoros of Mitylene, poet | F13: Die Gedichte des Christophoros Mitylenaios, Leipzig 1903 | G13: 59840374 / Kurtz, Eduard | I13: 59840374 / Kurtz, Eduard | K13: Christophoros of Mitylene | L13: title, p. 1
A14: Christos Philanthropos, note | F14: “Commémoraisons des Comnènes dans le typikon liturgique du monastère du Christ Philanthrope (ms. Panaghia Kamariotissa 29)”, Revue des études Byzantines 63 (2005), 41-69 | H14: Rízou-Kouroúpou, Matoúla; Vannier, Jean-François | J14: Rízou-Kouroúpou, Matoúla; Vannier, Jean-François | K14: Christos Philanthropos, note
A15: Chronicle of Matthew | B15: Zhamanakagrut‘iwn | D15: T2 Mattheos / Matthew of Edessa | F15: Žamanakagrutʿiwn, Vałaršapat, 1898 | H15: Melikʻ-Adamyan, Mambre; Ter-Mikʻayelyan, Nerses | I15: T2 Mattheos / Matthew of Edessa | K15: Chronicle of Matthew | L15: II.i | M15: Եւ վասն այսորիկ ես Մատթէոս Ուռհայեցի և վանական` զաշխատութեան զգործս իմ ոչինչ համարեցայ
A16: Chronicle of Matthew (Dostourian) | B16: Armenia and the Crusades | D16: T2 Mattheos / Matthew of Edessa | F16: Armenia and the Crusades: The Chronicle of Matthew of Edessa. Translated by Ara Edmond Dostourian. Second edition. Belmont, MA: Armenian Heritage Press, 2014. | G16: 77829335 / Dostourian, Ara Edmond | I16: 77829335 / Dostourian, Ara Edmond | K16: Chronicle of Matthew (Dostourian) | L16: Introduction
A17: Chrysobull of 1079 | F17: “Un chrysobulle de Nicéphore Botaneiatès à souscription synodale”, Byzantion 29 (1959) 29-41 | G17: 88739139 / Gouillard, Jean | I17: 88739139 / Gouillard, Jean | K17: Chrysobull of 1079
A18: Clement III to Basileios of Calabria | B18: Clement III to Basileios of Calabria | D18: Klemes 23 / antipope Clement III (Guibert of Ravenna) | F18: “Die Unionsverhandlungen zwischen Kaiser Alexios I. und Papst Urban II. im Jahre 1089″, Byzantinische Zeitschrift 28 (1928), 59-60 | G18: 7485449 / Holtzmann, Walther | I18: 51999624 / Ryder, Judith R. | K18: Clement III to Basileios of Calabria | L18: 59.1-60.5
A19: Dionysiou | B19: Deed of guarantee of Konstantinos Phasoulos | D19: Ioannes 411 / Ioannes, klerikos of Hagia Sophia (of Thessalonike) and nomikos | F19: Actes de Dionysiou, Archives de l’Athos IV, Paris 1968, pp. 35-42 | G19: 14774616 / Oikonomidēs, Nicolas | I19: 316793603 / Papacostas, Tassos | K19: Dionysiou | L19: 41.40-42.50
A20: Docheiariou 1 | B20: Hypomnema of Konstantinos Kamateros | D20: Konstantinos 256 / Konstantinos Kamateros, krites of Boleron, Strymon and Thessalonike | F20: Actes de Docheiariou, Archives de l’Athos XIII, Paris 1984, 53 | G20: 14774616 / Oikonomidēs, Nicolas | I20: 316793603 / Papacostas, Tassos | K20: Docheiariou 1 | L20: 53.2-35
A21: Docheiariou 2a | B21: Pittakion of Alexios I | E21: Niketas Xiphilinos, krites and anagrapheus of Boleron, Strymon and Thessalonike; Emperor Alexios I Komnenos | F21: Actes de Docheiariou, Archives de l’Athos XIII, Paris 1984, 58 | G21: 14774616 / Oikonomidēs, Nicolas | I21: 316793603 / Papacostas, Tassos | K21: Docheiariou 2a | L21: 58.1-59.40
A22: Docheiariou 2b | B22: Prostaxis of Anna Dalassene | E22: Niketas Xiphilinos, krites and anagrapheus of Boleron, Strymon and Thessalonike; Anna Dalassene | F22: Actes de Docheiariou, Archives de l’Athos XIII, Paris 1984, 58-59 | G22: 14774616 / Oikonomidēs, Nicolas | I22: 316793603 / Papacostas, Tassos | K22: Docheiariou 2b | L22: 58.1-59.40
A23: Documents 4 | B23: On Ordinations | D23: Niketas 135 / Niketas, metropolitan of Ankyra [1072, 1079, 1082] | F23: Documents inédits d'ecclésiologie byzantine, Leuven 1966, pp. 176-206 | G23: 19676388 / Darrouzès, Jean | I23: Niketas 135 / Niketas, metropolitan of Ankyra [1072, 1079, 1082] | K23: Documents 4 | L23: 176-206
A24: Domenico of Grado | B24: Domenico of Grado to Petros of Antioch | D24: Dominikos 101 / Domenico, archbishop of Grado or Aquileia, patriarch of Venice | F24: Acta et scripta quae de controversiis ecclesiae graecae et latinae saeculo undecimo composita extant, Leipzig and Marburg 1861, pp. 205-208 | G24: 29618378 / Will, Cornelius | I24: Dominikos 101 / Domenico, archbishop of Grado or Aquileia, patriarch of Venice | K24: Domenico of Grado | L24: 205.3-208.16
A25: Eleousa: Acts | B25: Chrysobull to Eleousa monastery | D25: Alexios 1 / Emperor Alexios I Komnenos | F25: “Le monastère de Notre-Dame de Pitié en Macédoine”, Izvestija Russkogo Arheologičeskogo Instituta v Konstantinopole 6 (1900) 25-27 | G25: 51721803 / Petit, Louis | I25: 316793603 / Papacostas, Tassos | K25: Eleousa: Acts | L25: 26.19-27.8
A26: Eleousa: Typikon | B26: Typikon of Eleousa monastery | D26: Manuel 63 / Manuel, bishop of Stroumitza (Tiberioupolis) | F26: “Le monastère de Notre-Dame de Pitié en Macédoine”, Izvestija Russkogo Arheologičeskogo Instituta v Konstantinopole 6 (1900) 69-125 | G26: 51721803 / Petit, Louis | I26: 34477027 / Whitby, Mary | K26: Eleousa: Typikon | L26: 93.24-8
A27: Esphigmenou 1 | B27: Deed of sale 1034 | E27: Dionysios, monk and scribe at Berroiotou on Athos; Germanos, hegoumenos of Theotokos Katadaimonon on Athos; Petros, hegoumenos of Theotokos Katadaimonon on Athos | F27: Actes d’Esphigménou, Archives de l’Athos VI, Paris 1973, 41-42 | G27: 71393851 / Lefort, Jacques | I27: 316793603 / Papacostas, Tassos | K27: Esphigmenou 1 | L27: 42.31-32
A28: Esphigmenou 2 | B28: Deed of Theoktistos to Nikephoros | E28: Bartholomaios, monk and scribe at Esphigmenou on Athos; Theoktistos, hegoumenos of Esphigmenou and protos of Athos | F28: Actes d’Esphigménou, Archives de l’Athos VI, Paris 1973, 45-46 | G28: 71393851 / Lefort, Jacques | I28: 316793603 / Papacostas, Tassos | K28: Esphigmenou 2 | L28: 46.37-39
A29: Esphigmenou 3 | B29: Guarantee of Theodoros of Galaiagra | E29: Theodoros, monk at Galeagra on Athos; Iakobos, monk at Galeagra on Athos | F29: Actes d’Esphigménou, Archives de l’Athos VI, Paris 1973, 48-49 | G29: 71393851 / Lefort, Jacques | I29: 316793603 / Papacostas, Tassos | K29: Esphigmenou 3 | L29: 48.1-49.34
A30: Esphigmenou 4 | B30: Deed of Nikolaos protospatharios | D30: Nikolaos 226 / Nikolaos, protospatharios and man of krites of the velon Christophoros | F30: Actes d’Esphigménou, Archives de l’Athos VI, Paris 1973, 52-54 | G30: 71393851 / Lefort, Jacques | I30: 316793603 / Papacostas, Tassos | K30: Esphigmenou 4 | L30: 53.20-26
A31: Esphigmenou 4a | B31: Parekbolaion of Christophoros krites | E31: Christophoros, krites of the velon and of Boleron, Strymon and Thessalonike; Nikolaos, protospatharios and man of krites of the velon Christophoros | F31: Actes d’Esphigménou, Archives de l’Athos VI, Paris 1973, 52-53 | G31: 71393851 / Lefort, Jacques | I31: 316793603 / Papacostas, Tassos | K31: Esphigmenou 4a | L31: 52.2-53.11
A32: Esphigmenou 5 | B32: Deed of Euthymios | D32: Euthymios 113 / Euthymios, anagrapheus of Boleron, Strymon and Thessalonike | F32: Actes d’Esphigménou, Archives de l’Athos VI, Paris 1973, 57-58 | G32: 71393851 / Lefort, Jacques | I32: 316793603 / Papacostas, Tassos | K32: Esphigmenou 5 | L32: 57.1-58.34
A33: Eustathios Romaios Peira | B33: Peira | D33: Eustathios 61 / Eustathios Romaios | F33: “Πεῖρα Εὐσταθίου τοῦ Ῥωμαίου”, Jus Graecoromanum vol.4, Athens 1931 | G33: 111939078 / Zepos, Panagiōtēs | I33: Eustathios 61 / Eustathios Romaios | K33: Eustathios Romaios Peira | L33: Peira, tit.
A34: Eustathios Romaios RPA | B34: Peri disexadelphōn | D34: Eustathios 61 / Eustathios Romaios | F34: Σύνταγμα τῶν θείων καὶ ἱερῶν κανόνων, vol. 5, Athens 1855, 32-36 | H34: Rállēs, Geṓrgios A.; Potlēs, Michaēl | I34: Eustathios 61 / Eustathios Romaios | K34: Eustathios Romaios RPA | L34: Ralles-Potles V, 32-36
A35: Eustathios Romaios RPB | B35: Hypomnēma peri duō exadelphōn labontōn duo exadelphas | D35: Eustathios 61 / Eustathios Romaios | F35: Σύνταγμα τῶν θείων καὶ ἱερῶν κανόνων, vol. 5, Athens 1855, 341-353 | H35: Rállēs, Geṓrgios A.; Potlēs, Michaēl | I35: Eustathios 61 / Eustathios Romaios | K35: Eustathios Romaios RPB | L35: Ralles-Potles V, 341
A36: Eustathios Romaios Schminck I | B36: Marriage of Ioannes and Maria | D36: Eustathios 61 / Eustathios Romaios | F36: “Vier eherechtliche Entscheidungen aus dem 11. Jahrhundert”, Fontes Minores 3 (1979) 221-279 | G36: 62165959 / Schminck, Andreas | I36: Eustathios 61 / Eustathios Romaios | K36: Eustathios Romaios Schminck I | L36: Schminck I, 1-111
A37: Eustathios Romaios Schminck II | B37: Marriage of Theophylact and Theophano | D37: Eustathios 61 / Eustathios Romaios | F37: “Vier eherechtliche Entscheidungen aus dem 11. Jahrhundert”, Fontes Minores 3 (1979) 221-279 | G37: 62165959 / Schminck, Andreas | I37: 62165959 / Schminck, Andreas | K37: Eustathios Romaios Schminck II | L37: p. 250
A38: Eustathios Romaios Schminck III | B38: Marriage of the daughter of Brachamios | D38: Eustathios 61 / Eustathios Romaios | F38: “Vier eherechtliche Entscheidungen aus dem 11. Jahrhundert”, Fontes Minores 3 (1979) 221-279 | G38: 62165959 / Schminck, Andreas | I38: Eustathios 61 / Eustathios Romaios | K38: Eustathios Romaios Schminck III | L38: Schminck III, 1-153
A39: Eustathios: Capture of Thessalonike | B39: De Thessalonica a Latinis capta | D39: Eustathios 20147 / Eustathios, metropolitan of Thessalonike | F39: La espugnazione di Tessalonica, Palermo 1961 | G39: 69687416 / Kyriakides, Stilpon Paraskeua | I39: Eustathios 20147 / Eustathios, metropolitan of Thessalonike | K39: Eustathios: Capture of Thessalonike | L39: 2.10-4.21
A40: Fulcher of Chartres | B40: Fulcheri Carnotensis Historia Hierosolymitana | D40: Fulcher 101 / Fulcher of Chartres, historian | F40: Fulcheri Carnotensis Historia Hierosolymitana (1095-1127), Heidelberg 1913 | G40: 5023204 / Hagenmeyer, Heinrich | I40: Fulcher 101 / Fulcher of Chartres, historian | K40: Fulcher of Chartres | L40: 41030
A41: Glykas | B41: Annales | D41: Michael 305 / Michael Sikidites, punished as a magician | F41: Michaelis Glycae Annales, Corpus scriptorum historiae Byzantinae 21, Bonn 1836 | G41: 44387193 / Bekker, Immanuel | I41: 44387193 / Bekker, Immanuel | K41: Glykas
A42: Gregory VII, Epistolae vagantes | B42: Gregory VII to Matilda of Tuscany | D42: Gregorios 27 / Pope Gregory VII | F42: The Epistolae vagantes of Pope Gregory VII, Oxford 1972 | G42: 2787145857122522922479 / Cowdrey, Herbert E. J. | I42: Gregorios 27 / Pope Gregory VII | K42: Gregory VII, Epistolae vagantes | L42: pp. 10-11: 5
A43: Gregory VII, in Caspar I, 18 | B43: Gregory VII to Emperor Michael VII | D43: Gregorios 27 / Pope Gregory VII | F43: Das Register Gregors VII, in Monumenta Germaniae historica. Epistolae selectae, 2 vols., Berlin 1920-1923 | G43: 10598157 / Caspar, Erich Ludwig Eduard | I43: Gregorios 27 / Pope Gregory VII | K43: Gregory VII, in Caspar I, 18 | L43: I, 18 (29.29-30)
A44: Gregory VII, in Caspar I, 46 | B44: Gregory VII to William of Burgundy | D44: Gregorios 27 / Pope Gregory VII | F44: Das Register Gregors VII, in Monumenta Germaniae historica. Epistolae selectae, 2 vols., Berlin 1920-1924 | G44: 10598157 / Caspar, Erich Ludwig Eduard | I44: Gregorios 27 / Pope Gregory VII | K44: Gregory VII, in Caspar I, 46 | L44: I, 46 (70-71)
A45: Gregory VII, in Caspar VII, 28 | B45: Gregory VII to Roffredo, Bishop of Benevento | D45: Gregorios 27 / Pope Gregory VII | F45: Das Register Gregors VII, in Monumenta Germaniae historica. Epistolae selectae, 2 vols., Berlin 1920-1932 | G45: 10598157 / Caspar, Erich Ludwig Eduard | I45: Gregorios 27 / Pope Gregory VII | K45: Gregory VII, in Caspar VII, 28 | L45: VII, 28 (509-510)
A46: Gregory VII, in Caspar VIII, 1 | B46: Gregory VII to Gregory, Archbishop of Armenia | D46: Gregorios 27 / Pope Gregory VII | F46: Das Register Gregors VII, in Monumenta Germaniae historica. Epistolae selectae, 2 vols., Berlin 1920-1933 | G46: 10598157 / Caspar, Erich Ludwig Eduard | I46: Gregorios 27 / Pope Gregory VII | K46: Gregory VII, in Caspar VIII, 1 | L46: VIII, 1 (510-514)
A47: Gregory VII, in Caspar VIII, 6 | B47: Gregory VII's Call to the Southern Italian Bishops for the Support of Emperor Michael VII | D47: Gregorios 27 / Pope Gregory VII | F47: Das Register Gregors VII, in Monumenta Germaniae historica. Epistolae selectae, 2 vols., Berlin 1920-1936 | G47: 10598157 / Caspar, Erich Ludwig Eduard | I47: Gregorios 27 / Pope Gregory VII | K47: Gregory VII, in Caspar VIII, 6 | L47: VIII, 6 (523-524)
A48: Hilandar | B48: Act of Paul protos | E48: Paulos, hegoumenos of Docheiariou and protos of Athos; Nikephoros, monk at Hilandar on Athos | F48: Actes de Chilandar I. Des origines à 1319, Archives de l’Athos XX, Paris 1998, 98-99 | H48: Živojinović, Mirjana; Kravari, Vassiliki; Giros, Christophe | I48: 316793603 / Papacostas, Tassos | K48: Hilandar | L48: 99.29
A49: Humbert, Commemoratio | B49: Brevis et succincta commemoratio eorum quae gesserunt apocrisiarii sanctae romanae et apostolicae sedis in regia urbe | D49: Humbert 101 / Humbert, cardinal bishop of Silva Candida | F49: Acta et scripta quae de controversiis ecclesiae graecae et latinae saeculo undecimo composita extant, Leipzig and Marburg 1861, pp. 150-52 | G49: 29618378 / Will, Cornelius | I49: 29618378 / Will, Cornelius | K49: Humbert, Commemoratio | L49: p. 150, tit.
A50: Humbert, Dialogus | B50: Humberti cardinalis Dialogus | D50: Humbert 101 / Humbert, cardinal bishop of Silva Candida | F50: Acta et scripta quae de controversiis ecclesiae graecae et latinae saeculo undecimo composita extant, Leipzig and Marburg 1861, pp. 92-126 | G50: 29618378 / Will, Cornelius | I50: Humbert 101 / Humbert, cardinal bishop of Silva Candida | K50: Humbert, Dialogus | L50: 93-126
A51: Humbert, Excommunication | B51: Excommunicatio, qua feriuntur Michael Cerularius atque eius sectatores | D51: Humbert 101 / Humbert, cardinal bishop of Silva Candida | F51: Acta et scripta quae de controversiis ecclesiae graecae et latinae saeculo undecimo composita extant, Leipzig and Marburg 1861, pp. 153-54 | G51: 29618378 / Will, Cornelius | I51: Humbert 101 / Humbert, cardinal bishop of Silva Candida | K51: Humbert, Excommunication | L51: 153A.1-15
A52: Hypomnema on marriage | B52: Hypomnema on marriage | F52: “Vier eherechtliche Entscheidungen aus dem 11. Jahrhundert”, Fontes Minores 3 (1979) 221-279 | G52: 62165959 / Schminck, Andreas | I52: 62165959 / Schminck, Andreas | K52: Hypomnema on marriage
A53: Ibn al-Athir | B53: al-Kamil fi'l-Ta'rikh' | D53: 54439868 / Ibn al-Athīr, ʿIzz al-Dīn | F53: The Chronicle of Ibn al-Athir for the Crusading Period from al-Kamil fi'l-Ta'rikh, London 2008: | G53: 112702543 / Richards, D. S. | I53: 112702543 / Richards, D. S. | K53: Ibn al-Athir | L53: page 288-289
A54: Ibn Shaddad | B54: Al-a'laq al-khatira fi dhikr umara' al-Sham wa'l-Jazira | D54: 81960386 / Ibn Shaddād, Muḥammad ibn ʻAlī | F54: La description de la Syrie du Nord de ‘Izz al-Din Ibn Saddad” (Ibn Shaddad, al-A’laq al-khatira fi dhikr umara’ al-Sham wa-l-Jazira, al-juz’ al-awwal, al-qism al-thani), Bulletin d’études orientales 32-33 (1980-81), 265-402 | G54: 17250992 / Eddé, Anne-Marie | I54: 17250992 / Eddé, Anne-Marie | K54: Ibn Shaddad | L54: Introduction
A55: Italos trial | F55: “Le proces officiel de Jean l’Italien: les actes et leurs sous-entendus,” Travaux et Memoires 9 (1985), 133-69 | G55: 88739139 / Gouillard, Jean | I55: 88739139 / Gouillard, Jean | K55: Italos trial
A56: Iveron 25 | B56: Testament of Loukas of Galeagra | E56: Loukas, hegoumenos of Galeagra on Athos; Iakobos, monk at Galeagra on Athos | F56: Actes d’Iviron I, Actes de l’Athos XIV, Paris 1985, 237-239 | H56: Lefort, Jacques; Oikonomidès, Nicolas; Papachryssanthou, Denise; Métrévéli, Hélène | J56: Loukas, hegoumenos of Galeagra on Athos; Iakobos, monk at Galeagra on Athos | K56: Iveron 25 | L56: 1.239.45
A57: Iveron 26 | B57: Act of exchange | E57: Maria, daughter of Stephanos Sthlabotas; Anna, landowner at Thessalonike; Agathe, landowner at Thessalonike; Niketas, librarian of Hagia Sophia of Thessalonike | F57: Actes d’Iviron I, Actes de l’Athos XIV, Paris 1985, 241-243 | H57: Lefort, Jacques; Oikonomidès, Nicolas; Papachryssanthou, Denise; Métrévéli, Hélène | I57: 316793603 / Papacostas, Tassos | K57: Iveron 26 | L57: 1.242.33-35
A58: Iveron 27 | B58: Act of delimitation | D58: Theodosios 106 / Theodosios, nomikos of Hierissos | F58: Actes d’Iviron I, Actes de l’Athos XIV, Paris 1985, 245-247 | H58: Lefort, Jacques; Oikonomidès, Nicolas; Papachryssanthou, Denise; Métrévéli, Hélène | I58: 316793603 / Papacostas, Tassos | K58: Iveron 27 | L58: 1.246.29-247.41
A59: Iveron 28 | B59: Act of Markos | E59: Markos, hegoumenos of Kyparissiou on Athos; Basileios, monk and scribe on Athos (Iveron?) | F59: Actes d’Iviron I, Actes de l’Athos XIV, Paris 1985, 249-251 | H59: Lefort, Jacques; Oikonomidès, Nicolas; Papachryssanthou, Denise; Métrévéli, Hélène | I59: 316793603 / Papacostas, Tassos | K59: Iveron 28 | L59: 1.250.27-28
A60: Iveron 29 | B60: Act of Andronikos anagrapheus | D60: Andronikos 104 / Andronikos, krites and anagrapheus of Boleron, Strymon and Thessalonike | F60: Actes d’Iviron I, Actes de l’Athos XIV, Paris 1985, 256-261 | H60: Lefort, Jacques; Oikonomidès, Nicolas; Papachryssanthou, Denise; Métrévéli, Hélène | I60: 316793603 / Papacostas, Tassos | K60: Iveron 29 | L60: 1.256.1-3, 261.97-98
A61: Iveron 30 | B61: Extract of Gregorios Chalkoutzes | D61: Gregorios 117 / Gregorios Chalkoutzes, chartoularios of the genikon logothesion | F61: Actes d’Iviron I, Actes de l’Athos XIV, Paris 1985, 268-270 | H61: Lefort, Jacques; Oikonomidès, Nicolas; Papachryssanthou, Denise; Métrévéli, Hélène | I61: 316793603 / Papacostas, Tassos | K61: Iveron 30 | L61: 1.270.34
A62: Iveron 31 | B62: Act of Leon Thylakas | E62: Leon Thylakas, krites of Boleron, Strymon and Thessalonike; Ioannes, spatharokandidatos and notarios | F62: Actes d’Iviron II, Actes de l’Athos XVI, Paris 1990, 77-80 | H62: Lefort, Jacques; Oikonomidès, Nicolas; Papachryssanthou, Denise; Kravari, Vassiliki; Métrévéli, Hélène | I62: 316793603 / Papacostas, Tassos | K62: Iveron 31 | L62: 2.80.61
A63: Iveron 31a | B63: Decree of Theodora | E63: Empress Theodora; Ioannes, spatharokandidatos and notarios | F63: Actes d’Iviron II, Actes de l’Athos XVI, Paris 1990, 77 | H63: Lefort, Jacques; Oikonomidès, Nicolas; Papachryssanthou, Denise; Kravari, Vassiliki; Métrévéli, Hélène | I63: 316793603 / Papacostas, Tassos | K63: Iveron 31a | L63: 2.77.1-10
A64: Iveron 31b | B64: Decree of Theodora | E64: Empress Theodora; Ioannes, spatharokandidatos and notarios | F64: Actes d’Iviron II, Actes de l’Athos XVI, Paris 1990, 77 | H64: Lefort, Jacques; Oikonomidès, Nicolas; Papachryssanthou, Denise; Kravari, Vassiliki; Métrévéli, Hélène | I64: 316793603 / Papacostas, Tassos | K64: Iveron 31a | L64: 2.78.27-2.79.39
A65: Iveron 31d | B65: Response of Ioannes kathegoumenos | E65: Ioannes, hegoumenos of Lavra; Ioannes, spatharokandidatos and notarios | F65: Actes d’Iviron II, Actes de l’Athos XVI, Paris 1990, 79 | H65: Lefort, Jacques; Oikonomidès, Nicolas; Papachryssanthou, Denise; Kravari, Vassiliki; Métrévéli, Hélène | I65: 316793603 / Papacostas, Tassos | K65: Iveron 31d | L65: 2.79.45-49
A66: Iveron 32 | B66: Act of Leon krites | D66: Leon 120 / Leon, patrikios, notarios, anagrapheus of the West | F66: Actes d’Iviron II, Actes de l’Athos XVI, Paris 1990, 85-87 | H66: Lefort, Jacques; Oikonomidès, Nicolas; Papachryssanthou, Denise; Kravari, Vassiliki; Métrévéli, Hélène | I66: 316793603 / Papacostas, Tassos | K66: Iveron 32 | L66: 2.86.33-87.40
A67: Iveron 33 | B67: Act of Nikephoros Botaneiates | D67: Nikephoros 3 / Emperor Nikephoros III Botaneiates | F67: Actes d’Iviron II, Actes de l’Athos XVI, Paris 1990, 90-91 | H67: Lefort, Jacques; Oikonomidès, Nicolas; Papachryssanthou, Denise; Kravari, Vassiliki; Métrévéli, Hélène | I67: 316793603 / Papacostas, Tassos | K67: Iveron 33 | L67: 2.91.22-24
A68: Iveron 34 | B68: Act of Nikolaos Serblias | D68: Nikolaos 115 / Nikolaos Serblias, krites of Boleron, Strymon and Thessalonike | F68: Actes d’Iviron II, Actes de l’Athos XVI, Paris 1990, 96-98 | H68: Lefort, Jacques; Oikonomidès, Nicolas; Papachryssanthou, Denise; Kravari, Vassiliki; Métrévéli, Hélène | I68: 316793603 / Papacostas, Tassos | K68: Iveron 34 | L68: 2.98.29-31
A69: Iveron 35 | B69: Act of Nikolaos Serblias | E69: Nikolaos Serblias, krites of Boleron, Strymon and Thessalonike; Petros, asekretis under Nikolaos Serblias | F69: Actes d’Iviron II, Actes de l’Athos XVI, Paris 1990, 102-104 | H69: Lefort, Jacques; Oikonomidès, Nicolas; Papachryssanthou, Denise; Kravari, Vassiliki; Métrévéli, Hélène | I69: 316793603 / Papacostas, Tassos | K69: Iveron 35 | L69: 2.104.51
A70: Iveron 35a | B70: Parekbolon of Nikolaos Serblias | D70: Nikolaos 115 / Nikolaos Serblias, krites of Boleron, Strymon and Thessalonike | F70: Actes d’Iviron II, Actes de l’Athos XVI, Paris 1990, 102 | H70: Lefort, Jacques; Oikonomidès, Nicolas; Papachryssanthou, Denise; Kravari, Vassiliki; Métrévéli, Hélène | I70: 316793603 / Papacostas, Tassos | K70: Iveron 35a | L70: 2.102.13-17
A71: Iveron 36 | B71: Pittakion of Constantine X | D71: Konstantinos 10 / Emperor Konstantinos X Doukas | F71: Actes d’Iviron II, Actes de l’Athos XVI, Paris 1990, 107 | H71: Lefort, Jacques; Oikonomidès, Nicolas; Papachryssanthou, Denise; Kravari, Vassiliki; Métrévéli, Hélène | I71: 316793603 / Papacostas, Tassos | K71: Iveron 36 | L71: 2.110.19-20
A72: Iveron 37 | B72: Act of Theodoros Dalassenos | D72: Theodoros 126 / Theodoros Dalassenos, doux of Thessalonike | F72: Actes d’Iviron II, Actes de l’Athos XVI, Paris 1990, 109-110 | H72: Lefort, Jacques; Oikonomidès, Nicolas; Papachryssanthou, Denise; Kravari, Vassiliki; Métrévéli, Hélène | I72: 316793603 / Papacostas, Tassos | K72: Iveron 37 | L72: 2.110.22-25
A73: Iveron 39 | B73: Act of Donation | D73: Nikolaos 116 / Nikolaos, protekdikos and nomikos of Hierissos | F73: Actes d’Iviron II, Actes de l’Athos XVI, Paris 1990, 116-118 | H73: Lefort, Jacques; Oikonomidès, Nicolas; Papachryssanthou, Denise; Kravari, Vassiliki; Métrévéli, Hélène | I73: 316793603 / Papacostas, Tassos | K73: Iveron 39 | L73: 2.117.33-34
A74: Iveron 40 | B74: Act of Stephanos of Serres | E74: Stephanos, metropolitan of Serres; Kyriakos, nomikos of Serres | F74: Actes d’Iviron II, Actes de l’Athos XVI, Paris 1990, 125-128 | H74: Lefort, Jacques; Oikonomidès, Nicolas; Papachryssanthou, Denise; Kravari, Vassiliki; Métrévéli, Hélène | I74: 316793603 / Papacostas, Tassos | K74: Iveron 40 | L74: 2.128.53-55, 2.128.65
A75: Iveron 40a | B75: Decision of John Xiphilinos | E75: Ioannes VIII Xiphilinos, patriarch of Constantinople; Kyriakos, nomikos of Serres | F75: Actes d’Iviron II, Actes de l’Athos XVI, Paris 1990, 125-126 | H75: Lefort, Jacques; Oikonomidès, Nicolas; Papachryssanthou, Denise; Kravari, Vassiliki; Métrévéli, Hélène | I75: 316793603 / Papacostas, Tassos | K75: Iveron 40a | L75: 2.125.6-126.13
A76: Iveron 40b | B76: Letter of Ioannikios megas oikonomos | D76: Ioannikios 102 / Ioannikios, megas oikonomos of Hagia Sophia | F76: Actes d’Iviron II, Actes de l’Athos XVI, Paris 1990, 126 | H76: Lefort, Jacques; Oikonomidès, Nicolas; Papachryssanthou, Denise; Kravari, Vassiliki; Métrévéli, Hélène | I76: 316793603 / Papacostas, Tassos | K76: Iveron 40b | L76: 2.126.18-22
A77: Iveron 41 | B77: Chrysobull of Nikephoros III | D77: Nikephoros 3 / Emperor Nikephoros III Botaneiates | F77: Actes d’Iviron II, Actes de l’Athos XVI, Paris 1990, 132-134 | H77: Lefort, Jacques; Oikonomidès, Nicolas; Papachryssanthou, Denise; Kravari, Vassiliki; Métrévéli, Hélène | I77: 316793603 / Papacostas, Tassos | K77: Iveron 41 | L77: 2.132.18-133.45
A78: Iveron 42 | B78: Act of Paulos protos | D78: Paulos 105 / Paulos, hegoumenos of Docheiariou and protos of Athos | F78: Actes d’Iviron II, Actes de l’Athos XVI, Paris 1990, 139-140 | H78: Lefort, Jacques; Oikonomidès, Nicolas; Papachryssanthou, Denise; Kravari, Vassiliki; Métrévéli, Hélène | I78: 316793603 / Papacostas, Tassos | K78: Iveron 42 | L78: 2.139.32-34, 2.140.39
A79: Iveron 43 | B79: Warranty of Theodoulos of Ezeba | E79: Theodoulos, bishop of Ezoba; Leon Tzainos, protopapas of Ezoba bishopric; Ioannes, nomikos of Chrysopolis | F79: Actes d’Iviron II, Actes de l’Athos XVI, Paris 1990, 145-150 | H79: Lefort, Jacques; Oikonomidès, Nicolas; Papachryssanthou, Denise; Kravari, Vassiliki; Métrévéli, Hélène | I79: 316793603 / Papacostas, Tassos | K79: Iveron 43 | L79: 2.149.49-50
A80: Iveron 44 | B80: Testament of Symbatios Pakourianos | E80: Symbatios Pakourianos, kouropalates and patron of Iveron; Ioannes Hagiotessarakontites, notarios and taboularios | F80: Actes d’Iviron II, Actes de l’Athos XVI, Paris 1990, 154-156 | H80: Lefort, Jacques; Oikonomidès, Nicolas; Papachryssanthou, Denise; Kravari, Vassiliki; Métrévéli, Hélène | I80: 316793603 / Papacostas, Tassos | K80: Iveron 44 | L80: 2.155.12, 2.155.25-156.25
A81: Iveron 45 | B81: Delimitation of Gregory Xeros | E81: Gregorios Xeros, monk, dikaiophylax and anagrapheus; Michael, vestes and imperial notarios of the oikeiaka | F81: Actes d’Iviron II, Actes de l’Athos XVI, Paris 1990, 161-167 | H81: Lefort, Jacques; Oikonomidès, Nicolas; Papachryssanthou, Denise; Kravari, Vassiliki; Métrévéli, Hélène | I81: 316793603 / Papacostas, Tassos | K81: Iveron 45 | L81: 2.167.96
A82: Iveron 46 | B82: Proxy of Kale | E82: Kale, wife of Symbatios Pakourianos; Eleutherios, notarios attached to the Hagioi Tessarakonta | F82: Actes d’Iviron II, Actes de l’Athos XVI, Paris 1990, 168-169 | H82: Lefort, Jacques; Oikonomidès, Nicolas; Papachryssanthou, Denise; Kravari, Vassiliki; Métrévéli, Hélène | I82: 316793603 / Papacostas, Tassos | K82: Iveron 46 | L82: 2.169.2-4
A83: Iveron 47 | B83: Testament of the nun Maria | E83: Kale, wife of Symbatios Pakourianos; Ioannes Phorites, notary at Constantinople | F83: Actes d’Iviron II, Actes de l’Athos XVI, Paris 1990, 170-183 | H83: Lefort, Jacques; Oikonomidès, Nicolas; Papachryssanthou, Denise; Kravari, Vassiliki; Métrévéli, Hélène | I83: 316793603 / Papacostas, Tassos | K83: Iveron 47 | L83: 2.182.69
A84: Kastamonitou | B84: Deed of Theophylaktos | D84: Athanasios 112 / Athanasios, monk of kyr Sisoe on Athos | F84: Actes de Kastamonitou, Archives de l’Athos IX, Paris 1978 | G84: 14774616 / Oikonomidēs, Nicolas | I84: 316793603 / Papacostas, Tassos | K84: Kastamonitou | L84: 29.20-25
A85: Kecharitomene | B85: Kecharitomene typikon | D85: Eirene 61 / Eirene Doukaina, wife of Alexios I | F85: “Le typikon de la Théotokos Kécharitôménè", Revue des Études Byzantines, 43 (1985), 5-165 | G85: 231073465 / Gautier, Paul | I85: 231073465 / Gautier, Paul | K85: Kecharitomene | L85: p. 137 l. 2087
A86: Kekaumenos | B86: Consilia et narrationes | D86: Anonymus 274 / Kekaumenos, author of the "Strategikon" | F86: Raccomandazioni e consigli di un galantuomo (Strategikon). Testo critico, traduzione e note, Hellenica 2. Testi e strumenti di letteratura greca antica, medievale e umanistica, Alessandria 1998 | G86: 38147676 / Spadaro, Maria Dora | I86: Anonymus 274 / Kekaumenos, author of the "Strategikon" | K86: Kekaumenos | L86: 228.28-37
A87: Keroularios ep. to Petros of Antioch I | B87: Letter I to Petros of Antioch | D87: Michael 11 / Michael I Keroularios, patriarch of Constantinople | F87: Acta et scripta quae de controversiis ecclesiae graecae et latinae saeculo undecimo composita extant, Leipzig and Marburg 1861, pp. 172-84 | G87: 29618378 / Will, Cornelius | I87: Michael 11 / Michael I Keroularios, patriarch of Constantinople | K87: Keroularios ep. to Petros of Antioch I | L87: ep. to Petros of Antioch I (Will) 172.1-184.9
A88: Keroularios ep. to Petros of Antioch II | B88: Letter II to Petros of Antioch | D88: Michael 11 / Michael I Keroularios, patriarch of Constantinople | F88: Acta et scripta quae de controversiis ecclesiae graecae et latinae saeculo undecimo composita extant, Leipzig and Marburg 1861, pp. 184-88 | G88: 29618378 / Will, Cornelius | I88: Michael 11 / Michael I Keroularios, patriarch of Constantinople | K88: Keroularios ep. to Petros of Antioch II | L88: ep. to Petros of Antioch II (Will) 184.1-188.38
A89: Kinnamos | B89: Epitome | D89: Ioannes 17001 / Ioannes Kinnamos (John Cinnamus) the historian | F89: Ioannis Cinnami Epitome, Corpus scriptorum historiae Byzantinae 10, Bonn 1836 | G89: 69736744 / Meineke, August | I89: Ioannes 17001 / Ioannes Kinnamos (John Cinnamus) the historian | K89: Kinnamos | L89: 39085
A90: Kleinchroniken 14 | B90: Short Chronicle #14 | F90: Die byzantinischen Kleinchroniken, 3 vols., Vienna 1975-1979, 121-155 | G90: 14789545 / Schreiner, Peter | I90: 14789545 / Schreiner, Peter | K90: Kleinchroniken 14
A91: Kleinchroniken 15 | B91: Short Chronicle #15 | F91: Die byzantinischen Kleinchroniken, 3 vols., Vienna 1975-1979, 156-162 | G91: 14789545 / Schreiner, Peter | I91: 14789545 / Schreiner, Peter | K91: Kleinchroniken 15
A92: Kleinchroniken 16 | B92: Short Chronicle #16 | F92: Die byzantinischen Kleinchroniken, 3 vols., Vienna 1975-1979, 163-168 | G92: 14789545 / Schreiner, Peter | I92: 14789545 / Schreiner, Peter | K92: Kleinchroniken 16
A93: Kleinchroniken 17 | B93: Short Chronicle #17 | F93: Die byzantinischen Kleinchroniken, 3 vols., Vienna 1975-1979, 169-170 | G93: 14789545 / Schreiner, Peter | I93: 14789545 / Schreiner, Peter | K93: Kleinchroniken 17
A94: Kleinchroniken 4 | B94: Short Chronicle #4 | F94: Die byzantinischen Kleinchroniken, 3 vols., Vienna 1975-1979, 52-53 | G94: 14789545 / Schreiner, Peter | I94: 14789545 / Schreiner, Peter | K94: Kleinchroniken 4
A95: Kleinchroniken 5 | B95: Short Chronicle #5 | F95: Die byzantinischen Kleinchroniken, 3 vols., Vienna 1975-1979, 54-56 | G95: 14789545 / Schreiner, Peter | I95: 14789545 / Schreiner, Peter | K95: Kleinchroniken 5
A96: Kleinchroniken 6 | B96: Short Chronicle #6 | F96: Die byzantinischen Kleinchroniken, 3 vols., Vienna 1975-1979, 57-58 | G96: 14789545 / Schreiner, Peter | I96: 14789545 / Schreiner, Peter | K96: Kleinchroniken 6
A97: Kyrillos Phileotes | B97: Life of Kyrillos Phileotes | D97: Nikolaos 194 / Nikolaos Kataskepenos, author of Life of Kyrillos Phileotes | F97: La vie de saint Cyrille le Philéote moine byzantin (+1110), Subsidia Hagiographica 39, Brussels 1964 | G97: 17296824 / Sargologos, Étienne | I97: Nikolaos 194 / Nikolaos Kataskepenos, author of Life of Kyrillos Phileotes | K97: Kyrillos Phileotes | L97: 43-44
A98: Lavra 26 | B98: Testament of Athanasios of Bouleuteria | E98: Athanasios, hegoumenos of Bouleuteria on Athos; Theodosios, monk and presbyter on Athos | F98: Actes de Lavra. Première partie: Des origines à 1204, Archives de l’Athos V, Paris 1970, 178-179 | H98: Lemerle, Paul; Guillou, André; Svoronos, Nicolas; Papachryssanthou, Denise | J98: Athanasios, hegoumenos of Bouleuteria on Athos; Theodosios, monk and presbyter on Athos | K98: Lavra 26 | L98: 178.1-30
A99: Lavra 27 | B99: Guarantee of Lavra | D99: Athanasios 105 / Athanasios II, hegoumenos of Lavra on Athos | F99: Actes de Lavra. Première partie: Des origines à 1204, Archives de l’Athos V, Paris 1970, 180-181 | H99: Lemerle, Paul; Guillou, André; Svoronos, Nicolas; Papachryssanthou, Denise | I99: 316793603 / Papacostas, Tassos | K99: Lavra 27 | L99: 180.1-181.30
A100: Lavra 28 | B100: Donation of Gabriel and Ignatios | E100: Gabriel, hegoumenos of kyr Nikolaos Hesychast on Athos; Ignatios, hegoumenos of kyr Nikolaos Hesychast on Athos; Antonios, monk and presbyter on Athos | F100: Actes de Lavra. Première partie: Des origines à 1204, Archives de l’Athos V, Paris 1970, 183-184 | H100: Lemerle, Paul; Guillou, André; Svoronos, Nicolas; Papachryssanthou, Denise | I100: 316793603 / Papacostas, Tassos | K100: Lavra 28 | L100: 184.15-16
...

Sheet Correspondence
A1: Letter sent | B1: Text therein | C1: From whom | D1: From group | E1: To whom | F1: To group | G1: When sent | H1: When received | I1: Where sent | J1: Where received | K1: Authority | L1: Authority group | M1: Based on | N1: Source text/publication | O1: Source text/reference | P1: Source text/excerpt
A2: Psellos, Letter 1 | B2: Psellos Papaioannou 1 | C2: Michael 61 / Michael Psellos (named Konstantinos till tonsure in 1054) | E2: Aikaterine 101 / Aikaterine of Bulgaria, wife of Isaakios I Komnenos | G2: J 1059 | K2: 60972463 / Papaioannou, Stratis | N2: Psellos Papaioannou 1 | O2: p. 1
A3: Psellos, Letter 2 | B3: Psellos Papaioannou 2 | C3: Michael 61 / Michael Psellos (named Konstantinos till tonsure in 1054) | E3: Aimilianos 61 / Aimilianos, patriarch of Antioch | I3: Antioch (on the Orontes) | K3: 60972463 / Papaioannou, Stratis | N3: Psellos Papaioannou 2 | O3: p. 3
A4: Psellos, Letter 3 | B4: Psellos Papaioannou 3 | C4: Michael 61 / Michael Psellos (named Konstantinos till tonsure in 1054) | E4: Aimilianos 61 / Aimilianos, patriarch of Antioch | I4: Antioch (on the Orontes) | K4: 60972463 / Papaioannou, Stratis | N4: Psellos Papaioannou 3 | O4: p. 4
A5: Psellos, Letter 4 | B5: Psellos Papaioannou 4 | C5: Michael 61 / Michael Psellos (named Konstantinos till tonsure in 1054) | E5: Aimilianos 61 / Aimilianos, patriarch of Antioch | I5: Antioch (on the Orontes) | K5: 60972463 / Papaioannou, Stratis | N5: Psellos Papaioannou 4 | O5: p. 6
A6: Psellos, Letter 5 | B6: Psellos Papaioannou 5 | C6: Michael 61 / Michael Psellos (named Konstantinos till tonsure in 1054) | E6: Aimilianos 61 / Aimilianos, patriarch of Antioch | I6: Antioch (on the Orontes) | K6: 60972463 / Papaioannou, Stratis | N6: Psellos Papaioannou 5 | O6: p. 7
A7: Psellos, Letter 6 | B7: Psellos Papaioannou 6 | C7: Michael 61 / Michael Psellos (named Konstantinos till tonsure in 1054) | E7: Aimilianos 61 / Aimilianos, patriarch of Antioch | I7: Antioch (on the Orontes) | K7: 60972463 / Papaioannou, Stratis | N7: Psellos Papaioannou 6 | O7: p. 10
A8: Psellos, Letter 7 | B8: Psellos Papaioannou 7 | C8: Michael 61 / Michael Psellos (named Konstantinos till tonsure in 1054) | E8: Aimilianos 61 / Aimilianos, patriarch of Antioch | I8: Antioch (on the Orontes) | K8: 60972463 / Papaioannou, Stratis | N8: Psellos Papaioannou 7 | O8: p. 12
A9: Psellos, Letter 8 | B9: Psellos Papaioannou 8 | C9: Michael 61 / Michael Psellos (named Konstantinos till tonsure in 1054) | E9: Aimilianos 61 / Aimilianos, patriarch of Antioch | I9: Antioch (on the Orontes) | K9: 60972463 / Papaioannou, Stratis | N9: Psellos Papaioannou 8 | O9: p. 14
A10: Psellos, Letter 9 | B10: Psellos Papaioannou 9 | C10: Michael 61 / Michael Psellos (named Konstantinos till tonsure in 1054) | E10: Aimilianos 61 / Aimilianos, patriarch of Antioch | I10: Antioch (on the Orontes) | K10: 60972463 / Papaioannou, Stratis | N10: Psellos Papaioannou 9 | O10: p. 15
A11: Psellos, Letter 10 | B11: Psellos Papaioannou 10 | C11: Michael 61 / Michael Psellos (named Konstantinos till tonsure in 1054) | E11: Aimilianos 61 / Aimilianos, patriarch of Antioch | I11: Antioch (on the Orontes) | K11: 60972463 / Papaioannou, Stratis | N11: Psellos Papaioannou 10 | O11: p. 19
A12: Psellos, Letter 11 | B12: Psellos Papaioannou 11 | C12: Michael 61 / Michael Psellos (named Konstantinos till tonsure in 1054) | E12: Aimilianos 61 / Aimilianos, patriarch of Antioch | I12: Antioch (on the Orontes) | K12: 60972463 / Papaioannou, Stratis | N12: Psellos Papaioannou 11 | O12: p. 22
A13: Psellos, Letter 12 | B13: Psellos Papaioannou 12 | C13: Michael 61 / Michael Psellos (named Konstantinos till tonsure in 1054) | E13: Aimilianos 61 / Aimilianos, patriarch of Antioch | I13: Antioch (on the Orontes) | K13: 60972463 / Papaioannou, Stratis | N13: Psellos Papaioannou 12 | O13: p. 25
A14: Psellos, Letter 13 | B14: Psellos Papaioannou 13 | C14: Michael 61 / Michael Psellos (named Konstantinos till tonsure in 1054) | E14: Aimilianos 61 / Aimilianos, patriarch of Antioch | I14: Antioch (on the Orontes) | K14: 60972463 / Papaioannou, Stratis | N14: Psellos Papaioannou 13 | O14: p. 26
... A17: Psellos, Letter 16 | B17: Psellos Papaioannou 16 | C17: Michael 61 / Michael Psellos (named Konstantinos till tonsure in 1054) | E17: Aimilianos 61 / Aimilianos, patriarch of Antioch | I17: Antioch (on the Orontes) | K17: 60972463 / Papaioannou, Stratis | N17: Psellos Papaioannou 16 | O17: p. 41
A18: Psellos, Letter 17 | B18: Psellos Papaioannou 17 | C18: Michael 61 / Michael Psellos (named Konstantinos till tonsure in 1054) | E18: Theodoros 106 / Theodoros (Leon) Alopos, envoy of Michael VI to Isaakios Komnenos | G18: J 1059 | K18: 60972463 / Papaioannou, Stratis | N18: Psellos Papaioannou 17 | O18: p. 44
A19: Psellos, Letter 18 | B19: Psellos Papaioannou 18 | C19: Michael 61 / Michael Psellos (named Konstantinos till tonsure in 1054) | E19: Anonymus 2545 / Aristenos, correspondent of Michael Psellos | K19: 60972463 / Papaioannou, Stratis | N19: Psellos Papaioannou 18 | O19: p. 46
A20: Psellos, Letter 19 | B20: Psellos Papaioannou 19 | C20: Michael 61 / Michael Psellos (named Konstantinos till tonsure in 1054) | E20: Anonymus 2300 / Aristenos, protoasekretis | K20: 60972463 / Papaioannou, Stratis | N20: Psellos Papaioannou 19 | O20: p. 48
A21: Psellos, Letter 20 | B21: Psellos Papaioannou 20 | C21: Michael 61 / Michael Psellos (named Konstantinos till tonsure in 1054) | E21: Anonymus 2300 / Aristenos, protoasekretis | K21: 60972463 / Papaioannou, Stratis | N21: Psellos Papaioannou 20 | O21: p. 49
A22: Psellos, Letter 21 | B22: Psellos Papaioannou 21 | C22: Michael 61 / Michael Psellos (named Konstantinos till tonsure in 1054) | E22: Anonymus 2300 / Aristenos, protoasekretis | G22: J 1068 [TAQ] | K22: 60972463 / Papaioannou, Stratis | N22: Psellos Papaioannou 21 | O22: p. 51
A23: Psellos, Letter 22 | B23: Psellos Papaioannou 22 | C23: Michael 61 / Michael Psellos (named Konstantinos till tonsure in 1054) | E23: Anonymus 2300 / Aristenos, protoasekretis | G23: J 1068 [TAQ] | K23: 60972463 / Papaioannou, Stratis | N23: Psellos Papaioannou 22 | O23: p. 51
A24: Psellos, Letter 23 | B24: Psellos Papaioannou 23 | C24: Michael 61 / Michael Psellos (named Konstantinos till tonsure in 1054) | E24: Anonymus 2300 / Aristenos, protoasekretis | G24: J 1068 [TAQ] | K24: 60972463 / Papaioannou, Stratis | N24: Psellos Papaioannou 23 | O24: p. 54
A25: Psellos, Letter 23 | B25: Psellos Papaioannou 23 | C25: Michael 61 / Michael Psellos (named Konstantinos till tonsure in 1054) | E25: Leon 101 / Leon, epi ton deeseon, killed at Mantzikert | G25: J 1068 [TAQ] | K25: 60972463 / Papaioannou, Stratis | N25: Psellos Papaioannou 23 | O25: p. 54
A26: Psellos, Letter 23 | B26: Psellos Papaioannou 23 | C26: Michael 61 / Michael Psellos (named Konstantinos till tonsure in 1054) | E26: Ioannes 20154 / Ioannes Libellisios | G26: J 1068 [TAQ] | K26: 60972463 / Papaioannou, Stratis | N26: Psellos Papaioannou 23 | O26: p. 54
A27: Psellos, Letter 24 | B27: Psellos Papaioannou 24 | C27: Michael 61 / Michael Psellos (named Konstantinos till tonsure in 1054) | E27: Basileios 2103 / Basileios, epi tou kanikleiou | G27: J 1068 [TAQ] | K27: 60972463 / Papaioannou, Stratis | N27: Psellos Papaioannou 24 | O27: p. 60
A28: Psellos, Letter 25 | B28: Psellos Papaioannou 25 | C28: Michael 61 / Michael Psellos (named Konstantinos till tonsure in 1054) | E28: Basileios 2103 / Basileios, epi tou kanikleiou | G28: J 1068 [TAQ] | K28: 60972463 / Papaioannou, Stratis | N28: Psellos Papaioannou 25 | O28: p. 62
A29: Psellos, Letter 26 | B29: Psellos Papaioannou 26 | C29: Michael 61 / Michael Psellos (named Konstantinos till tonsure in 1054) | E29: Basileios 2103 / Basileios, epi tou kanikleiou | G29: J 1072 | K29: 60972463 / Papaioannou, Stratis | N29: Psellos Papaioannou 26 | O29: p. 64
A30: Psellos, Letter 27 | B30: Psellos Papaioannou 27 | C30: Michael 61 / Michael Psellos (named Konstantinos till tonsure in 1054) | E30: Basileios 2105 / Basileios, krites of Armeniakon | I30: Armeniakon | K30: 60972463 / Papaioannou, Stratis | N30: Psellos Papaioannou 27 | O30: p. 65
A31: Psellos, Letter 28 | B31: Psellos Papaioannou 28 | C31: Michael 61 / Michael Psellos (named Konstantinos till tonsure in 1054) | E31: Basileios 2104 / Basileios, krites (?) of Cappadocia | I31: Cappadocia | K31: 60972463 / Papaioannou, Stratis | N31: Psellos Papaioannou 28 | O31: p. 67
A32: Psellos, Letter 29 | B32: Psellos Papaioannou 29 | C32: Michael 61 / Michael Psellos (named Konstantinos till tonsure in 1054) | E32: Basileios 180 / Basileios, metropolitan of Nikomedeia [1072] | G32: J 1064 - J 1075 | I32: Nikomedeia | K32: 60972463 / Papaioannou, Stratis | N32: Psellos Papaioannou 29 | O32: p. 70
A33: Psellos, Letter 30 | B33: Psellos Papaioannou 30 | C33: Michael 61 / Michael Psellos (named Konstantinos till tonsure in 1054) | E33: Basileios 180 / Basileios, metropolitan of Nikomedeia [1072] | I33: Nikomedeia | K33: 60972463 / Papaioannou, Stratis | N33: Psellos Papaioannou 30 | O33: p. 71
A34: Psellos, Letter 31 | B34: Psellos Papaioannou 31 | C34: Michael 61 / Michael Psellos (named Konstantinos till tonsure in 1054) | E34: Anonymus 2223 / Bourtzes (Ioannes?), correspondent of Michael Psellos | K34: 60972463 / Papaioannou, Stratis | N34: Psellos Papaioannou 31 | O34: p. 72
A35: Psellos, Letter 32 | B35: Psellos Papaioannou 32 | C35: Michael 61 / Michael Psellos (named Konstantinos till tonsure in 1054) | E35: Georgios 2102 / Georgios, aktouarios | K35: 60972463 / Papaioannou, Stratis | N35: Psellos Papaioannou 32 | O35: p. 76
A36: Psellos, Letter 33 | B36: Psellos Papaioannou 33 | C36: Michael 61 / Michael Psellos (named Konstantinos till tonsure in 1054) | E36: Georgios 2101 / Georgios, correspondent of Michael Psellos | K36: 60972463 / Papaioannou, Stratis | N36: Psellos Papaioannou 33 | O36: p. 78
A37: Psellos, Letter 34 | B37: Psellos Papaioannou 34 | C37: Michael 61 / Michael Psellos (named Konstantinos till tonsure in 1054) | E37: Georgios 2101 / Georgios, correspondent of Michael Psellos | K37: 60972463 / Papaioannou, Stratis | N37: Psellos Papaioannou 34 | O37: p. 79
A38: Psellos, Letter 35 | B38: Psellos Papaioannou 35 | C38: Michael 61 / Michael Psellos (named Konstantinos till tonsure in 1054) | E38: Theodoros 126 / Theodoros Dalassenos, doux of Thessalonike | G38: J 1062 - J 1063 | K38: 60972463 / Papaioannou, Stratis | N38: Psellos Papaioannou 35 | O38: p. 81
A39: Psellos, Letter 36 | B39: Psellos Papaioannou 36 | C39: Michael 61 / Michael Psellos (named Konstantinos till tonsure in 1054) | E39: Theodoros 126 / Theodoros Dalassenos, doux of Thessalonike | G39: J 1062 - J 1063 | K39: 60972463 / Papaioannou, Stratis | N39: Psellos Papaioannou 36 | O39: p. 82
A40: Psellos, Letter 37 | B40: Psellos Papaioannou 37 | C40: Michael 61 / Michael Psellos (named Konstantinos till tonsure in 1054) | E40: Romanos 4 / Emperor Romanos IV Diogenes | G40: J 1069 | K40: 60972463 / Papaioannou, Stratis | N40: Psellos Papaioannou 37 | O40: p. 83
A41: Psellos, Letter 38 | B41: Psellos Papaioannou 38 | C41: Michael 61 / Michael Psellos (named Konstantinos till tonsure in 1054) | E41: Romanos 4 / Emperor Romanos IV Diogenes | G41: J 1069 | K41: 60972463 / Papaioannou, Stratis | N41: Psellos Papaioannou 38 | O41: p. 85
A42: Psellos, Letter 39 | B42: Psellos Papaioannou 39 | C42: Michael 61 / Michael Psellos (named Konstantinos till tonsure in 1054) | E42: Romanos 4 / Emperor Romanos IV Diogenes | G42: J 1072, June 29 [TPQ] | K42: 60972463 / Papaioannou, Stratis | N42: Psellos Papaioannou 39 | O42: p. 88
A43: Psellos, Letter 40 | B43: Psellos Papaioannou 40 | C43: Michael 61 / Michael Psellos (named Konstantinos till tonsure in 1054) | E43: Theodoros 101 / Theodoros Dokeianos | G43: J 1059, September 24 [TPQ] | K43: 60972463 / Papaioannou, Stratis | N43: Psellos Papaioannou 40 | O43: p. 93
A44: Psellos, Letter 41 | B44: Psellos Papaioannou 41 | C44: Michael 61 / Michael Psellos (named Konstantinos till tonsure in 1054) | E44: Theodoros 101 / Theodoros Dokeianos | G44: J 1059 | K44: 60972463 / Papaioannou, Stratis | N44: Psellos Papaioannou 41 | O44: p. 96
A45: Psellos, Letter 42 | B45: Psellos Papaioannou 42 | C45: Michael 61 / Michael Psellos (named Konstantinos till tonsure in 1054) | E45: Andronikos 61 / Andronikos Doukas, son of the kaisar Ioannes | G45: J 1071, August [TPQ] | K45: 60972463 / Papaioannou, Stratis | N45: Psellos Papaioannou 42 | O45: p. 97
A46: Psellos, Letter 43 | B46: Psellos Papaioannou 43 | C46: Michael 61 / Michael Psellos (named Konstantinos till tonsure in 1054) | E46: Ioannes 62 / Ioannes Doukas, kaisar | K46: 60972463 / Papaioannou, Stratis | N46: Psellos Papaioannou 43 | O46: p. 99
A47: Psellos, Letter 44 | B47: Psellos Papaioannou 44 | C47: Michael 61 / Michael Psellos (named Konstantinos till tonsure in 1054) | E47: Ioannes 62 / Ioannes Doukas, kaisar | K47: 60972463 / Papaioannou, Stratis | N47: Psellos Papaioannou 44 | O47: p. 103
A48: Psellos, Letter 45 | B48: Psellos Papaioannou 45 | C48: Michael 61 / Michael Psellos (named Konstantinos till tonsure in 1054) | E48: Ioannes 62 / Ioannes Doukas, kaisar | K48: 60972463 / Papaioannou, Stratis | N48: Psellos Papaioannou 45 | O48: p. 104
A49: Psellos, Letter 46 | B49: Psellos Papaioannou 46 | C49: Michael 61 / Michael Psellos (named Konstantinos till tonsure in 1054) | E49: Ioannes 62 / Ioannes Doukas, kaisar | K49: 60972463 / Papaioannou, Stratis | N49: Psellos Papaioannou 46 | O49: p. 106
A50: Psellos, Letter 47 | B50: Psellos Papaioannou 47 | C50: Michael 61 / Michael Psellos (named Konstantinos till tonsure in 1054) | E50: Ioannes 62 / Ioannes Doukas, kaisar | K50: 60972463 / Papaioannou, Stratis | N50: Psellos Papaioannou 47 | O50: p. 107
A51: Psellos, Letter 48 | B51: Psellos Papaioannou 48 | C51: Michael 61 / Michael Psellos (named Konstantinos till tonsure in 1054) | E51: Ioannes 62 / Ioannes Doukas, kaisar | G51: J 1060-1067 | K51: 60972463 / Papaioannou, Stratis | N51: Psellos Papaioannou 48 | O51: p. 109
A52: Psellos, Letter 49 | B52: Psellos Papaioannou 49 | C52: Michael 61 / Michael Psellos (named Konstantinos till tonsure in 1054) | E52: Ioannes 62 / Ioannes Doukas, kaisar | G52: J 1060-1067 | K52: 60972463 / Papaioannou, Stratis | N52: Psellos Papaioannou 49 | O52: p. 111
A53: Psellos, Letter 50 | B53: Psellos Papaioannou 50 | C53: Michael 61 / Michael Psellos (named Konstantinos till tonsure in 1054) | E53: Ioannes 62 / Ioannes Doukas, kaisar | I53: Choirobakchoi | K53: 60972463 / Papaioannou, Stratis | N53: Psellos Papaioannou 50 | O53: p. 112, l. 2
A54: Psellos, Letter 51 | B54: Psellos Papaioannou 51 | C54: Michael 61 / Michael Psellos (named Konstantinos till tonsure in 1054) | E54: Ioannes 62 / Ioannes Doukas, kaisar | G54: J 1060-1067 | K54: 60972463 / Papaioannou, Stratis | N54: Psellos Papaioannou 51 | O54: p. 113
A55: Psellos, Letter 52 | B55: Psellos Papaioannou 52 | C55: Michael 61 / Michael Psellos (named Konstantinos till tonsure in 1054) | E55: Ioannes 62 / Ioannes Doukas, kaisar | K55: 60972463 / Papaioannou, Stratis | N55: Psellos Papaioannou 52 | O55: p. 115
A56: Psellos, Letter 53 | B56: Psellos Papaioannou 53 | C56: Michael 61 / Michael Psellos (named Konstantinos till tonsure in 1054) | E56: Ioannes 62 / Ioannes Doukas, kaisar | G56: J 1060-1067 | K56: 60972463 / Papaioannou, Stratis | N56: Psellos Papaioannou 53 | O56: p. 117
A57: Psellos, Letter 54 | B57: Psellos Papaioannou 54 | C57: Michael 61 / Michael Psellos (named Konstantinos till tonsure in 1054) | E57: Ioannes 62 / Ioannes Doukas, kaisar | K57: 60972463 / Papaioannou, Stratis | N57: Psellos Papaioannou 54 | O57: p. 120
A58: Psellos, Letter 55 | B58: Psellos Papaioannou 55 | C58: Michael 61 / Michael Psellos (named Konstantinos till tonsure in 1054) | E58: Ioannes 62 / Ioannes Doukas, kaisar | K58: 60972463 / Papaioannou, Stratis | N58: Psellos Papaioannou 55 | O58: p. 122
A59: Psellos, Letter 56 | B59: Psellos Papaioannou 56 | C59: Michael 61 / Michael Psellos (named Konstantinos till tonsure in 1054) | E59: Ioannes 62 / Ioannes Doukas, kaisar | K59: 60972463 / Papaioannou, Stratis | N59: Psellos Papaioannou 56 | O59: p. 123
A60: Psellos, Letter 57 | B60: Psellos Papaioannou 57 | C60: Michael 61 / Michael Psellos (named Konstantinos till tonsure in 1054) | E60: Ioannes 62 / Ioannes Doukas, kaisar | K60: 60972463 / Papaioannou, Stratis | N60: Psellos Papaioannou 57 | O60: p. 124
A61: Psellos, Letter 58 | B61: Psellos Papaioannou 58 | C61: Michael 61 / Michael Psellos (named Konstantinos till tonsure in 1054) | E61: Ioannes 62 / Ioannes Doukas, kaisar | K61: 60972463 / Papaioannou, Stratis | N61: Psellos Papaioannou 58 | O61: p. 125
A62: Psellos, Letter 59 | B62: Psellos Papaioannou 59 | C62: Michael 61 / Michael Psellos (named Konstantinos till tonsure in 1054) | E62: Ioannes 62 / Ioannes Doukas, kaisar | K62: 60972463 / Papaioannou, Stratis | N62: Psellos Papaioannou 59 | O62: p. 127
A63: Psellos, Letter 60 | B63: Psellos Papaioannou 60 | C63: Michael 61 / Michael Psellos (named Konstantinos till tonsure in 1054) | E63: Ioannes 62 / Ioannes Doukas, kaisar | K63: 60972463 / Papaioannou, Stratis | N63: Psellos Papaioannou 60 | O63: p. 130
A64: Psellos, Letter 61 | B64: Psellos Papaioannou 61 | C64: Michael 61 / Michael Psellos (named Konstantinos till tonsure in 1054) | E64: Ioannes 62 / Ioannes Doukas, kaisar | K64: 60972463 / Papaioannou, Stratis | N64: Psellos Papaioannou 61 | O64: p. 133
A65: Psellos, Letter 62 | B65: Psellos Papaioannou 62 | C65: Michael 61 / Michael Psellos (named Konstantinos till tonsure in 1054) | E65: Ioannes 62 / Ioannes Doukas, kaisar | K65: 60972463 / Papaioannou, Stratis | N65: Psellos Papaioannou 62 | O65: p. 135
A66: Psellos, Letter 63 | B66: Psellos Papaioannou 63 | C66: Michael 61 / Michael Psellos (named Konstantinos till tonsure in 1054) | E66: Ioannes 62 / Ioannes Doukas, kaisar | K66: 60972463 / Papaioannou, Stratis | N66: Psellos Papaioannou 63 | O66: p. 137
A67: Psellos, Letter 64 | B67: Psellos Papaioannou 64 | C67: Michael 61 / Michael Psellos (named Konstantinos till tonsure in 1054) | E67: Ioannes 62 / Ioannes Doukas, kaisar | K67: 60972463 / Papaioannou, Stratis | N67: Psellos Papaioannou 64 | O67: p. 141
A68: Psellos, Letter 65 | B68: Psellos Papaioannou 65 | C68: Michael 61 / Michael Psellos (named Konstantinos till tonsure in 1054) | E68: Ioannes 62 / Ioannes Doukas, kaisar | K68: 60972463 / Papaioannou, Stratis | N68: Psellos Papaioannou 65 | O68: p. 145
... A78: Psellos, Letter 75 | B78: Psellos Papaioannou 75 | C78: Michael 61 / Michael Psellos (named Konstantinos till tonsure in 1054) | E78: Ioannes 62 / Ioannes Doukas, kaisar | K78: 60972463 / Papaioannou, Stratis | N78: Psellos Papaioannou 75 | O78: p. 161
A79: Psellos, Letter 76 | B79: Psellos Papaioannou 76 | C79: Michael 61 / Michael Psellos (named Konstantinos till tonsure in 1054) | E79: Ioannes 62 / Ioannes Doukas, kaisar | G79: J 1068 - J 1071 | K79: 60972463 / Papaioannou, Stratis | N79: Psellos Papaioannou 76 | O79: p. 162
A80: Psellos, Letter 77 | B80: Psellos Papaioannou 77 | C80: Michael 61 / Michael Psellos (named Konstantinos till tonsure in 1054) | E80: Ioannes 62 / Ioannes Doukas, kaisar | K80: 60972463 / Papaioannou, Stratis | N80: Psellos Papaioannou 77 | O80: p. 167
A81: Psellos, Letter 78 | B81: Psellos Papaioannou 78 | C81: Michael 61 / Michael Psellos (named Konstantinos till tonsure in 1054) | E81: Ioannes 62 / Ioannes Doukas, kaisar | K81: 60972463 / Papaioannou, Stratis | N81: Psellos Papaioannou 78 | O81: p. 170
A82: Psellos, Letter 79 | B82: Psellos Papaioannou 79 | C82: Michael 61 / Michael Psellos (named Konstantinos till tonsure in 1054) | E82: Ioannes 62 / Ioannes Doukas, kaisar | K82: 60972463 / Papaioannou, Stratis | N82: Psellos Papaioannou 79 | O82: p. 174
A83: Psellos, Letter 80 | B83: Psellos Papaioannou 80 | C83: Michael 61 / Michael Psellos (named Konstantinos till tonsure in 1054) | E83: Konstantinos 10 / Emperor Konstantinos X Doukas | K83: 60972463 / Papaioannou, Stratis | N83: Psellos Papaioannou 80 | O83: p. 176
A84: Psellos, Letter 81 | B84: Psellos Papaioannou 81 | C84: Michael 61 / Michael Psellos (named Konstantinos till tonsure in 1054) | E84: Konstantinos 10 / Emperor Konstantinos X Doukas | K84: 60972463 / Papaioannou, Stratis | N84: Psellos Papaioannou 81 | O84: p. 177
A85: Psellos, Letter 82 | B85: Psellos Papaioannou 82 | C85: Michael 61 / Michael Psellos (named Konstantinos till tonsure in 1054) | E85: Konstantinos 10 / Emperor Konstantinos X Doukas | K85: 60972463 / Papaioannou, Stratis | N85: Psellos Papaioannou 82 | O85: p. 177
A86: Psellos, Letter 83 | B86: Psellos Papaioannou 83 | C86: Michael 61 / Michael Psellos (named Konstantinos till tonsure in 1054) | E86: Konstantinos 10 / Emperor Konstantinos X Doukas | K86: 60972463 / Papaioannou, Stratis | N86: Psellos Papaioannou 83 | O86: p. 178
A87: Psellos, Letter 84 | B87: Psellos Papaioannou 84 | C87: Michael 61 / Michael Psellos (named Konstantinos till tonsure in 1054) | E87: Konstantinos 10 / Emperor Konstantinos X Doukas | K87: 60972463 / Papaioannou, Stratis | N87: Psellos Papaioannou 84 | O87: p. 179
A88: Psellos, Letter 85 | B88: Psellos Papaioannou 85 | C88: Michael 61 / Michael Psellos (named Konstantinos till tonsure in 1054) | E88: Konstantinos 10 / Emperor Konstantinos X Doukas | K88: 60972463 / Papaioannou, Stratis | N88: Psellos Papaioannou 85 | O88: p. 180
A89: Psellos, Letter 86 | B89: Psellos Papaioannou 86 | C89: Michael 61 / Michael Psellos (named Konstantinos till tonsure in 1054) | E89: Konstantinos 10 / Emperor Konstantinos X Doukas | K89: 60972463 / Papaioannou, Stratis | N89: Psellos Papaioannou 86 | O89: p. 181
A90: Psellos, Letter 87 | B90: Psellos Papaioannou 87 | C90: Michael 61 / Michael Psellos (named Konstantinos till tonsure in 1054) | E90: Michael 7 / Emperor Michael VII Doukas | K90: 60972463 / Papaioannou, Stratis | N90: Psellos Papaioannou 87 | O90: p. 183
A91: Psellos, Letter 88 | B91: Psellos Papaioannou 88 | C91: Michael 61 / Michael Psellos (named Konstantinos till tonsure in 1054) | E91: Michael 7 / Emperor Michael VII Doukas | K91: 60972463 / Papaioannou, Stratis | N91: Psellos Papaioannou 88 | O91: p. 186
A92: Psellos, Letter 89 | B92: Psellos Papaioannou 89 | C92: Michael 61 / Michael Psellos (named Konstantinos till tonsure in 1054) | E92: Robert 61 / Robert Guiscard | G92: J 1072 | K92: 60972463 / Papaioannou, Stratis | N92: Psellos Papaioannou 89 | O92: p. 189
A93: Psellos, Letter 90 | B93: Psellos Papaioannou 90 | C93: Michael 61 / Michael Psellos (named Konstantinos till tonsure in 1054) | E93: Robert 61 / Robert Guiscard | G93: J 1073 | K93: 60972463 / Papaioannou, Stratis | N93: Psellos Papaioannou 90 | O93: p. 194
A94: Psellos, Letter 91 | B94: Psellos Papaioannou 91 | C94: Michael 61 / Michael Psellos (named Konstantinos till tonsure in 1054) | E94: Anonymus 2164 / Zomas, krites of Opsikion | I94: Opsikion | K94: 60972463 / Papaioannou, Stratis | N94: Psellos Papaioannou 91 | O94: p. 197
A95: Psellos, Letter 92 | B95: Psellos Papaioannou 92 | C95: Michael 61 / Michael Psellos (named Konstantinos till tonsure in 1054) | E95: Anonymus 2164 / Zomas, krites of Opsikion | I95: Opsikion | K95: 60972463 / Papaioannou, Stratis | N95: Psellos Papaioannou 92 | O95: p. 198
A96: Psellos, Letter 93 | B96: Psellos Papaioannou 93 | C96: Michael 61 / Michael Psellos (named Konstantinos till tonsure in 1054) | E96: Elias 2102 / Elias, protonotarios | K96: 60972463 / Papaioannou, Stratis | N96: Psellos Papaioannou 93 | O96: p. 201
A97: Psellos, Letter 94 | B97: Psellos Papaioannou 94 | C97: Michael 61 / Michael Psellos (named Konstantinos till tonsure in 1054) | E97: Esaias 2102 / Esaias, proximos | K97: 60972463 / Papaioannou, Stratis | N97: Psellos Papaioannou 94 | O97: p. 202
A98: Psellos, Letter 95 | B98: Psellos Papaioannou 95 | C98: Michael 61 / Michael Psellos (named Konstantinos till tonsure in 1054) | E98: Anonymus 2297 / Iasites, kouropalates | K98: 60972463 / Papaioannou, Stratis | N98: Psellos Papaioannou 95 | O98: p. 203
A99: Psellos, Letter 96 | B99: Psellos Papaioannou 96 | C99: Michael 61 / Michael Psellos (named Konstantinos till tonsure in 1054) | E99: Anonymus 2297 / Iasites, kouropalates | G99: J 1069 | K99: 60972463 / Papaioannou, Stratis | N99: Psellos Papaioannou 96 | O99: p. 208
A100: Psellos, Letter 97 | B100: Psellos Papaioannou 97 | C100: Michael 61 / Michael Psellos (named Konstantinos till tonsure in 1054) | E100: Konstantinos 2103 / Konstantinos Hierax, exiled correspondent of Michael Psellos | K100: 60972463 / Papaioannou, Stratis | N100: Psellos Papaioannou 97 | O100: p. 210
A101: Psellos, Letter 98 | B101: Psellos Papaioannou 98 | C101: Michael 61 / Michael Psellos (named Konstantinos till tonsure in 1054) | E101: Ioannes 2110 / Ioannes, protonotarios of the dromos | K101: 60972463 / Papaioannou, Stratis | N101: Psellos Papaioannou 98 | O101: p. 212
A102: Psellos, Letter 99 | B102: Psellos Papaioannou 99 | C102: Michael 61 / Michael Psellos (named Konstantinos till tonsure in 1054) | E102: Anonymus 2366 / Kalokyros, exiled acquaintance of Michael Psellos | K102: 60972463 / Papaioannou, Stratis | N102: Psellos Papaioannou 99 | O102: p. 213
A103: Psellos, Letter 100 | B103: Psellos Papaioannou 100 | C103: Michael 61 / Michael Psellos (named Konstantinos till tonsure in 1054) | E103: Symeon 2102 / Symeon Kenchres, monk | K103: 60972463 / Papaioannou, Stratis | N103: Psellos Papaioannou 100 | O103: p. 214
A104: Psellos, Letter 101 | B104: Psellos Papaioannou 101 | C104: Michael 61 / Michael Psellos (named Konstantinos till tonsure in 1054) | E104: Kekaumenos 101 / Kekaumenos Katakalon | G104: J 1059 - J 1067 | K104: 60972463 / Papaioannou, Stratis | N104: Psellos Papaioannou 101 | O104: p. 219
A105: Psellos, Letter 102 | B105: Psellos Papaioannou 102 | C105: Michael 61 / Michael Psellos (named Konstantinos till tonsure in 1054) | E105: Kekaumenos 101 / Kekaumenos Katakalon | G105: J 1059 - J 1067 | K105: 60972463 / Papaioannou, Stratis | N105: Psellos Papaioannou 102 | O105: p. 229
A106: Psellos, Letter 103 | B106: Psellos Papaioannou 103 | C106: Michael 61 / Michael Psellos (named Konstantinos till tonsure in 1054) | E106: Kekaumenos 101 / Kekaumenos Katakalon | G106: J 1059 - J 1067 | K106: 60972463 / Papaioannou, Stratis | N106: Psellos Papaioannou 103 | O106: p. 221
A107: Psellos, Letter 104 | B107: Psellos Papaioannou 104 | C107: Michael 61 / Michael Psellos (named Konstantinos till tonsure in 1054) | E107: Michael 11 / Michael I Keroularios, patriarch of Constantinople | K107: 60972463 / Papaioannou, Stratis | N107: Psellos Papaioannou 104 | O107: p. 224
A108: Psellos, Letter 105 | B108: Psellos Papaioannou 105 | C108: Michael 61 / Michael Psellos (named Konstantinos till tonsure in 1054) | E108: Michael 11 / Michael I Keroularios, patriarch of Constantinople | K108: 60972463 / Papaioannou, Stratis | N108: Psellos Papaioannou 105 | O108: p. 226
A109: Psellos, Letter 106 | B109: Psellos Papaioannou 106 | C109: Michael 61 / Michael Psellos (named Konstantinos till tonsure in 1054) | E109: Michael 11 / Michael I Keroularios, patriarch of Constantinople | G109: J 1054 [TAQ] | K109: 60972463 / Papaioannou, Stratis | N109: Psellos Papaioannou 106 | O109: p. 229
A110: Psellos, Letter 107 | B110: Psellos Papaioannou 107 | C110: Michael 61 / Michael Psellos (named Konstantinos till tonsure in 1054) | E110: Michael 11 / Michael I Keroularios, patriarch of Constantinople | G110: J 1054 [TAQ] | K110: 60972463 / Papaioannou, Stratis | N110: Psellos Papaioannou 107 | O110: p. 230
A111: Psellos, Letter 108 | B111: Psellos Papaioannou 108 | C111: Michael 61 / Michael Psellos (named Konstantinos till tonsure in 1054) | E111: Michael 11 / Michael I Keroularios, patriarch of Constantinople | K111: 60972463 / Papaioannou, Stratis | N111: Psellos Papaioannou 108 | O111: p. 231
...

Sheet Manuscripts
A1: Identifier | B1: Dating | C1: Place copied | D1: Contains text | E1: Scribe | F1: Commissioned by | G1: Authority | H1: Authority group | I1: Based on | J1: Source text/publication | K1: Source text/reference | L1: Source text/excerpt

Sheet Historical text sources
A1: Text identifier | B1: Used source | C1: Authority | D1: Authority group | E1: Based on | F1: Source text/publication | G1: Source text/reference | H1: Source text/excerpt

Sheet Births and deaths
A1: Who | B1: Which | C1: When | D1: Where | E1: Authority | F1: Authority group | G1: Based on | H1: Source text/publication | I1: Source text/reference | J1: Source text/excerpt
A2: Anna 62 / Anna Komnene, daughter of Alexios I and historian | B2: Birth | C2: J 1083 December 2 | D2: Constantinople | E2: Anna 62 / Anna Komnene, daughter of Alexios I and historian
A3: T1 Dawatanos / Diabatenos / Dawatanos, doux of Edessa | B3: Death | C3: A 511 | D3: Amida | E3: T2 Mattheos / Matthew of Edessa | H3: Chronicle of Matthew | I3: II.17
A4: Ioannes 62 / Ioannes Doukas, kaisar | B4: Birth | D4: Paphlagonia | E4: Michael 61 / Michael Psellos (named Konstantinos till tonsure in 1054) | H4: Psellos Papaioannou 68 | I4: p. 154, l. 38
A5: Basileios 2 / Emperor Basileios II Boulgaroktonos | B5: Death | C5: J 1025 | E5: 54236315 / Pertz, Georg Heinrich | H5: Annales Barenses | I5: 39-42
A6: Abu Usama 101 / Abu Usama, the cadi of Aleppo | B6: Death | C6: J 1025 | E6: 79063594 / Yaḥyā ibn Saʻīd al-Anṭākī | H6: Yahya al-Antaki | I6: 478
A7: Mawsuf 101 / Mawsuf the eunuch | B7: Death | C7: J 1025 | E7: 79063594 / Yaḥyā ibn Saʻīd al-Anṭākī | H7: Yahya al-Antaki | I7: 478
A8: Basileios 2 / Emperor Basileios II Boulgaroktonos | B8: Death | C8: J 1025, December | E8: 256344105 / Lampsidēs, Odysseus | H8: Manasses, Chronicle | I8: 5939
A9: Basileios 2 / Emperor Basileios II Boulgaroktonos | B9: Death | C9: J 1025, December 1 | E9: 14789545 / Schreiner, Peter | H9: Kleinchroniken 15 | I9: 158,5
A10: Basileios 2 / Emperor Basileios II Boulgaroktonos | B10: Death | C10: J 1025, December 12 | E10: 79063594 / Yaḥyā ibn Saʻīd al-Anṭākī | H10: Yahya al-Antaki | I10: 480
A11: Basileios 2 / Emperor Basileios II Boulgaroktonos | B11: Death | C11: J 1025, December 13 | E11: 14789545 / Schreiner, Peter | H11: Kleinchroniken 16 | I11: 165,8
A12: Basileios 2 / Emperor Basileios II Boulgaroktonos | B12: Death | C12: J 1026 | E12: 13129565 / Anonymus Barensis | H12: Anonymus Barensis | I12: 149
A13: Georgios 105 / Georgios/Giorgi I, king of Abchasia and Georgia | B13: Death | C13: J 1027, August | E13: 54176097 / Wortley, John | H13: Skylitzes (English) | I13: p. 356, n. 18
A14: Konstantinos 8 / Emperor Konstantinos VIII | B14: Death | C14: J 1028 | E14: 0009-0007-1432-0127 / Anđelović, Aleksandar | H14: Psellos: Chronographia | I14: II 10.26-8
A15: Konstantinos 8 / Emperor Konstantinos VIII | B15: Death | C15: J 1028, November 11 | E15: 14789545 / Schreiner, Peter | H15: Kleinchroniken 15 | I15: 158,7
A16: Konstantinos 8 / Emperor Konstantinos VIII | B16: Death | C16: J 1028, November 12 | E16: 79063594 / Yaḥyā ibn Saʻīd al-Anṭākī | H16: Yahya al-Antaki | I16: 488
... A22: Helena 102 / Helena, first wife of Romanos III | B22: Death | C22: J 1032 | E22: Ioannes 110 / Ioannes Skylitzes, historian | H22: Skylitzes | I22: 386.74-78
A23: Ioannes 273 / Ioannes, John VIII bar Abdun, Jacobite patriarch of Antioch | B23: Death | C23: J 1033 | F23: Kračkovskij, Ignati; Micheau, Françoise; Troupeau, Gérard | H23: Yahya al-Antaki | I23: 490
A24: Elias 103 / Elias II, patriarch of Antioch | B24: Death | C24: J 1033, September 8 | F24: Kračkovskij, Ignati; Micheau, Françoise; Troupeau, Gérard | H24: Yahya al-Antaki | I24: 520
A25: Anonymus 153 / Varangian who attempted to rape a woman in Thrakesion | B25: Death | C25: J 1034 | E25: 0009-0007-1432-0127 / Anđelović, Aleksandar | H25: Glykas | I25: 587.1-6
A26: Anonymus 153 / Varangian who attempted to rape a woman in Thrakesion | B26: Death | C26: J 1034 | E26: 0009-0007-1432-0127 / Anđelović, Aleksandar | H26: Skylitzes | I26: 394.73-77
A27: Romanos 3 / Emperor Romanos III Argyros | B27: Death | C27: J 1034 | E27: 13129565 / Anonymus Barensis | H27: Anonymus Barensis | I27: 149
A28: Romanos 3 / Emperor Romanos III Argyros | B28: Death | C28: J 1034 | E28: 84485715 / Lupus Protospatharius | H28: Lupus protospatharius | I28: 58.4-5
A29: Romanos 3 / Emperor Romanos III Argyros | B29: Death | C29: J 1034, April 11 | E29: 0009-0007-1432-0127 / Anđelović, Aleksandar | H29: Skylitzes | I29: 388.17-18
A30: Romanos 3 / Emperor Romanos III Argyros | B30: Death | C30: J 1034, April 11 | E30: 0009-0007-1432-0127 / Anđelović, Aleksandar | H30: Skylitzes | I30: 417,92
A31: Romanos 3 / Emperor Romanos III Argyros | B31: Death | C31: J 1034, April 11 | E31: 256344105 / Lampsidēs, Odysseus | H31: Manasses, Chronicle | I31: 5992-5995
A32: Romanos 3 / Emperor Romanos III Argyros | B32: Death | C32: J 1034, April 11 | E32: Ioannes 110 / Ioannes Skylitzes, historian | H32: Skylitzes | I32: 390.93-94
A33: Romanos 3 / Emperor Romanos III Argyros | B33: Death | C33: J 1034, April 11 | E33: Ioannes 110 / Ioannes Skylitzes, historian | H33: Skylitzes | I33: 392.10-12
A34: Romanos 3 / Emperor Romanos III Argyros | B34: Death | C34: J 1034, April 11 | E34: 79063594 / Yaḥyā ibn Saʻīd al-Anṭākī | H34: Yahya al-Antaki | I34: 536
A35: Romanos 3 / Emperor Romanos III Argyros | B35: Death | C35: J 1034, April 11-12 | E35: 0009-0007-1432-0127 / Anđelović, Aleksandar | H35: Psellos: Chronographia | I35: III 26.9-12
A36: Niketas 104 / Niketas, brother of Michael IV | B36: Death | C36: J 1034, September | E36: Ioannes 110 / Ioannes Skylitzes, historian | H36: Skylitzes | I36: 397.58-60
... A48: Michael 4 / Emperor Michael IV Paphlagon | B48: Death | C48: J 1041 | E48: 13129565 / Anonymus Barensis | H48: Anonymus Barensis | I48: 150
A49: Michael 4 / Emperor Michael IV Paphlagon | B49: Death | C49: J 1041, December 10 | F49: Kaldellis, Anthony; Krallis, Dimitris | H49: Attaleiates: History (English) | I49: p. 595, n. 15
A50: Michael 4 / Emperor Michael IV Paphlagon | B50: Death | C50: J 1041, December 10 | E50: Ioannes 110 / Ioannes Skylitzes, historian | H50: Skylitzes | I50: 415.50-52
A51: Michael 4 / Emperor Michael IV Paphlagon | B51: Death | C51: J 1041, December 9-10 | E51: 14789545 / Schreiner, Peter | H51: Kleinchroniken 15 | I51: 159,9
A52: Konstantinos 112 / Konstantinos Artoklines, katepano | B52: Death | C52: J 1042 | E52: 0009-0007-1432-0127 / Anđelović, Aleksandar | H52: Skylitzes | I52: 423.31-32
A53: Konstantinos 112 / Konstantinos Artoklines, katepano | B53: Death | C53: J 1042 | E53: Michael 305 / Michael Sikidites, punished as a magician | H53: Glykas | I53: 593.5-6
A54: Michael 4 / Emperor Michael IV Paphlagon | B54: Death | C54: J 1042 | E54: 84485715 / Lupus Protospatharius | H54: Lupus protospatharius | I54: 58.20-21
A55: Apolaphar Mouchoumet 101 / Ahmad al-Akhal, amir of Sicily | B55: Death | C55: J 1042, April | E55: 54176097 / Wortley, John | H55: Skylitzes (English) | I55: p. 383
A56: Anonymus 178 / Pardos, successor of Maniakes in Italy | B56: Death | C56: J 1042, October | E56: 54176097 / Wortley, John | H56: Skylitzes (English) | I56: p. 402, n. 31
A57: Georgios 62 / Georgios Maniakes | B57: Death | C57: J 1042-1043 | E57: 0009-0007-1432-0127 / Anđelović, Aleksandar | H57: Aristakes | I57: 53.2-3 (43)
A58: Anonyma 123 / wife of Dobronas, ruler of Zara and Salona | B58: Death | C58: J 1042-1055 | E58: 0009-0007-1432-0127 / Anđelović, Aleksandar | H58: Kekaumenos | I58: 236.25-27
A59: Dobronas 101 / Dobronas, ruler of Zadar and Split | B59: Death | C59: J 1042-1055 | E59: 0009-0007-1432-0127 / Anđelović, Aleksandar | H59: Kekaumenos | I59: 236.25-27
A60: Romanos 3 / Emperor Romanos III Argyros | B60: Death | C60: J 1042-1055 | E60: 0009-0007-1432-0127 / Anđelović, Aleksandar | H60: Kekaumenos | I60: 236,14
A61: Anonymus 180 / prominent Scythian (Rus) murdered at Constantinople | B61: Death | C61: J 1043 | E61: 0009-0007-1432-0127 / Anđelović, Aleksandar | H61: Skylitzes | I61: 430,41
... A84: Michael 103 / Michael Dokeianos, katepano of Italy | B84: Death | C84: J 1050 | E84: 0009-0007-1432-0127 / Anđelović, Aleksandar | H84: Attaleiates: History | I84: 34.21-24 / 27.7-9
A85: Zoe 1 / Empress Zoe | B85: Death | C85: J 1050 | F85: Kaldellis, Anthony; Krallis, Dimitris | H85: Attaleiates: History (English) | I85: n. 89
A86: Zoe 1 / Empress Zoe | B86: Death | C86: J 1050 | E86: 9429963 / Sewter, Edgar Robert Ashton | H86: Psellos: Chronographia (English) | I86: n. 135
A87: Zoe 1 / Empress Zoe | B87: Death | C87: J 1050 | E87: 9429963 / Sewter, Edgar Robert Ashton | H87: Psellos: Chronographia (English) | I87: n. 142
A88: Zoe 1 / Empress Zoe | B88: Death | C88: J 1050 | E88: 13129565 / Anonymus Barensis | H88: Anonymus Barensis | I88: 151
A89: Zoe 1 / Empress Zoe | B89: Death | C89: J 1050 | E89: 84485715 / Lupus Protospatharius | H89: Lupus protospatharius | I89: 59.9-13
A90: Zoe 1 / Empress Zoe | B90: Death | C90: J 1050 | E90: 54176097 / Wortley, John | H90: Skylitzes (English) | I90: p. 445, n. 207
A91: Konstantinos 116 / Konstantinos Arianites, doux of Adrianople | B91: Death | C91: J 1050, June | E91: Ioannes 110 / Ioannes Skylitzes, historian | H91: Skylitzes | I91: 470.89-90
A92: Leon 29 / Pope Leo IX | B92: Death | C92: J 1054 | E92: 13129565 / Anonymus Barensis | H92: Anonymus Barensis | I92: 152
A93: Konstantinos 9 / Emperor Konstantinos IX Monomachos | B93: Death | C93: J 1054-1055 | E93: 0009-0007-1432-0127 / Anđelović, Aleksandar | H93: Attaleiates: History | I93: 47.12-15 / 36.3-5
A94: Alkan 101 / Alkan, leader of the Chorasmians | B94: Death | C94: J 1054-1055 | E94: 89679890 / McGeer, Eric | H94: McGeer, Tradition and Reality | I94: p. 137
A95: Konstantinos 116 / Konstantinos Arianites, doux of Adrianople | B95: Death | C95: J 1055 | E95: 0009-0007-1432-0127 / Anđelović, Aleksandar | H95: Attaleiates: History | I95: 34.15-16 / 27.3-4
A96: Konstantinos 9 / Emperor Konstantinos IX Monomachos | B96: Death | C96: J 1055 | E96: 13129565 / Anonymus Barensis | H96: Anonymus Barensis | I96: 152
A97: Konstantinos 9 / Emperor Konstantinos IX Monomachos | B97: Death | C97: J 1055 | E97: Aristakes 101 / Aristakes Lastivertc'i / of Lastivert, Armenian historian | H97: Aristakes | I97: 95.21-23 (88)
... A104: Romanos 106 / Romanos, son of Eustathios Boilas | B104: Death | C104: J 1056 | E104: 0009-0007-1432-0127 / Anđelović, Aleksandar | H104: Boilas | I104: 21.38-39, 23.104-105
A105: Michael 149 / Michael, protos of Athos | B105: Death | C105: J 1056 [TAQ] | F105: Empress Theodora; Ioannes, spatharokandidatos and notarios | H105: Iveron 31b | I105: 2.78.23, 2.78.30
A106: Paulos 104 / Paulos, hegoumenos of Mylonas on Athos | B106: Death | C106: J 1056 [TAQ] | F106: Empress Theodora; Ioannes, spatharokandidatos and notarios | H106: Iveron 31b | I106: 2.78.23, 2.78.30
A107: Theodoulos 105 / Theodoulos, monk on Athos | B107: Death | C107: J 1056 [TAQ] | F107: Empress Theodora; Ioannes, spatharokandidatos and notarios | H107: Iveron 31b | I107: 2.78.23, 2.78.30
A108: Theopistos 101 / Theopistos, monk on Athos | B108: Death | C108: J 1056 [TAQ] | F108: Empress Theodora; Ioannes, spatharokandidatos and notarios | H108: Iveron 31b | I108: 2.78.23, 2.78.30
A109: Theodora 1 / Empress Theodora | B109: Death | C109: J 1056, August | E109: Michael 61 / Michael Psellos (named Konstantinos till tonsure in 1054) | H109: Psellos, Hypomnema | I109: 309-312
A110: Theodora 1 / Empress Theodora | B110: Death | C110: J 1056, August | E110: Ioannes 110 / Ioannes Skylitzes, historian | H110: Skylitzes | I110: 0
A111: Theodora 1 / Empress Theodora | B111: Death | C111: J 1056, August 27 | E111: 14789545 / Schreiner, Peter | H111: Kleinchroniken 14 | I111: 143.69, 160.13
A112: Theodora 1 / Empress Theodora | B112: Death | C112: J 1056, August 31 | F112: Kaldellis, Anthony; Krallis, Dimitris | H112: Attaleiates: History (English) | I112: n. 92
A113: Leon 113 / Leon Antiochos, supporter of Isaakios I Komnenos | B113: Death | C113: J 1057 | E113: 0009-0007-1432-0127 / Anđelović, Aleksandar | H113: Skylitzes | I113: 496,69
A114: Theodora 1 / Empress Theodora | B114: Death | C114: J 1057 | E114: 84485715 / Lupus Protospatharius | H114: Lupus protospatharius | I114: 59,27
A115: Anonymus 205 / Katzamountes, commander under Michael VI | B115: Death | C115: J 1057, August 20 | E115: 0009-0007-1432-0127 / Anđelović, Aleksandar | H115: Skylitzes | I115: 495.54-58
A116: Anonymus 204 / Maurokatakalos, commander under Michael VI | B116: Death | C116: J 1057, August 20 | E116: 0009-0007-1432-0127 / Anđelović, Aleksandar | H116: Skylitzes | I116: 495.54-58
A117: Pnyemios 101 / Pnyemios the Iberian, general under Michael VI | B117: Death | C117: J 1057, August 20 | E117: 0009-0007-1432-0127 / Anđelović, Aleksandar | H117: Skylitzes | I117: 495.54-58
A118: Michael 11 / Michael I Keroularios, patriarch of Constantinople | B118: Death | C118: J 1058, December 20 | E118: Michael 202 / Michael Attaleiates | H118: Attaleiates: History | I118: 65.16-66.1 / 50.10-17
A119: Michael 6 / Emperor Michael VI Stratiotikos | B119: Death | C119: J 1059 | E119: 84485715 / Lupus Protospatharius | H119: Lupus protospatharius | I119: 59,29
A120: Michael 11 / Michael I Keroularios, patriarch of Constantinople | B120: Death | C120: J 1059, January 21 | E120: 89679890 / McGeer, Eric | H120: Skylitzes Continuatus (English) | I120: p. 42, n. 21
A121: Michael 11 / Michael I Keroularios, patriarch of Constantinople | B121: Death | C121: J 1059, January 21 | F121: Kaldellis, Anthony; Polémīs, Dīmī́trios I. | H121: Psellos and the Patriarchs | I121: p. 152
A122: Isaakios 1 / Emperor Isaakios I Komnenos | B122: Death | C122: J 1059, November 22 | E122: 256344105 / Lampsidēs, Odysseus | H122: Manasses, Chronicle | I122: 6308-6311a
A123: Konstantinos 9 / Emperor Konstantinos IX Monomachos | B123: Death | C123: J 1060 [TAQ] | E123: 0009-0007-1432-0127 / Anđelović, Aleksandar | H123: Lavra 33 | I123: 197,44
A124: al-Basasiri 101 / al-Basasiri, commander of Baghdad | B124: Death | C124: J 1060, January 15 | E124: 231073465 / Gautier, Paul | H124: Bryennios | I124: 90, n. 4
A125: Isaakios 1 / Emperor Isaakios I Komnenos | B125: Death | C125: J 1060, May | E125: 14789545 / Schreiner, Peter | H125: Kleinchroniken 15 | I125: 160,16
A126: Aikaterine 101 / Aikaterine of Bulgaria, wife of Isaakios I Komnenos | B126: Death | C126: J 1063 [TPQ] | E126: 61401675 / Varzos, Kōnstantinos | H126: Varzos, Genealogy | I126: p. 47
A127: Konstantinos 13 / Konstantinos III Leichoudes, patriarch of Constantinople | B127: Death | C127: J 1063, August 9-10 | F127: Kaldellis, Anthony; Polémīs, Dīmī́trios I. | H127: Psellos and the Patriarchs | I127: p. 160
A128: Konstantinos 10 / Emperor Konstantinos X Doukas | B128: Death | C128: J 1066, May | E128: Michael 202 / Michael Attaleiates | H128: Attaleiates: History | I128: 92.4-10 / 69.9-13
A129: Ioannes 63 / Ioannes Komnenos, father of Alexios I | B129: Death | C129: J 1067, July 12 | F129: Rízou-Kouroúpou, Matoúla; Vannier, Jean-François | H129: Christos Philanthropos, note | I129: 29
A130: Konstantinos 10 / Emperor Konstantinos X Doukas | B130: Death | C130: J 1067, May | E130: 0009-0007-1432-0127 / Anđelović, Aleksandar | H130: Skylitzes Continuatus | I130: 118.2-18
A131: Konstantinos 10 / Emperor Konstantinos X Doukas | B131: Death | C131: J 1067, May | E131: 84485715 / Lupus Protospatharius | H131: Lupus protospatharius | I131: 59.42-43
A132: Ioannes 63 / Ioannes Komnenos, father of Alexios I | B132: Death | C132: J 1067, May 23 | E132: 231073465 / Gautier, Paul | H132: Bryennios | I132: 85.14-16
A133: Konstantinos 10 / Emperor Konstantinos X Doukas | B133: Death | C133: J 1067, May 23 | E133: 231073465 / Gautier, Paul | H133: Bryennios | I133: 85.11-12
A134: Konstantinos 10 / Emperor Konstantinos X Doukas | B134: Death | C134: J 1067, May 23 | E134: 256344105 / Lampsidēs, Odysseus | H134: Manasses, Chronicle | I134: 6345-6346a
A135: Konstantinos 10 / Emperor Konstantinos X Doukas | B135: Death | C135: J 1067, May 23 | E135: 14789545 / Schreiner, Peter | H135: Kleinchroniken 4 | I135: 52.2, 160.17, 170.2
A136: Ioannes 63 / Ioannes Komnenos, father of Alexios I | B136: Death | C136: J 1067. July 12 | E136: 231073465 / Gautier, Paul | H136: Kecharitomene | I136: 1855-1856
A137: Konstantinos 10 / Emperor Konstantinos X Doukas | B137: Death | C137: J 1068 | E137: 13129565 / Anonymus Barensis | H137: Anonymus Barensis | I137: 153
A138: Aboulchare 101 / Aboulchare, doux of Italy | B138: Death | C138: J 1068, June | E138: 13129565 / Anonymus Barensis | H138: Anonymus Barensis | I138: 153
A139: Eustratios 101 / Eustratios Choirosphaktes, killed at Mantzikert | B139: Death | C139: J 1071 | E139: 0009-0007-1432-0127 / Anđelović, Aleksandar | H139: Attaleiates: History | I139: 167.13 / 124.12
A140: Eustratios 101 / Eustratios Choirosphaktes, killed at Mantzikert | B140: Death | C140: J 1071 | E140: 0009-0007-1432-0127 / Anđelović, Aleksandar | H140: Skylitzes Continuatus | I140: 151.27-152.2
A141: Leon 101 / Leon, epi ton deeseon, killed at Mantzikert | B141: Death | C141: J 1071 | E141: 0009-0007-1432-0127 / Anđelović, Aleksandar | H141: Attaleiates: History | I141: 167.11-12 / 124.10-11
... A145: Robert 101 / Robert Crepin, Norman mercenary | B145: Death | C145: J 1071 [TPQ] | E145: 0009-0007-1432-0127 / Anđelović, Aleksandar | H145: Psellos: Chronographia | I145: VIIb 39.4
A146: Manuel 61 / Manuel Komnenos, eldest brother of Alexios I | B146: Death | C146: J 1071, April 17 | F146: Rízou-Kouroúpou, Matoúla; Vannier, Jean-François | H146: Christos Philanthropos, note | I146: 22
A147: Alp Arslan 51 / Alp Arslan, Seljuk Sultan | B147: Death | C147: J 1072 | E147: 0009-0007-1432-0127 / Anđelović, Aleksandar | H147: Aristakes | I147: 141.20-21 (128)
...

Sheet Relationship types
A1: Relationship type | B1: Kinship?
A2: ancestor (grandfather) | B2: yes
A3: aunt | B3: yes
A4: betrothed of granddaughter | B4: no
A5: brother | B5: yes
A6: brother (elder) | B6: yes
A7: brother (first) | B7: yes
A8: brother (full) | B8: yes
A9: brother (in fact, nephew) | B9: yes
A10: brother (in fact, uncle) | B10: yes
A11: brother (younger) | B11: yes
A12: brother-in-law | B12: yes
... A38: father-in-law (designate) | B38: no
A39: father-in-law (joint)
A40: father-in-law (potential) | B40: no
A41: father-in-law of child | B41: yes
A42: fiancé | B42: no
A43: fiancée | B43: no
A44: grand nephew | B44: yes
A45: granddaughter | B45: yes
A46: grandfather | B46: yes
A47: grandfather (maternal) | B47: yes
A48: grandfather (paternal) | B48: yes
A49: grandmother | B49: yes
A50: grandmother (maternal) | B50: yes
A51: grandmother (paternal) | B51: yes
... A151: wife (second) | B151: yes

Sheet Social relationships
A1: Main person | B1: Related person | C1: Relationship type | D1: Start date | E1: End date | F1: Authority | G1: Authority group | H1: Based on | I1: Source text/publication | J1: Source text/reference | K1: Source text/excerpt

Sheet Journeys
A1: Journey id | B1: Who travelled | C1: Group travelled | D1: Journey type | E1: Sent by person | F1: Visited person | G1: Visited place | H1: Visited when | I1: Des. Origin | J1: Des. Destination | K1: Real Origin | L1: Real Dest. | M1: Start date | N1: End date | O1: Authority | P1: Authority group | Q1: Based on | R1: Source text/publication | S1: Source text/reference | T1: Source text/excerpt

Sheet Geopolitical Events
A1: Event label | B1: Event date | C1: Event type | D1: Involved person | E1: Created place | F1: Destroyed place | G1: Challenge to authority status | H1: Intended target place of attack | I1: Intended target population | J1: Combatant individual | K1: Combatant group | L1: Authority | M1: Authority group | N1: Based on | O1: Source text/publication | P1: Source text/reference | Q1: Source text/excerpt

Sheet Authority Status
A1: Authority status label | B1: Status type | C1: Authority ascribed by | D1: Authority ascribed | E1: Geographic scope | F1: Temporal scope | G1: Authority | H1: Authority group | I1: Based on | J1: Source text/publication | K1: Source text/reference | L1: Source text/excerpt

Sheet Boulloteria
A1: Boulloterion title | B1: External URL | C1: Owner | D1: Text obverse | E1: Transl. obverse | F1: Text reverse | G1: Transl. reverse | H1: Dating | I1: Material | J1: Diameter | K1: Authority | L1: Authority group | M1: Based on | N1: Source text/publication | O1: Source text/reference | P1: Source text/excerpt

Sheet Lead seals
A1: Seal ID | B1: Seal collection | C1: Boulloterion | D1: External url

Sheet Other objects
A1: Title | B1: External identifier | C1: Description | D1: Type | E1: Documented location | F1: Documented date | G1: Creation location | H1: Creation date | I1: Decoration material | J1: Design element | K1: Material | L1: Owned by | M1: Owned by group | N1: Owned when | O1: Owned where | P1: Authority | Q1: Authority group | R1: Based on | S1: Source text/publication | T1: Source text/reference | U1: Source text/excerpt

Sheet Controlled vocabularies
A1: Social role (C2) | B1: Legal role (C12) | C1: Religious affiliation | D1: Gender | E1: Language | F1: Ethnicity | G1: Object type | H1: Material | I1: Design | J1: Place type | K1: Population label | L1: Event type | M1: Authority status type
A2: Agent | B2: Abbas | C2: Bogomil | D2: Eunuch | E2: Arabic | F2: American | G2: Gravestone | H2: Lead | I2: Candy stripes | J2: City | K2: Armenians of Edessa, 1050s to 1146 | L2: Attack | M2: Imperium
A3: Anadochos | B3: Abbess | C3: Chalcedonian | D3: Female | E3: Armenian | F3: Alan | H3: Wood | I3: Cross | J3: Theme | K3: Syrians of Edessa | L3: Annexation | M3: Ducate
A4: Armourer | B4: Abbot | C4: Christian | D4: Male | E4: French | F4: Albanian | H4: Ivory | K4: Muslims of Antioch | L4: Succession | M4: Emirate
A5: Ascetic | B5: Abbot of St Mary of the Latins | C5: Heathen | E5: Georgian | F5: Apulian | H5: Enamel
A6: Asekretissa | B6: Abbot of the Valley of Jehosaphat | C6: Jacobite | E6: Greek | F6: Arab
A7: Asketes | B7: Abydikos | C7: Jew | E7: Italian | F7: Armenian
A8: Baker | B8: Akolouthos | C8: Manichaean | E8: Latin | F8: Bulgarian
A9: Basileus (rebel) | B9: Aktouarios | C9: Muslim | E9: Persian | F9: Burgundian
A10: Bedroom attendant | B10: Amir | C10: Orthodox | E10: Turkish | F10: Byzantine
A11: Beggar | B11: Amir (chief) | C11: Paulician | F11: Cuman
A12: Blacksmith | B12: Amir of the Turcomans | C12: non-Christian | F12: English
A13: Bodyguard | B13: Anagnostes | F13: Flemish
A14: Boundary guard | B14: Anagrapheus | F14: Frank
A15: Builder | B15: Anagrapheus of the Armenian themes | F15: French
A16: Bureaucrat | B16: Anagrapheus of the West | F16: From Flanders
A17: Carpenter | B17: Anagrapheus of the eastern dromos of Malagina | F17: Genoese
A18: Caulker of ships | B18: Annonarios of the Nea church | F18: Georgian
A19: Cavalryman | B19: Anthypatos | F19: German
A20: Cleric | B20: Antigrapheus | F20: German - Swabian?
A21: Cook | B21: Antipope | F21: Greek
A22: Coppersmith | B22: Antiprosopon in the genikon | F22: Half-caste
A23: Copyist | B23: Antiprosopon in the imperial sekreton | F23: Hungarian
A24: Courtier | B24: Antiprosopon in the sekreton of the imperial sakelle | F24: Italian
... A45: Helmsman | B45: Arkarios | F45: Western European
A46: Herald | B46: Arkarios of the tameion
A47: Hermit | B47: Artoklines, Atriklines
A48: Hesychast (hermit) | B48: Asekretis
A49: Historian | B49: Atabeg
A50: Hyperperilampros | B50: Augousta
A51: Hypersebastos | B51: Augoustalios
A52: Imperial doctor | B52: Augoustos
A53: Inn-keeper | B53: Autokrator
A54: Interpreter | B54: Autokrator strategos
A55: Interpreter of the Bulgarians | B55: Autokratorissa
A56: Interpreter of the English | B56: Axiarchos
A57: Interpreter of the Romans | B57: Basileopator
... A145: Xenodochos | B145: Deacon of the Nea church
B146: Dekanos
B147: Demarchos
B148: Demarchos of the Blues
B149: Depotatos
B150: Deputy governor
B151: Deputy steward
B152: Despoina
B153: Despotes
B154: Despotis
B155: Deutereuon
B156: Deuteros of the charitable foundations
B157: Deuteros of the stratiotikon
... B920: Zoste

Sheet OLD deaths
A1: Name | B1: Code | C1: Source | D1: Source loc | E1: Description in PBW | F1: Death date | G1: Dating authority | H1: Outside Source | I1: Notes | L1: Who | M1: Which | N1: When | O1: Where | P1: Authority | Q1: Authority group | R1: Based on | S1: Source text/publication | T1: Source text/reference | U1: Source text/excerpt
A2: Basileios | B2: 2 | C2: Annales Barenses | D2: 39-42 | E2: His death in the second year (?), by the obstruction of sins, brought the expedition against Sicily to an end, and all returned without success | F2: J 1025 | G2: Editor | H2: n. 24 | I2: The footnote 24 of the edition clearly states that Basil died in 1025. | L2: =_xlfn.XLOOKUP(_xlfn.CONCAT(A2, " ", B2), Persons!B:B, Persons!S:S) -> Basileios 2 / Emperor Basileios II Boulgaroktonos | M2: Death | N2: =F2 -> J 1025 | P2: =_xlfn.XLOOKUP(C2,'Text publications'!A:A,'Text publications'!G:G,"") -> 54236315 / Pertz, Georg Heinrich | S2: =C2 -> Annales Barenses | T2: =D2 -> 39-42
A3: Abu Usama | B3: 101 | C3: Yahya al-Antaki | D3: 478 | E3: Was killed by <Salih 101> as one of the leaders of the revolt at Aleppo, together with <Mawsuf 101> | F3: J 1025 | G3: Source | L3: =_xlfn.XLOOKUP(_xlfn.CONCAT(A3, " ", B3), Persons!B:B, Persons!S:S) -> Abu Usama 101 / Abu Usama, the cadi of Aleppo | M3: Death | N3: =F3 -> J 1025 | P3: =_xlfn.XLOOKUP(C3,'Text publications'!A:A,'Text publications'!D:D,"") -> 79063594 / Yaḥyā ibn Saʻīd al-Anṭākī | S3: =C3 -> Yahya al-Antaki | T3: =D3 -> 478
A4: Mawsuf | B4: 101 | C4: Yahya al-Antaki | D4: 478 | E4: Was killed by <Salih 101> as one of the leaders of the revolt at Aleppo, together with <Abu Usama 101> | F4: J 1025 | G4: Source | L4: =_xlfn.XLOOKUP(_xlfn.CONCAT(A4, " ", B4), Persons!B:B, Persons!S:S) -> Mawsuf 101 / Mawsuf the eunuch | M4: Death | N4: =F4 -> J 1025 | P4: =_xlfn.XLOOKUP(C4,'Text publications'!A:A,'Text publications'!D:D,"") -> 79063594 / Yaḥyā ibn Saʻīd al-Anṭākī | S4: =C4 -> Yahya al-Antaki | T4: =D4 -> 478
A5: Basileios | B5: 2 | C5: Manasses, Chronicle | D5: 5939 | E5: He died in extreme old age | F5: J 1025, December | G5: Editor | H5: p. 320, n. 5937-39a | I5: Manasses doesn't state the year but he says that Basileios died at the age of 50, and the editor of the text says that this was December 1025. | L5: =_xlfn.XLOOKUP(_xlfn.CONCAT(A5, " ", B5), Persons!B:B, Persons!S:S) -> Basileios 2 / Emperor Basileios II Boulgaroktonos | M5: Death | N5: =F5 -> J 1025, December | P5: =_xlfn.XLOOKUP(C5,'Text publications'!A:A,'Text publications'!G:G,"") -> 256344105 / Lampsidēs, Odysseus | S5: =C5 -> Manasses, Chronicle | T5: =D5 -> 5939
A6: Basileios | B6: 2 | C6: Kleinchroniken 15 | D6: 158,5 | E6: Died after a reign of 20 years | F6: J 1025, December 1 | G6: Source | L6: =_xlfn.XLOOKUP(_xlfn.CONCAT(A6, " ", B6), Persons!B:B, Persons!S:S) -> Basileios 2 / Emperor Basileios II Boulgaroktonos | M6: Death | N6: =F6 -> J 1025, December 1 | S6: =C6 -> Kleinchroniken 15 | T6: =D6 -> 158,5
A7: Basileios | B7: 2 | C7: Yahya al-Antaki | D7: 480 | E7: Died at the age of 68 after a reign of 49 years and 11 months and was buried in vestments worth slightly more than 20 dinars | F7: J 1025, December 12 | G7: Source | I7: Sunday, 12 Kanun al-Awwal 1337 | L7: =_xlfn.XLOOKUP(_xlfn.CONCAT(A7, " ", B7), Persons!B:B, Persons!S:S) -> Basileios 2 / Emperor Basileios II Boulgaroktonos | M7: Death | N7: =F7 -> J 1025, December 12 | P7: =_xlfn.XLOOKUP(C7,'Text publications'!A:A,'Text publications'!D:D,"") -> 79063594 / Yaḥyā ibn Saʻīd al-Anṭākī | S7: =C7 -> Yahya al-Antaki | T7: =D7 -> 480
A8: Basileios | B8: 2 | C8: Kleinchroniken 16 | D8: 165,8 | E8: Died after a reign of 50 years at the age of 77 | F8: J 1025, December 13 | G8: Source | I8: on December 13 of the 9th indiction in the year 65 | L8: =_xlfn.XLOOKUP(_xlfn.CONCAT(A8, " ", B8), Persons!B:B, Persons!S:S) -> Basileios 2 / Emperor Basileios II Boulgaroktonos | M8: Death | N8: =F8 -> J 1025, December 13 | P8: 14789545 / Schreiner, Peter | S8: =C8 -> Kleinchroniken 16 | T8: =D8 -> 165,8
A9: Basileios | B9: 2 | C9: Anonymus Barensis | D9: 149 | E9: He died, and his brother <Konstantinos 8> succeeded him | F9: J 1026 | G9: Source | L9: =_xlfn.XLOOKUP(_xlfn.CONCAT(A9, " ", B9), Persons!B:B, Persons!S:S) -> Basileios 2 / Emperor Basileios II Boulgaroktonos | M9: Death | N9: =F9 -> J 1026 | P9: =_xlfn.XLOOKUP(C9,'Text publications'!A:A,'Text publications'!D:D,"") -> 13129565 / Anonymus Barensis | S9: =C9 -> Anonymus Barensis | T9: =D9 -> 149
A10: Georgios | B10: 105 | C10: Skylitzes | D10: 377,19 | E10: Died from an illness while the Roman army was gathering to attack Berroia in Syria | F10: J 1027, August | G10: Wortley | H10: p. 356, n. 18 | I10: Skylitzes doesn't mention the year, but the English translator says that George of Abasgia died on 16 August 1027. | L10: =_xlfn.XLOOKUP(_xlfn.CONCAT(A10, " ", B10), Persons!B:B, Persons!S:S) -> Georgios 105 / Georgios/Giorgi I, king of Abchasia and Georgia | M10: Death | N10: =F10 -> J 1027, August | P10: 54176097 / Wortley, John | S10: Skylitzes (English) | T10: =H10 -> p. 356, n. 18
A11: Konstantinos | B11: 8 | C11: Psellos: Chronographia | D11: II 10.26-8 | E11: After surviving long enough to see the marriage (of <Zoe 1> and <Romanos 3>) he quit life, leaving the power to his son-in-law Romanos | F11: J 1028 | G11: Aleksandar | H11: Source, II 10.26-8 | I11: Psellos, as usual, does not provide the date, only the claim that Konstantinos VIII died the same year when Zoë's and Romanos' wedding took place, which is autumn of 1028. | L11: =_xlfn.XLOOKUP(_xlfn.CONCAT(A11, " ", B11), Persons!B:B, Persons!S:S) -> Konstantinos 8 / Emperor Konstantinos VIII | M11: Death | N11: =F11 -> J 1028 | P11: 0009-0007-1432-0127 / Anđelović, Aleksandar | S11: =C11 -> Psellos: Chronographia | T11: =D11 -> II 10.26-8
A12: Konstantinos | B12: 8 | C12: Kleinchroniken 15 | D12: 158,7 | E12: Died after a reign of 3 years | F12: J 1028, November 11 | G12: Source | I12: on November 11 of the 12th indiction in the year 6537 | L12: =_xlfn.XLOOKUP(_xlfn.CONCAT(A12, " ", B12), Persons!B:B, Persons!S:S) -> Konstantinos 8 / Emperor Konstantinos VIII | M12: Death | N12: =F12 -> J 1028, November 11 | P12: 14789545 / Schreiner, Peter | S12: =C12 -> Kleinchroniken 15 | T12: =D12 -> 158,7
A13: Konstantinos | B13: 8 | C13: Yahya al-Antaki | D13: 488 | E13: Died five days after marrying <Zoe 1> to <Romanos 3>, at the age of 69 | F13: J 1028, November 12 | G13: Source | L13: =_xlfn.XLOOKUP(_xlfn.CONCAT(A13, " ", B13), Persons!B:B, Persons!S:S) -> Konstantinos 8 / Emperor Konstantinos VIII | M13: Death | N13: =F13 -> J 1028, November 12 | P13: =_xlfn.XLOOKUP(C13,'Text publications'!A:A,'Text publications'!D:D,"") -> 79063594 / Yaḥyā ibn Saʻīd al-Anṭākī | S13: =C13 -> Yahya al-Antaki | T13: =D13 -> 488
A14: Konstantinos | B14: 8 | C14: Skylitzes | D14: 374.40-42 | E14: Died at the age of 70, three days after the marriage of his daughter <Zoe 1> to <Romanos 3> | F14: J 1028, November 9 | G14: Source | I14: At the beginning of this passage, Skylitzes says that Constantine fell ill "On 9 November, twelfth year of the indiction, AM 6537" which is 1028. | L14: =_xlfn.XLOOKUP(_xlfn.CONCAT(A14, " ", B14), Persons!B:B, Persons!S:S) -> Konstantinos 8 / Emperor Konstantinos VIII | M14: Death | N14: =F14 -> J 1028, November 9 | P14: =_xlfn.XLOOKUP(C14,'Text publications'!A:A,'Text publications'!D:D,"") -> Ioannes 110 / Ioannes Skylitzes, historian | S14: =C14 -> Skylitzes | T14: =D14 -> 374.40-42
A15: Konstantinos | B15: 8 | C15: Anonymus Barensis | D15: 149 | E15: He died, and his son-in-law <Romanos 3> succeeded him | F15: J 1029 | G15: Source | I15: Mill. XXIX. Ind. XII | L15: =_xlfn.XLOOKUP(_xlfn.CONCAT(A15, " ", B15), Persons!B:B, Persons!S:S) -> Konstantinos 8 / Emperor Konstantinos VIII | M15: Death | N15: =F15 -> J 1029 | P15: =_xlfn.XLOOKUP(C15,'Text publications'!A:A,'Text publications'!D:D,"") -> 13129565 / Anonymus Barensis | S15: =C15 -> Anonymus Barensis | T15: =D15 -> 149
A16: Konstantinos | B16: 8 | C16: Lupus protospatharius | D16: 57,4 | E16: Died, and appointed <Romanos 3> in his place | F16: J 1029 | G16: Source | I16: Worthy of note is that it doesn't mean that it was the year 1029, but Lupus protospatharius is known for starting the year in September. | L16: =_xlfn.XLOOKUP(_xlfn.CONCAT(A16, " ", B16), Persons!B:B, Persons!S:S) -> Konstantinos 8 / Emperor Konstantinos VIII | M16: Death | N16: =F16 -> J 1029 | P16: =_xlfn.XLOOKUP(C16,'Text publications'!A:A,'Text publications'!D:D,"") -> 84485715 / Lupus Protospatharius | S16: =C16 -> Lupus protospatharius | T16: =D16 -> 57,4
A17: Mousaraph | B17: 101 | C17: Skylitzes | D17: 383.85-86 | E17: Was killed after he was captured in the region of Tripoli while fleeing from his fort at Menikos | F17: J 1031, December 1 | G17: Wortley | H17: p. 362, n. 44 | I17: Skylitzes doesn't mention the year, but the English translator claims that Mousaraph was killed in December 1, 1031, see p. 362, n. 44. | L17: =_xlfn.XLOOKUP(_xlfn.CONCAT(A17, " ", B17), Persons!B:B, Persons!S:S) -> Mousaraph 101 / Nasr ibn Musharraf, Arab opponent of Antioch | M17: Death | N17: =F17 -> J 1031, December 1 | P17: 54176097 / Wortley, John | S17: Skylitzes (English) | T17: =H17 -> p. 362, n. 44
A18: Konstantinos | B18: 101 | C18: Skylitzes | D18: 385.48-49 | E18: Died after throwing himself off the walls at the palace of Blachernai breaking his neck, and his body was thrown where people committing suicide are usually cast | F18: J 1031-1032 | G18: Source | I18: Skylitzes here focuses on AM 6540 which is September 1, 1031 - August 31, 1032, and terminus ante quem here is July 28. Therefore Konstantinos Diogenes died, according to Skylitzes, either in late 1031 or in the first half of 1032. | L18: =_xlfn.XLOOKUP(_xlfn.CONCAT(A18, " ", B18), Persons!B:B, Persons!S:S) -> Konstantinos 101 / Konstantinos Diogenes, father of Romanos IV | M18: Death | N18: =F18 -> J 1031-1032 | P18: =_xlfn.XLOOKUP(C18,'Text publications'!A:A,'Text publications'!D:D,"") -> Ioannes 110 / Ioannes Skylitzes, historian | S18: =C18 -> Skylitzes | T18: =D18 -> 385.48-49
A19: Helena | B19: 102 | C19: Skylitzes | D19: 386.74-78 | E19: When she died, her husband <Romanos 3> distributed many gifts in her memory | F19: J 1032 | G19: Source | I19: AM 6540, which is 1032 | L19: =_xlfn.XLOOKUP(_xlfn.CONCAT(A19, " ", B19), Persons!B:B, Persons!S:S) -> Helena 102 / Helena, first wife of Romanos III | M19: Death | N19: =F19 -> J 1032 | P19: =_xlfn.XLOOKUP(C19,'Text publications'!A:A,'Text publications'!D:D,"") -> Ioannes 110 / Ioannes Skylitzes, historian | S19: =C19 -> Skylitzes | T19: =D19 -> 386.74-78
A20: Ioannes | B20: 273 | C20: Yahya al-Antaki | D20: 490 | E20: Died after 3 years in exile | F20: J 1033 | G20: Editor | H20: p. 490, n. 47 | I20: Apart from Yahya who informs us that Ioannes died after three years in exile, the editor of Yahya notes that "we know that this patriarch was exiled to the convent of Mount Ganos, in Thrace, on October 13, 1029; he was to die in 1033," see p. 490, n. 47. | L20: =_xlfn.XLOOKUP(_xlfn.CONCAT(A20, " ", B20), Persons!B:B, Persons!S:S) -> Ioannes 273 / Ioannes, John VIII bar Abdun, Jacobite patriarch of Antioch | M20: Death | N20: =F20 -> J 1033 | Q20: =_xlfn.XLOOKUP(C20,'Text publications'!A:A,'Text publications'!H:H,"") -> Kračkovskij, Ignati; Micheau, Françoise; Troupeau, Gérard | S20: =C20 -> Yahya al-Antaki | T20: =D20 -> 490
A21: Elias | B21: 103 | C21: Yahya al-Antaki | D21: 520 | E21: Died after a reign of 1 year, 5 months and 8 days | F21: J 1033, September 8 | G21: Editor | H21: p. 520, n. 35 | I21: Yahya doesn't explicitly mention the date of the death, but says that Elias ascended on the throne on April 1 of the year 1343 according to the Alexandrian calendar (1032) and that he died after reigning for 1 year, 5 months and 8 days, which makes it 8 September 1033, which the editor also notes, see p. 520, n. 35. | L21: =_xlfn.XLOOKUP(_xlfn.CONCAT(A21, " ", B21), Persons!B:B, Persons!S:S) -> Elias 103 / Elias II, patriarch of Antioch | M21: Death | N21: =F21 -> J 1033, September 8 | Q21: =_xlfn.XLOOKUP(C21,'Text publications'!A:A,'Text publications'!H:H,"") -> Kračkovskij, Ignati; Micheau, Françoise; Troupeau, Gérard | S21: =C21 -> Yahya al-Antaki | T21: =D21 -> 520
A22: Anonymus | B22: 153 | C22: Glykas | D22: 587.1-6 | E22: Was killed with his own sword by the woman he tried to rape (<Anonyma 112>) and his body was thrown away without a burial by his fellow Varangians, who offered his possessions to her | F22: J 1034 | G22: Aleksandar | H22: Source, 586 | I22: Glykas also refers to Romanos' death and Michael's ascent to the throne, which is 1034, although he doesn't state the year exactly: Κατ' ἐκεῖνο δὴ καιροῦ καὶ τοιοῦτόν τι συνέβη ἐν τῷ θέματι τῶν Θρᾳκησίων. | L22: =_xlfn.XLOOKUP(_xlfn.CONCAT(A22, " ", B22), Persons!B:B, Persons!S:S) -> Anonymus 153 / Varangian who attempted to rape a woman in Thrakesion | M22: Death | N22: =F22 -> J 1034 | P22: 0009-0007-1432-0127 / Anđelović, Aleksandar | S22: =C22 -> Glykas | T22: =D22 -> 587.1-6
A23: Anonymus | B23: 153 | C23: Skylitzes | D23: 394.73-77 | E23: Was killed instantly by a woman (<Anonyma 112>) who hit him with his own sword at the heart, and his body was left unburied and was thrown away by his fellow-Varangians, following the law of those who die a violent death | F23: J 1034 | G23: Aleksandar | H23: Souce, 394 | I23: Actually Skylitzes does date this event, in his own way: he starts this story by saying "In that year something else worthy of note took place", and this whole chapter is about Michael IV Paphlagonian's ascent to throne, which occurred in 1034, as recorded in Psellos' Chronographia. | L23: =_xlfn.XLOOKUP(_xlfn.CONCAT(A23, " ", B23), Persons!B:B, Persons!S:S) -> Anonymus 153 / Varangian who attempted to rape a woman in Thrakesion | M23: Death | N23: =F23 -> J 1034 | P23: 0009-0007-1432-0127 / Anđelović, Aleksandar | S23: =C23 -> Skylitzes | T23: =D23 -> 394.73-77
A24: Romanos | B24: 3 | C24: Anonymus Barensis | D24: 149 | E24: He died, and was succeeded by <Michael 4> | F24: J 1034 | G24: Source | I24: Mill. XXXIV. Ind. II | L24: =_xlfn.XLOOKUP(_xlfn.CONCAT(A24, " ", B24), Persons!B:B, Persons!S:S) -> Romanos 3 / Emperor Romanos III Argyros | M24: Death | N24: =F24 -> J 1034 | P24: =_xlfn.XLOOKUP(C24,'Text publications'!A:A,'Text publications'!D:D,"") -> 13129565 / Anonymus Barensis | S24: =C24 -> Anonymus Barensis | T24: =D24 -> 149
A25: Romanos | B25: 3 | C25: Lupus protospatharius | D25: 58.4-5 | E25: He died in Constantinople, to be succeeded by <Michael 4> | F25: J 1034 | G25: Source | L25: =_xlfn.XLOOKUP(_xlfn.CONCAT(A25, " ", B25), Persons!B:B, Persons!S:S) -> Romanos 3 / Emperor Romanos III Argyros | M25: Death | N25: =F25 -> J 1034 | P25: =_xlfn.XLOOKUP(C25,'Text publications'!A:A,'Text publications'!D:D,"") -> 84485715 / Lupus Protospatharius | S25: =C25 -> Lupus protospatharius | T25: =D25 -> 58.4-5
A26: Romanos | B26: 3 | C26: Skylitzes | D26: 388.17-18 | E26: His death prevented him from fulfilling his wish to rebuild the Holy Sepulchre in Jerusalem | F26: J 1034, April 11 | G26: Aleksandar | H26: Source, 390 | I26: No date provided in this section. However, Skylitzes actually very precisely and clearly dates Romanos' death in another section, in 390, saying that "he lasted until 11 April, second year of the indiction, AM 6542." Which is April 11, 1034, see below. | L26: =_xlfn.XLOOKUP(_xlfn.CONCAT(A26, " ", B26), Persons!B:B, Persons!S:S) -> Romanos 3 / Emperor Romanos III Argyros | M26: Death | N26: =F26 -> J 1034, April 11 | P26: 0009-0007-1432-0127 / Anđelović, Aleksandar | S26: =C26 -> Skylitzes | T26: =D26 -> 388.17-18
A27: Romanos | B27: 3 | C27: Skylitzes | D27: 417,92 | E27: It was said that he died as a result of treachery | F27: J 1034, April 11 | G27: Aleksandar | H27: Source, 390 | I27: No date provided in this section. However, Skylitzes actually very precisely and clearly dates Romanos' death, in 390, saying that "he lasted until 11 April, second year of the indiction, AM 6542." Which is April 11, 1034. Also, some manuscripts of Skylitzes state here 'assassination' instead of 'treachery'. | L27: =_xlfn.XLOOKUP(_xlfn.CONCAT(A27, " ", B27), Persons!B:B, Persons!S:S) -> Romanos 3 / Emperor Romanos III Argyros | M27: Death | N27: =F27 -> J 1034, April 11 | P27: 0009-0007-1432-0127 / Anđelović, Aleksandar | S27: =C27 -> Skylitzes | T27: =D27 -> 417,92
A28: Romanos | B28: 3 | C28: Manasses, Chronicle | D28: 5992-5995 | E28: They fell in a murderous manner upon the emperor, who was taking care of his body and relaxing in the bath, and strangled him | F28: J 1034, April 11 | G28: Editor | H28: p. 323, n. 5996-99 | I28: In the section chosen for death description by PBW editors Manasses does not provide any dating, however two verses later he says that Romanos ruled for five and a half years. Also, the editor of Manasses states that Romanos died on April 11, 1034, see p. 323, n. 5996-99. | L28: =_xlfn.XLOOKUP(_xlfn.CONCAT(A28, " ", B28), Persons!B:B, Persons!S:S) -> Romanos 3 / Emperor Romanos III Argyros | M28: Death | N28: =F28 -> J 1034, April 11 | P28: =_xlfn.XLOOKUP(C28,'Text publications'!A:A,'Text publications'!G:G,"") -> 256344105 / Lampsidēs, Odysseus | S28: =C28 -> Manasses, Chronicle | T28: =D28 -> 5992-5995
A29: Romanos | B29: 3 | C29: Skylitzes | D29: 390.93-94 | E29: Was drowned in the swimming pool of the Great Palace bath by <Michael 4>'s men | F29: J 1034, April 11 | G29: Source | L29: =_xlfn.XLOOKUP(_xlfn.CONCAT(A29, " ", B29), Persons!B:B, Persons!S:S) -> Romanos 3 / Emperor Romanos III Argyros | M29: Death | N29: =F29 -> J 1034, April 11 | P29: =_xlfn.XLOOKUP(C29,'Text publications'!A:A,'Text publications'!D:D,"") -> Ioannes 110 / Ioannes Skylitzes, historian | S29: =C29 -> Skylitzes | T29: =D29 -> 390.93-94
A30: Romanos | B30: 3 | C30: Skylitzes | D30: 392.10-12 | E30: Was buried in the monastery of the Peribleptos which he had founded | F30: J 1034, April 11 | G30: Source | L30: =_xlfn.XLOOKUP(_xlfn.CONCAT(A30, " ", B30), Persons!B:B, Persons!S:S) -> Romanos 3 / Emperor Romanos III Argyros | M30: Death | N30: =F30 -> J 1034, April 11 | P30: =_xlfn.XLOOKUP(C30,'Text publications'!A:A,'Text publications'!D:D,"") -> Ioannes 110 / Ioannes Skylitzes, historian | S30: =C30 -> Skylitzes | T30: =D30 -> 392.10-12
A31: Romanos | B31: 3 | C31: Yahya al-Antaki | D31: 536 | E31: Suffered from tuberculosis, died suddenly in his bath and was buried at the monastery he had founded in the tomb he had prepared | F31: J 1034, April 11 | G31: Source | L31: =_xlfn.XLOOKUP(_xlfn.CONCAT(A31, " ", B31), Persons!B:B, Persons!S:S) -> Romanos 3 / Emperor Romanos III Argyros | M31: Death | N31: =F31 -> J 1034, April 11 | P31: =_xlfn.XLOOKUP(C31,'Text publications'!A:A,'Text publications'!D:D,"") -> 79063594 / Yaḥyā ibn Saʻīd al-Anṭākī | S31: =C31 -> Yahya al-Antaki | T31: =D31 -> 536
A32: Romanos | B32: 3 | C32: Psellos: Chronographia | D32: III 26.9-12 | E32: In this state (of health) he completed the preliminary rites of our common resurrection and at the same time was preparing himself to go forth to the public festival next day. Before day he set out to use the baths there in the palace, without an escort and not close to death: in a perfectly normal way he went up to anoint himself and bathe and purify his body. He entered the bath, first thoroughly cleansed his head, then showered his body too; since he was breathing strongly, he consigned himself to the swimming pool which had been deepened in the middle. At first he swam pleasurably in the water and floated lightly, spurting water with great pleasure and refreshing himself; later some of his attendants went in to support him and give him a rest, as he had prescribed. <Michael 61> is unable to say accurately whether the attendants who went into the bath with him committed some crime against him. Those who have linked other events with this say that when he plunged his head into the water, as he was in the habit of doing, (his attendants) pressed on his neck and held on for a long time, then released him and left. His breath lightened him and made him appear on the water almost breathless, floating at random like a cork. When he had recovered breath a little, he realised what a dreadful plight he was in, and stretching out a hand begged for someone to take hold of him and set him on his feet. One man took pity on him and his condition, put his hands under him, embraced him and drew him out; carrying him as he was he set him down on a couch in a wretched state. When an outcry arose (as he was lifted from the bath), <Zoe 1> herself was among others who came along, without a bodyguard, apparently in terrible grief; after seeing him, she left again, having assured herself by looking that he would die. He groaned heavy and deep and looked around hither and thither, unable to speak but showing what he wanted by signs and nods; as no one understood him, he closed his eyes and began to breathe heavily again. Then suddenly there flowed out from his gaping mouth blackish coagulated matter; at this he gasped two or three times and departed life. So he died, after being master of the empire for five and a half years. | F32: J 1034, April 11-12 | G32: Aleksandar | H32: Source, III-IV | I32: [I merged thirteen subsequent entries about Romanos' death from Chronographia into one as they all refer to the same passage from Psellos' Chronographia (III.26.9-IV.1.2)]. This huge description does not pertain to dating at all, so there is no date or year provided, except that Romanos died after reigning for 5,5 years and that it was Good Friday [11/12 April 1034] | L32: =_xlfn.XLOOKUP(_xlfn.CONCAT(A32, " ", B32), Persons!B:B, Persons!S:S) -> Romanos 3 / Emperor Romanos III Argyros | M32: Death | N32: =F32 -> J 1034, April 11-12 | P32: 0009-0007-1432-0127 / Anđelović, Aleksandar | S32: =C32 -> Psellos: Chronographia | T32: =D32 -> III 26.9-12
A33: Niketas | B33: 104 | C33: Skylitzes | D33: 397.58-60 | E33: Died and was succeeded as doux of Antioch by his brother <Konstantinos 64> | F33: J 1034, September | G33: Source | I33: "In the month of September, AM 6543" [1034] is the last date Skylitzes mentions before mentioning Niketas' death. | L33: =_xlfn.XLOOKUP(_xlfn.CONCAT(A33, " ", B33), Persons!B:B, Persons!S:S) -> Niketas 104 / Niketas, brother of Michael IV | M33: Death | N33: =F33 -> J 1034, September | P33: =_xlfn.XLOOKUP(C33,'Text publications'!A:A,'Text publications'!D:D,"") -> Ioannes 110 / Ioannes Skylitzes, historian | S33: =C33 -> Skylitzes | T33: =D33 -> 397.58-60
A34: Aleim | B34: 101 | C34: Skylitzes | D34: 389.47-48 | E34: Was killed by <Niketas 103> Pegonites when the latter captured the fort of Berkri | F34: J 1035 | G34: Aleksandar | H34: Blöndal, 53 | I34: Skylitzes just mentions that Aleim and his son were killed by Niketas Pegonites, without mentioning the year. However in other sources I found that the siege of fort Berkri happened in 1035, when, I suppose, Aleim was killed as well, according to Skylitze's account. Interestingly, in Pegonites' army there were Varangians, see Sigfús Blöndal, The Varangians of Byzantium (Cambridge: CUP, 1978), 53. | L34: =_xlfn.XLOOKUP(_xlfn.CONCAT(A34, " ", B34), Persons!B:B, Persons!S:S) -> Aleim 101 / Aleim, Arab commander of the fort of Berkri | M34: Death | N34: =F34 -> J 1035 | P34: 0009-0007-1432-0127 / Anđelović, Aleksandar | S34: =C34 -> Skylitzes | T34: =D34 -> 389.47-48
A35: Anonymus | B35: 151 | C35: Skylitzes | D35: 389.47-48 | E35: Was killed by <Niketas 103> Pegonites when the latter captured the fort of Berkri | F35: J 1035 | G35: Aleksandar | H35: Blöndal, 53 | I35: Skylitzes just mentions that Aleim and his son were killed by Niketas Pegonites, without mentioning the year. However in other sources I found that the siege of fort Berkri happened in 1035, when, I suppose, Aleim was killed as well, according to Skylitzes' account. Interestingly, in Pegonites' army there were Varangians, see Sigfús Blöndal, The Varangians of Byzantium (Cambridge: CUP, 1978), 53. | L35: =_xlfn.XLOOKUP(_xlfn.CONCAT(A35, " ", B35), Persons!B:B, Persons!S:S) -> Anonymus 151 / son of Aleim, the commander of the fort of Berkrin | M35: Death | N35: =F35 -> J 1035 | P35: 0009-0007-1432-0127 / Anđelović, Aleksandar | S35: =C35 -> Skylitzes | T35: =D35 -> 389.47-48
A36: Jaroslav | B36: 101 | C36: Skylitzes | D36: 399.13-15 | E36: Died and was succeeded by <Zinisthlabos 101> | F36: J 1036 | G36: Source | I36: Skylitzes says at the beginning of this passage "AM 6544, fourth year of the indiction, in the spring" which is 1036. | L36: =_xlfn.XLOOKUP(_xlfn.CONCAT(A36, " ", B36), Persons!B:B, Persons!S:S) -> Jaroslav 101 / Jaroslav, ruler of the Rus | M36: Death | N36: =F36 -> J 1036 | P36: =_xlfn.XLOOKUP(C36,'Text publications'!A:A,'Text publications'!D:D,"") -> Ioannes 110 / Ioannes Skylitzes, historian | S36: =C36 -> Skylitzes | T36: =D36 -> 399.13-15
A37: Nesisthlabos | B37: 101 | C37: Skylitzes | D37: 399.13-15 | E37: Died and was succeeded by <Zinisthlabos 101> | F37: J 1036 | G37: Source | I37: Skylitzes says at the beginning of this passage "AM 6544, fourth year of the indiction, in the spring" which is 1036. | L37: =_xlfn.XLOOKUP(_xlfn.CONCAT(A37, " ", B37), Persons!B:B, Persons!S:S) -> Nesisthlabos 101 / Nesisthlabos, ruler of the Rus' | M37: Death | N37: =F37 -> J 1036 | P37: =_xlfn.XLOOKUP(C37,'Text publications'!A:A,'Text publications'!D:D,"") -> Ioannes 110 / Ioannes Skylitzes, historian | S37: =C37 -> Skylitzes | T37: =D37 -> 399.13-15
A38: Amer | B38: 102 | C38: Skylitzes | D38: 399,17 | E38: After his death his wife (<Anonyma 114>) sent embassies to the emperor (<Michael 4>) | F38: J 1036, June | G38: Source | I38: "AM 6544, fourth year of the indiction, in the spring" [1036]". Amer (Amr) died on June 13, 1036. | L38: =_xlfn.XLOOKUP(_xlfn.CONCAT(A38, " ", B38), Persons!B:B, Persons!S:S) -> Amer 102 / Amer, amir of Egypt | M38: Death | N38: =F38 -> J 1036, June | P38: =_xlfn.XLOOKUP(C38,'Text publications'!A:A,'Text publications'!D:D,"") -> Ioannes 110 / Ioannes Skylitzes, historian | S38: =C38 -> Skylitzes | T38: =D38 -> 399,17
A39: Ioannes | B39: 109 | C39: Skylitzes | D39: 400,32 | E39: Died and was succeeded by <Leon 108> | F39: J 1036-1037 | G39: Aleksandar | H39: Source, 399 | I39: Skilitzes' previous chapter was about the year 1036 (fifth year of the indiction, AM 6546), and Leo of Ohrid was installed in 1037, so John died sometime 1036/7. | L39: =_xlfn.XLOOKUP(_xlfn.CONCAT(A39, " ", B39), Persons!B:B, Persons!S:S) -> Ioannes 109 / Ioannes, appointed archbishop of Bulgaria under Michael IV | M39: Death | N39: =F39 -> J 1036-1037 | P39: 0009-0007-1432-0127 / Anđelović, Aleksandar | S39: =C39 -> Skylitzes | T39: =D39 -> 400,32
A40: Ioannes | B40: 272 | C40: Psellos, Monodies (Gautier) 98-104 | D40: 98.2, 17-18, 165-166 | E40: He died at a great age, probably in Constantinople, without having previously suffered illness, and received a monody from <Michael 61> | F40: J 1039 [TPQ] | G40: Aleksandar | H40: Source, 85 | I40: The date of his death is unknown, but it was certainly after 1039, when Ioannes, the metropolitan of Melitene, signed a synodical document; moreover, he most certainly survived till the middle of the 11th century, which Psellos also hints to when he says that Ioannes "had carried the burden of the episcopate to his extreme old age," see Gautier's edition of Psellos' Monodies used for PBW, p. 85. | L40: =_xlfn.XLOOKUP(_xlfn.CONCAT(A40, " ", B40), Persons!B:B, Persons!S:S) -> Ioannes 272 / Ioannes, metropolitan of Melitene who persecuted Jacobites [1027, 1028, 1029, 1032, 1039] | M40: Death | N40: =F40 -> J 1039 [TPQ] | P40: 0009-0007-1432-0127 / Anđelović, Aleksandar | S40: =C40 -> Psellos, Monodies (Gautier) 98-104 | T40: =D40 -> 98.2, 17-18, 165-166
A41: Ioannes | B41: 111 | C41: Skylitzes | D41: 411,63 | E41: Was cut into pieces by the Nikopolitans | F41: J 1040 | G41: Aleksandar | H41: Source, 411 | I41: Skylitzes doesn't provide the year but the year is probably 1040 as the whole section is about this year. | L41: =_xlfn.XLOOKUP(_xlfn.CONCAT(A41, " ", B41), Persons!B:B, Persons!S:S) -> Ioannes 111 / Ioannes Koutzomytes, tax collector at Nikopolis | M41: Death | N41: =F41 -> J 1040 | P41: 0009-0007-1432-0127 / Anđelović, Aleksandar | S41: =C41 -> Skylitzes | T41: =D41 -> 411,63
A42: Mahmud | B42: 102 | C42: Skylitzes | D42: 445.59-61 | E42: Perished having broken his neck after a fall while encouraging his army (fighting against <Tughrul Beg 51>) | F42: J 1040 | G42: Wortley | H42: p. 419 | I42: The battle occurred in 1040, says the latest English translator, see p. 419. | L42: =_xlfn.XLOOKUP(_xlfn.CONCAT(A42, " ", B42), Persons!B:B, Persons!S:S) -> Mahmud 102 / Mahmud of Ghazni, prince of Khurasan | M42: Death | N42: =F42 -> J 1040 | P42: 54176097 / Wortley, John | S42: Skylitzes (English) | T42: =H42 -> p. 419
A43: Mahmud | B43: 102 | C43: Bryennios | D43: 95.11-15 | E43: Was not hit by an arrow, nor a lance, but while encouraging his men in battle his horse slipped and fell on him; he broke his neck and died | F43: J 1040, May | G43: Editor | H43: p. 94, n. 3 | I43: Bryennios, like Skylitzes, refers to the battle of Aspahan, and the editor of Bryennios, Gautier, mentions that this occurred in May 1040, see p. 94, n. 3. | L43: =_xlfn.XLOOKUP(_xlfn.CONCAT(A43, " ", B43), Persons!B:B, Persons!S:S) -> Mahmud 102 / Mahmud of Ghazni, prince of Khurasan | M43: Death | N43: =F43 -> J 1040, May | P43: =_xlfn.XLOOKUP(C43,'Text publications'!A:A,'Text publications'!G:G,"") -> 231073465 / Gautier, Paul | S43: =C43 -> Bryennios | T43: =D43 -> 95.11-15
A44: Mahmud | B44: 102 | C44: Attaleiates: History | D44: 44.5 / 33.20-21 | E44: After his death power was taken over by the leader (<Tughrul Beg 51>) of the Nephthalite Huns (Seljuk Turks) who had crossed the Ganges (Jaxartes?) into Persia | F44: J 1040-1050 | G44: Aleksandar | H44: Source, 44 | I44: Attaleiates here discusses a long term the rise of Seljuks, but he approximatelly talks about periond 1040-1050, and says "during those same years." | L44: =_xlfn.XLOOKUP(_xlfn.CONCAT(A44, " ", B44), Persons!B:B, Persons!S:S) -> Mahmud 102 / Mahmud of Ghazni, prince of Khurasan | M44: Death | N44: =F44 -> J 1040-1050 | P44: 0009-0007-1432-0127 / Anđelović, Aleksandar | S44: =C44 -> Attaleiates: History | T44: =D44 -> 44.5 / 33.20-21
A45: Michael | B45: 4 | C45: Anonymus Barensis | D45: 150 | E45: He died, and was succeeded by his nephew <Michael 5> the kaisar, who sent <Georgios 62> to Apulia | F45: J 1041 | G45: Source | I45: On this page in Anonymi Barensis I cannot see anything that says "Michael IV died", although it is implied by the fact that Michael V took the throne over. | L45: =_xlfn.XLOOKUP(_xlfn.CONCAT(A45, " ", B45), Persons!B:B, Persons!S:S) -> Michael 4 / Emperor Michael IV Paphlagon | M45: Death | N45: =F45 -> J 1041 | P45: =_xlfn.XLOOKUP(C45,'Text publications'!A:A,'Text publications'!D:D,"") -> 13129565 / Anonymus Barensis | S45: =C45 -> Anonymus Barensis | T45: =D45 -> 150
A46: Michael | B46: 4 | C46: Attaleiates: History | D46: 10.13-15, 10.18-19 / 8.9-10, 9.2-3 | E46: Died shortly after his victory over the Bulgarian rebels and the celebrations of his triumph and was buried at the monastery of the Saints Who Took No Payment [for medical treatment] (the Holy Anargyroi, Kosmas & Damianos) | F46: J 1041, December 10 | G46: Kaldellis & Krallis | H46: p. 595, n. 15 | I46: The English translators also date this to December 10, 1041, see p. 595, n. 15. Also, Attaleiates' calculation is pretty accurate (April 1034-December 1041 = 7 years 7 months) | L46: =_xlfn.XLOOKUP(_xlfn.CONCAT(A46, " ", B46), Persons!B:B, Persons!S:S) -> Michael 4 / Emperor Michael IV Paphlagon | M46: Death | N46: =F46 -> J 1041, December 10 | Q46: Kaldellis, Anthony; Krallis, Dimitris | S46: Attaleiates: History (English) | T46: =H46 -> p. 595, n. 15
A47: Michael | B47: 4 | C47: Skylitzes | D47: 415.50-52 | E47: Died after confessing and repenting | F47: J 1041, December 10 | G47: Source | I47: Skylitzes precisely and very clearly dates the death of Michael the Paphlagonian. | L47: =_xlfn.XLOOKUP(_xlfn.CONCAT(A47, " ", B47), Persons!B:B, Persons!S:S) -> Michael 4 / Emperor Michael IV Paphlagon | M47: Death | N47: =F47 -> J 1041, December 10 | P47: =_xlfn.XLOOKUP(C47,'Text publications'!A:A,'Text publications'!D:D,"") -> Ioannes 110 / Ioannes Skylitzes, historian | S47: =C47 -> Skylitzes | T47: =D47 -> 415.50-52
A48: Michael | B48: 4 | C48: Kleinchroniken 15 | D48: 159,9 | E48: Died after becoming a monk | F48: J 1041, December 9-10 | G48: Source | I48: 1041, December 9-10 [on December 9 of the 10th indiction of the year 1041] | L48: =_xlfn.XLOOKUP(_xlfn.CONCAT(A48, " ", B48), Persons!B:B, Persons!S:S) -> Michael 4 / Emperor Michael IV Paphlagon | M48: Death | N48: =F48 -> J 1041, December 9-10 | P48: 14789545 / Schreiner, Peter | S48: =C48 -> Kleinchroniken 15 | T48: =D48 -> 159,9
A49: Konstantinos | B49: 112 | C49: Skylitzes | D49: 423.31-32 | E49: Died poisoned by his wife (<Anonyma 117>) | F49: J 1042 | G49: Aleksandar | H49: Source, 423 | I49: Skylitzes does not provide the death date for Konstantinos Artoklines, but later in the same chapter talks about Monomachos as the only choice left after Artoklines was poisoned, and how Zoë and Monomachos married in 1042, so it is likely that Artoklines died early in 1042. | L49: =_xlfn.XLOOKUP(_xlfn.CONCAT(A49, " ", B49), Persons!B:B, Persons!S:S) -> Konstantinos 112 / Konstantinos Artoklines, katepano | M49: Death | N49: =F49 -> J 1042 | P49: 0009-0007-1432-0127 / Anđelović, Aleksandar | S49: =C49 -> Skylitzes | T49: =D49 -> 423.31-32
A50: Konstantinos | B50: 112 | C50: Glykas | D50: 593.5-6 | E50: Was poisoned by his wife (<Anonyma 117>) | F50: J 1042 | G50: Source | I50: "was poisoned by his wife … Zoë got married to Monomachos in AM 6550" [1042] Glykas does not provide the death date for Konstantinos Artoklines, but later in the same chapter (593) describes Monomachos as the only choice left for Zoë after Artoklines was poisoned, and how Zoë and Monomachos married in 1042, so it is likely that Artoklines died early in 1042. Glykas draws information from Skylitzes to a great extent so it's not a surprise that the two accounts are identical. | L50: =_xlfn.XLOOKUP(_xlfn.CONCAT(A50, " ", B50), Persons!B:B, Persons!S:S) -> Konstantinos 112 / Konstantinos Artoklines, katepano | M50: Death | N50: =F50 -> J 1042 | P50: =_xlfn.XLOOKUP(C50,'Text publications'!A:A,'Text publications'!D:D,"") -> Michael 305 / Michael Sikidites, punished as a magician | S50: =C50 -> Glykas | T50: =D50 -> 593.5-6
A51: Michael | B51: 4 | C51: Lupus protospatharius | D51: 58.20-21 | E51: He died, and was succeeded by his nephew the kaisar <Michael 5> | F51: J 1042 | G51: Source | I51: The year stated is 1042, however it does not mean that the dating is incorrect, as the Byzantine year started in September. It all depends on how the author of this chronicon calculated time. | L51: =_xlfn.XLOOKUP(_xlfn.CONCAT(A51, " ", B51), Persons!B:B, Persons!S:S) -> Michael 4 / Emperor Michael IV Paphlagon | M51: Death | N51: =F51 -> J 1042 | P51: =_xlfn.XLOOKUP(C51,'Text publications'!A:A,'Text publications'!D:D,"") -> 84485715 / Lupus Protospatharius | S51: =C51 -> Lupus protospatharius | T51: =D51 -> 58.20-21
A52: Apolaphar Mouchoumet | B52: 101 | C52: Skylitzes | D52: 407,36 | E52: Was killed by the troops of <Katakalon 101> Kekaumenos | F52: J 1042, April | G52: Wortley | H52: p. 383 | I52: Skylitzes says that Katakalon killed Apolaphar "on the fourth day (it was the Wednesday on which we are accustomed to celebrate mid-Pentecost)" and the translator of Skylitzes speculates that this was probably "1041 since he was at Constantinople in April 1042." See A Synopsis of Byzantine History, trans. Wortley (Cambridge: CUP, 2010), p. 383. | L52: =_xlfn.XLOOKUP(_xlfn.CONCAT(A52, " ", B52), Persons!B:B, Persons!S:S) -> Apolaphar Mouchoumet 101 / Ahmad al-Akhal, amir of Sicily | M52: Death | N52: =F52 -> J 1042, April | P52: 54176097 / Wortley, John | S52: Skylitzes (English) | T52: =H52 -> p. 383
A53: Anonymus | B53: 178 | C53: Skylitzes | D53: 428,74 | E53: Was murdered by <Georgios 62> Maniakes | F53: J 1042, October | G53: Wortley | H53: p. 402, n. 31 | I53: Although Skylitzes does not mention any date in this section, Maniakes killed Pardos when in Italy, and as a matter of fact Maniakes landed at Otranto in April 1042 and remained shut up in the town while the Normans ravaged the region of Oria, see Annales Barenses, Monumenta Germaniae Historica. Scriptores, v, 52-6, 54. Therefore Pardos was killed by Maniakes either in late 1042 or 1043. Also, the most recent English translator of Skylitzes says that Pardos was killed in October 1042, see A Synopsis of Byzantine History, trans. Wortley (Cambridge: CUP, 2010), p. 402, n. 31. | L53: =_xlfn.XLOOKUP(_xlfn.CONCAT(A53, " ", B53), Persons!B:B, Persons!S:S) -> Anonymus 178 / Pardos, successor of Maniakes in Italy | M53: Death | N53: =F53 -> J 1042, October | P53: 54176097 / Wortley, John | S53: Skylitzes (English) | T53: =H53 -> p. 402, n. 31
A54: Georgios | B54: 62 | C54: Aristakes | D54: 53.2-3 (43) | E54: Was found dead among the frontline troops (?), not killed by anyone but brought down by a powerful angel | F54: J 1042-1043 | G54: Aleksandar | H54: Source, 53 | I54: Now the question is what "year" means for Aristakes, because the "first year" of Monomachos' reign might have meant both 1042 and 1043 for Aristakes. This is why I put neither 1042 nor 1043 as Maniakes' death according to Aristakes, but I only leave the description. | L54: =_xlfn.XLOOKUP(_xlfn.CONCAT(A54, " ", B54), Persons!B:B, Persons!S:S) -> Georgios 62 / Georgios Maniakes | M54: Death | N54: =F54 -> J 1042-1043 | P54: 0009-0007-1432-0127 / Anđelović, Aleksandar | S54: =C54 -> Aristakes | T54: =D54 -> 53.2-3 (43)
A55: Anonyma | B55: 123 | C55: Kekaumenos | D55: 236.25-27 | E55: Died in prison (in the Praitorion) during the reign of Monomachos (<Konstantinos 9>) | F55: J 1042-1055 | G55: Aleksandar | H55: Source, 236 | I55: 1042-1055 [during the reign of Monomachos] | L55: =_xlfn.XLOOKUP(_xlfn.CONCAT(A55, " ", B55), Persons!B:B, Persons!S:S) -> Anonyma 123 / wife of Dobronas, ruler of Zara and Salona | M55: Death | N55: =F55 -> J 1042-1055 | P55: 0009-0007-1432-0127 / Anđelović, Aleksandar | S55: =C55 -> Kekaumenos | T55: =D55 -> 236.25-27
A56: Dobronas | B56: 101 | C56: Kekaumenos | D56: 236.25-27 | E56: Died in prison (in the Praitorion) during the reign of Monomachos (<Konstantinos 9>) | F56: J 1042-1055 | G56: Aleksandar | H56: Source, 236 | I56: "Died during the reign of Monomachos." [1042-1055] | L56: =_xlfn.XLOOKUP(_xlfn.CONCAT(A56, " ", B56), Persons!B:B, Persons!S:S) -> Dobronas 101 / Dobronas, ruler of Zadar and Split | M56: Death | N56: =F56 -> J 1042-1055 | P56: 0009-0007-1432-0127 / Anđelović, Aleksandar | S56: =C56 -> Kekaumenos | T56: =D56 -> 236.25-27
A57: Romanos | B57: 3 | C57: Kekaumenos | D57: 236,14 | E57: Died and was succeeded by <Michael 4> Paphlagon | F57: J 1042-1055 | G57: Aleksandar | H57: Source, 236 | I57: No year provided in this section, although the whole passage in Kekaumenos is about Dobronas, who died [see above for his death] during Monomachos' reign, so the terminus post quem here is 1042. | L57: =_xlfn.XLOOKUP(_xlfn.CONCAT(A57, " ", B57), Persons!B:B, Persons!S:S) -> Romanos 3 / Emperor Romanos III Argyros | M57: Death | N57: =F57 -> J 1042-1055 | P57: 0009-0007-1432-0127 / Anđelović, Aleksandar | S57: =C57 -> Kekaumenos | T57: =D57 -> 236,14
A58: Anonymus | B58: 180 | C58: Skylitzes | D58: 430,41 | E58: Was murdered during a scuffle at Constantinople | F58: J 1043 | G58: Aleksandar | H58: Source, 430 | I58: Skylitzes clearly says "the same year of the indiction" when referring to this murder, and the year he talked about previously is 1043, and, what is more, he says that then happened "the Russian attack on the capital" which, as is well known, occured in 1043. There are even interesting papers on this, for example see J. Shepard, ‘Why did the Russians attack Byzantium in 1043?’ Byzantinische-neugriechische Jahrbücher 22 (1979): 147-202. | L58: =_xlfn.XLOOKUP(_xlfn.CONCAT(A58, " ", B58), Persons!B:B, Persons!S:S) -> Anonymus 180 / prominent Scythian (Rus) murdered at Constantinople | M58: Death | N58: =F58 -> J 1043 | P58: 0009-0007-1432-0127 / Anđelović, Aleksandar | S58: =C58 -> Skylitzes | T58: =D58 -> 430,41
A59: Anonymus | B59: 180 | C59: Zonaras | D59: 17.24.4 | E59: Was numbered among those who died in a quarrel which came to blows between Scythian traders and Romans in Constantinople | F59: J 1043 | G59: Aleksandar | H59: Source, 17 | I59: Although Zonaras doesn't state any year, he says that this murder prompted the conflict between Rus and Byzantium which occurred in 1043, so he indubitably refers to the same event as Skylitzes. | L59: =_xlfn.XLOOKUP(_xlfn.CONCAT(A59, " ", B59), Persons!B:B, Persons!S:S) -> Anonymus 180 / prominent Scythian (Rus) murdered at Constantinople | M59: Death | N59: =F59 -> J 1043 | P59: 0009-0007-1432-0127 / Anđelović, Aleksandar | S59: =C59 -> Zonaras | T59: =D59 -> 17.24.4
A60: Georgios | B60: 62 | C60: Psellos, Orationes panegyricae II | D60: 750-774 | E60: 1043 summary: at the crisis of the battle he fell dead witout a wound; a star was seen above him as he died, and he cried out that he was being killed by a horseman: it was thought he was killed by an angel | F60: J 1043 | G60: Aleksandar | H60: Source, II | I60: Psellos does not mention the year but he refers to the battle of Ostrovo. | L60: =_xlfn.XLOOKUP(_xlfn.CONCAT(A60, " ", B60), Persons!B:B, Persons!S:S) -> Georgios 62 / Georgios Maniakes | M60: Death | N60: =F60 -> J 1043 | P60: 0009-0007-1432-0127 / Anđelović, Aleksandar | S60: =C60 -> Psellos, Orationes panegyricae II | T60: =D60 -> 750-774
A61: Georgios | B61: 62 | C61: Psellos: Chronographia | D61: VI 84-86 | E61: As he was throwing the army into confusion - wherever he rushed the ranks were broken and the wall of the army withdrew, their unity fragmented - suddenly he was hit in the right side, not superficially but deeply, with great loss of blood. It was as if he did not feel the blow, but seeing the blood and putting his hand where it was pouring, he realised the blow was fatal; in complete despair trying to withdraw to his own camp he did get a little way from the armies. No longer able to direct his horse, his body utterly failing and his head fainting, with a little groan as much as his strength allowed, he at once lost control of the bridle, slid from his seat and fell to the ground, a pitiful sight. When the Roman army saw him lying, they still held in their bridles, afraid the sight was a trick; but as <Anonymus 7013> was not there and his horse ran uncontrolled and free between the two armies, all rushed in a body on his corpse. Seeing him and being amazed how much ground his body lay stretched over, the men cut off his head and brought it to Stephanos 102; many claimed to have killed him and accounts of it were composed and fabricated. As it was impossible to prove what was said, the story was invented that unknown riders had rushed against him and beheaded him; many such tales were told, but it was impossible to prove any. As he was wounded in the side it was alleged that it the wound was from a lance, but the identity of the one who inflicted the wound was unknown to the time that <Michael 61>'s history was written. Before the army returned to <Konstantinos 9>, his head was sent. <Konstantinos 9> fixed his head high up in the great hippodrome, so that all might see it even from far off in the open air and in their midst. | F61: J 1043 | G61: Aleksandar | H61: Source, VI | I61: Psellos, like Zonaras, Skylitzes and Glykas, does not state any year, but he obviously refers to the same battle of Ostrovo that occurred in 1043. [I merged several entries about Maniakes' death from Psellos' Chronographia into one as they refer to the same two passages from Chronographia (6.84-86)] | L61: =_xlfn.XLOOKUP(_xlfn.CONCAT(A61, " ", B61), Persons!B:B, Persons!S:S) -> Georgios 62 / Georgios Maniakes | M61: Death | N61: =F61 -> J 1043 | P61: 0009-0007-1432-0127 / Anđelović, Aleksandar | S61: =C61 -> Psellos: Chronographia | T61: =D61 -> VI 84-86
A62: Georgios | B62: 62 | C62: Zonaras | D62: 17.22.15-18. | E62: Suddenly he was seen to be wounded with a mortal blow; the blood flowing down from it spread a great mist over him and inflicted paralysis on his limbs, so that the bridle fell from his hand and he was thrown down to the ground from his horse. He died at once and lay a little outside no-man's land, and the emperor's men meantime were afraid to approach him. When his men realised that their leader had fallen, they were seized by terror and scattered. Then those from the other side ran to him as he lay, and cutting off the head of the wretched man brought it to their general (<Stephanos 102>). His head was sent by the general (<Stephanos 102>) to the emperor (<Konstantinos 9>) who raised it on high in the theatre. | F62: J 1043 | G62: Aleksandar | H62: Source, 17 | I62: Zonaras does not state any year/date, but he clearly refers to the battle of Ostrovo. [I merged several entries about Maniakes' death from Zonaras into one as they refer to the same two passages from Zonaras (17.22.15-18)] | L62: =_xlfn.XLOOKUP(_xlfn.CONCAT(A62, " ", B62), Persons!B:B, Persons!S:S) -> Georgios 62 / Georgios Maniakes | M62: Death | N62: =F62 -> J 1043 | P62: 0009-0007-1432-0127 / Anđelović, Aleksandar | S62: =C62 -> Zonaras | T62: =D62 -> 17.22.15-18.
A63: Ioannes | B63: 68 | C63: Zonaras | D63: 17.22.26 | E63: Lived for a few days after his mutilation and then measured out his life | F63: J 1043 | G63: Aleksandar | H63: Source, 17 | I63: Zonaras doesn't explicitly mention the year but he previously discussed Keroullarios' installment and the battle of Ostrovo, which both occurred in 1043, and thus he clearly reefers to 1043. | L63: =_xlfn.XLOOKUP(_xlfn.CONCAT(A63, " ", B63), Persons!B:B, Persons!S:S) -> Ioannes 68 / Ioannes the Orphanotrophos, brother of Michael IV | M63: Death | N63: =F63 -> J 1043 | P63: 0009-0007-1432-0127 / Anđelović, Aleksandar | S63: =C63 -> Zonaras | T63: =D63 -> 17.22.26
A64: Anonymus | B64: 178 | C64: Anonymus Barensis | D64: 151 | E64: He was killed at Otranto by <Georgios 62> Maniakes | F64: J 1043 | G64: Source | L64: =_xlfn.XLOOKUP(_xlfn.CONCAT(A64, " ", B64), Persons!B:B, Persons!S:S) -> Anonymus 178 / Pardos, successor of Maniakes in Italy | M64: Death | N64: =F64 -> J 1043 | P64: =_xlfn.XLOOKUP(C64,'Text publications'!A:A,'Text publications'!D:D,"") -> 13129565 / Anonymus Barensis | S64: =C64 -> Anonymus Barensis | T64: =D64 -> 151
A65: Konstantinos | B65: 113 | C65: Skylitzes | D65: 432,15 | E65: Died fighting against the Scythians (Rus') | F65: J 1043 | G65: Source | I65: This death can be actually dated from Skylitzes: he starts the whole story with "AM 6551, eleventh year of the indiction" which is September 1033-August 1043, and then describes the Rus'–Byzantine war for which we know that it took place in 1043, and starts the section where he mentions Kaballourios with "July the same year." Therefore, Konstantinos Kaballourios died during the Rus'–Byzantine war in 1043. | L65: =_xlfn.XLOOKUP(_xlfn.CONCAT(A65, " ", B65), Persons!B:B, Persons!S:S) -> Konstantinos 113 / Konstantinos Kaballourios, naval commander | M65: Death | N65: =F65 -> J 1043 | P65: =_xlfn.XLOOKUP(C65,'Text publications'!A:A,'Text publications'!D:D,"") -> Ioannes 110 / Ioannes Skylitzes, historian | S65: =C65 -> Skylitzes | T65: =D65 -> 432,15
A66: Romanos | B66: 3 | C66: Kleinchroniken 15 | D66: 159.8, 165.10 | E66: Died having drowned in his bath | F66: J 1043, April 11-12 | G66: Source | I66: on April 11 of the 12th indiction in the year 6542 [April 1034] | L66: =_xlfn.XLOOKUP(_xlfn.CONCAT(A66, " ", B66), Persons!B:B, Persons!S:S) -> Romanos 3 / Emperor Romanos III Argyros | M66: Death | N66: =F66 -> J 1043, April 11-12 | P66: 14789545 / Schreiner, Peter | S66: =C66 -> Kleinchroniken 15 | T66: =D66 -> 159.8, 165.10
A67: Alexios | B67: 11 | C67: Skylitzes | D67: 429.18-19 | E67: His life was brought to an end and he was succeeded by <Michael 11> Keroularios | F67: J 1043, February 20 | G67: Source | I67: "on February 20 of the 11th indiction" [1043] Alexios Stoudites, patriarch of Constantinople; Τῇ δὲ εἰκοστῇ τοῦ Φεβρουαρίου μηνός, τῆς ἑνδεκάτης ἰνδικτιῶνος, κατέλυσε τὴν ζωὴν Ἀλέξιος ὁ πατριάρχης, καὶ ἀνάγεται εἰς τὸν αὐτοῦ θρόνον Μιχαὴλ ὁ Κηρουλάριος κατὰ τὴν ἡμέραν τοῦ εὐαγγελισμοῦ | L67: =_xlfn.XLOOKUP(_xlfn.CONCAT(A67, " ", B67), Persons!B:B, Persons!S:S) -> Alexios 11 / Alexios Stoudites, patriarch of Constantinople | M67: Death | N67: =F67 -> J 1043, February 20 | P67: =_xlfn.XLOOKUP(C67,'Text publications'!A:A,'Text publications'!D:D,"") -> Ioannes 110 / Ioannes Skylitzes, historian | S67: =C67 -> Skylitzes | T67: =D67 -> 429.18-19
A68: Georgios | B68: 62 | C68: Glykas | D68: 594.16-18 | E68: Had his head chopped off when he fell off his horse during the battle at Ostrobos, and it was sent to the emperor (<Konstantinos 9>) | F68: J 1043, March [TAQ] | G68: Aleksandar | H68: Source, 504-595 | I68: Glykas does not mention the date nor year, but he talks about the battle of Ostrovo which happened in 1043, and also the next chapter starts with the clear reference to patriarch Alexios' death and Keroullarios' installment as the new patriarch of Constantinople, which happened on March 25 1043. Therefore the terminus ante quem for Maniakes' death, according to Glykas, is March 1043. | L68: =_xlfn.XLOOKUP(_xlfn.CONCAT(A68, " ", B68), Persons!B:B, Persons!S:S) -> Georgios 62 / Georgios Maniakes | M68: Death | N68: =F68 -> J 1043, March [TAQ] | P68: 0009-0007-1432-0127 / Anđelović, Aleksandar | S68: =C68 -> Glykas | T68: =D68 -> 594.16-18
A69: Georgios | B69: 62 | C69: Skylitzes | D69: 428.87-1 | E69: Having dropped dead from his horse following an injury on the chest, his head was chopped off and carried by <Stephanos 102> to Constantinople where it was paraded on a spear through the Plateia | F69: J 1043, March [TAQ] | G69: Aleksandar | H69: Source, 428-429 | I69: Skylitzes does not mention the date nor year, but he talks about the battle of Ostrovo which happened in 1043, and also the next chapter starts with the clear reference to patriarch Alexios' death and Keroullarios' installment as the new patriarch of Constantinople, which happened on March 25 1043. Therefore the terminus ante quem for Maniakes' death, according to Skylitzes, is March 1043. | L69: =_xlfn.XLOOKUP(_xlfn.CONCAT(A69, " ", B69), Persons!B:B, Persons!S:S) -> Georgios 62 / Georgios Maniakes | M69: Death | N69: =F69 -> J 1043, March [TAQ] | P69: 0009-0007-1432-0127 / Anđelović, Aleksandar | S69: =C69 -> Skylitzes | T69: =D69 -> 428.87-1
A70: Ioannes | B70: 68 | C70: Skylitzes | D70: 429,28 | E70: Died shortly after his blinding | F70: J 1043, May 13 | G70: Aleksandar | H70: Source, 428-429 | I70: Skylitzes clearly states that this is May 13, "the same year" and he previously discussed Keroullarios' installment and the battle of Ostrovo. | L70: =_xlfn.XLOOKUP(_xlfn.CONCAT(A70, " ", B70), Persons!B:B, Persons!S:S) -> Ioannes 68 / Ioannes the Orphanotrophos, brother of Michael IV | M70: Death | N70: =F70 -> J 1043, May 13 | P70: 0009-0007-1432-0127 / Anđelović, Aleksandar | S70: =C70 -> Skylitzes | T70: =D70 -> 429,28
A71: Anonymus | B71: 178 | C71: Annales Barenses | D71: 56,36 | E71: He was killed on the spot as one of the embassy taking a pardon to <Georgios 62> Maniakes | F71: J 1043, October | G71: Source | L71: =_xlfn.XLOOKUP(_xlfn.CONCAT(A71, " ", B71), Persons!B:B, Persons!S:S) -> Anonymus 178 / Pardos, successor of Maniakes in Italy | M71: Death | N71: =F71 -> J 1043, October | P71: 54236315 / Pertz, Georg Heinrich | S71: =C71 -> Annales Barenses | T71: =D71 -> 56,36
A72: Anonymus | B72: 179 | C72: Skylitzes | D72: 430,34 | E72: Died shortly after his blinding | F72: J 1043-1044 | G72: Aleksandar | H72: Source, 430 | I72: Skylitzes describes Lampros' death in the same passage where he described the death of patriarch Alexios, for which he clearly states that it occurred in 1043 (on February 20 of the 11th indiction). Since for Lambros he says that he died "shortly after", then the year of Lambros' death is either 1043 or early 1044. | L72: =_xlfn.XLOOKUP(_xlfn.CONCAT(A72, " ", B72), Persons!B:B, Persons!S:S) -> Anonymus 179 / Lampros, father of the strategos of Melitene Leon | M72: Death | N72: =F72 -> J 1043-1044 | P72: 0009-0007-1432-0127 / Anđelović, Aleksandar | S72: =C72 -> Skylitzes | T72: =D72 -> 430,34
A73: Ioannes | B73: 106 | C73: Aristakes | D73: 55.8-9 (43-44) | E73: Died within a year of his brother <Ashot 101>, signalling the end of Armenia | F73: J 1044 | G73: Source | I73: Aristakes finishes the previous chapter as follows: "Such things occurred at the outset of Constantine's reign, which was the year 490 according to our [Armenian] calendar [1041]." and starts the chapter where he mentions Smbat's death as "three years later." | L73: =_xlfn.XLOOKUP(_xlfn.CONCAT(A73, " ", B73), Persons!B:B, Persons!S:S) -> Ioannes 106 / Ioannes Smbat, king of Armenia | M73: Death | N73: =F73 -> J 1044 | P73: =_xlfn.XLOOKUP(C73,'Text publications'!A:A,'Text publications'!D:D,"") -> Aristakes 101 / Aristakes Lastivertc'i / of Lastivert, Armenian historian | S73: =C73 -> Aristakes | T73: =D73 -> 55.8-9 (43-44)
A74: al-Basasiri | B74: 101 | C74: Skylitzes | D74: 446,75 | E74: Was killed by <Tughrul Beg 51> | F74: J 1044 | G74: Wortley | H74: n. 118 | I74: Skylitzes does not mention any year in this section, but the English translator of Skylitzes says that the chronology in this section is problematic, but the events revolve around the year 1044, see p. 419, n. 118. | L74: =_xlfn.XLOOKUP(_xlfn.CONCAT(A74, " ", B74), Persons!B:B, Persons!S:S) -> al-Basasiri 101 / al-Basasiri, commander of Baghdad | M74: Death | N74: =F74 -> J 1044 | P74: 54176097 / Wortley, John | S74: Skylitzes (English) | T74: =H74 -> n. 118
A75: Maria | B75: 64 | C75: Psellos: Chronographia | D75: VI 69.5-9 | E75: A sudden illness seized her: it fought every provision and skill, cutting short the plans of <Konstantinos 9> and her hopes; it was resistant to every application of care: she had chest pains and terrible difficulty in breathing | F75: J 1044 | G75: Sewter | H75: n. 100 | I75: No date provided by Psellos, but the English translator says that Scleraina probably died in 1044, see Michael Psellus: Chronographia, trans E.R.A Sewter, (New Haven: Yale University Press, 1953), n. 100. | L75: =_xlfn.XLOOKUP(_xlfn.CONCAT(A75, " ", B75), Persons!B:B, Persons!S:S) -> Maria 64 / Maria Skleraina, mistress of Konstantinos IX | M75: Death | N75: =F75 -> J 1044 | P75: 9429963 / Sewter, Edgar Robert Ashton | S75: Psellos: Chronographia (English) | T75: =H75 -> n. 100
A76: Maria | B76: 64 | C76: Psellos, Poema 17 | D76: 17.1-448 | E76: Her death was marked by a long iambic monody by <Michael 61>, containing anguish over the event, the laments of her mother (<Anonyma 2108>), brother (<Romanos 104>) and of <Konstantinos 9>, ending with Michael's own consolation for the bereaved | F76: J 1045 | G76: P. Agapitos | H76: p. 559 | I76: No date given, but see P. Agapitos, ‘Public and Private Death in Psellos’, BZ 101 (2008), 559, who claims that Maria died of bronchitis around 1045. | L76: =_xlfn.XLOOKUP(_xlfn.CONCAT(A76, " ", B76), Persons!B:B, Persons!S:S) -> Maria 64 / Maria Skleraina, mistress of Konstantinos IX | M76: Death | N76: =F76 -> J 1045 | P76: 37011634 / Agapītós, Panagiṓtīs A. | S76: Agapitos, Public and Private Death | T76: =H76 -> p. 559
A77: Anonymus | B77: 188 | C77: Skylitzes | D77: 467.86-87 | E77: Was killed during a battle against the Pechenegs (at the fort of Dampolis) | F77: J 1047 | G77: Aleksandar | H77: Source, 467 | I77: Skylitzes doesn't date this event, but it probably occurred in 1047, when the clash between Konstantinos Arianites (doux of the west in Adrianople) and the Balkan Pechenegs happened. | L77: =_xlfn.XLOOKUP(_xlfn.CONCAT(A77, " ", B77), Persons!B:B, Persons!S:S) -> Anonymus 188 / Polys, supporter of Leon Tornikios | M77: Death | N77: =F77 -> J 1047 | P77: 0009-0007-1432-0127 / Anđelović, Aleksandar | S77: =C77 -> Skylitzes | T77: =D77 -> 467.86-87
A78: Asan | B78: 101 | C78: Skylitzes | D78: 449.74-75 | E78: Died fighting the Romans who attacked him while he pillaged their camp | F78: J 1047 | G78: Aleksandar | H78: Source, 467 | I78: Skylitzes does not provide the date but writes about Asan's defeat by Kekaumenos Katakalon that occurred in Vaspurakan in 1047. | L78: =_xlfn.XLOOKUP(_xlfn.CONCAT(A78, " ", B78), Persons!B:B, Persons!S:S) -> Asan 101 / Asan the Deaf, nephew of Tughrul Beg | M78: Death | N78: =F78 -> J 1047 | P78: 0009-0007-1432-0127 / Anđelović, Aleksandar | S78: =C78 -> Skylitzes | T78: =D78 -> 449.74-75
A79: Leon | B79: 61 | C79: Manasses, Chronicle | D79: 6221-6223 | E79: He was quickly snatched away by (divine) justice, which shot him down with her inescapable arrows and caused wounds around the chest of the beast_x000D_ | F79: J 1047, December | G79: Editor | H79: p. 335, n. 6217/23 | I79: Manasses doesn't state the year but the editor of the text says that the rebellion of Leo Tornicios lasted from September until December 24 1047, see p. 335, n. 6217-23. | L79: =_xlfn.XLOOKUP(_xlfn.CONCAT(A79, " ", B79), Persons!B:B, Persons!S:S) -> Leon 61 / Leon Tornikios | M79: Death | N79: =F79 -> J 1047, December | P79: =_xlfn.XLOOKUP(C79,'Text publications'!A:A,'Text publications'!G:G,"") -> 256344105 / Lampsidēs, Odysseus | S79: =C79 -> Manasses, Chronicle | T79: =D79 -> 6221-6223
A80: Michael | B80: 103 | C80: Skylitzes | D80: 470.88-89 | E80: Fell during the defeat of the Roman troops (under <Konstantinos 115>) by the Pechenegs (at Basilike Libas) | F80: J 1049-1050 | G80: Source | L80: =_xlfn.XLOOKUP(_xlfn.CONCAT(A80, " ", B80), Persons!B:B, Persons!S:S) -> Michael 103 / Michael Dokeianos, katepano of Italy | M80: Death | N80: =F80 -> J 1049-1050 | P80: =_xlfn.XLOOKUP(C80,'Text publications'!A:A,'Text publications'!D:D,"") -> Ioannes 110 / Ioannes Skylitzes, historian | S80: =C80 -> Skylitzes | T80: =D80 -> 470.88-89
A81: Michael | B81: 103 | C81: Attaleiates: History | D81: 34.21-24 / 27.7-9 | E81: Died a brave death at the hands of the furious Scythians (Pechenegs whose leader <Anonymus 5047> he had hit) who cut him into pieces, opened up his belly, removed his entrails, and inserted in their place his arms and legs which they had chopped off | F81: J 1050 | G81: Aleksandar | H81: Skylitzes, 470 | I81: Attaleiates doesn't date this event, but it probably occurred in 1050, when the clash with Pechenegs happened and when Arianites died as well, as Skylitzes says, "AM 6558 [Sept 1049-Aug 1050]" | L81: =_xlfn.XLOOKUP(_xlfn.CONCAT(A81, " ", B81), Persons!B:B, Persons!S:S) -> Michael 103 / Michael Dokeianos, katepano of Italy | M81: Death | N81: =F81 -> J 1050 | P81: 0009-0007-1432-0127 / Anđelović, Aleksandar | S81: =C81 -> Attaleiates: History | T81: =D81 -> 34.21-24 / 27.7-9
A82: Zoe | B82: 1 | C82: Attaleiates: History | D82: 51.20-21 / 39.2 | E82: Had already died by the time her sister <Theodora 1> took power after the death of <Konstantinos 9> Monomachos (in early 1055) | F82: J 1050 | G82: Kaldellis & Krallis | H82: n. 89 | I82: Attaleiates does not mention the year, but the English translator notes that Zoe died in 1050, see n. 89. | L82: =_xlfn.XLOOKUP(_xlfn.CONCAT(A82, " ", B82), Persons!B:B, Persons!S:S) -> Zoe 1 / Empress Zoe | M82: Death | N82: =F82 -> J 1050 | Q82: Kaldellis, Anthony; Krallis, Dimitris | S82: Attaleiates: History (English) | T82: =H82 -> n. 89
A83: Zoe | B83: 1 | C83: Psellos: Chronographia | D83: VI 160.1-13 | E83: When her appointed time was complete and she was about to die, her physical constitution showed small preliminary signs. Her desire for nourishment faded, the lack of nourishment increased and kindled a fatal fever in her; the wasting of her body, its fading as it were, was a preliminary sign that death was near. She immediately thought of the prisons, remitted debts, released from misfortune those condemned, opened the imperial treasuries and let the gold in them flow out like a river. The imperial gold was dispersed unsparingly, intemperately; but after a short struggle with death and a slight change in her appearance she relinquished this life, after living for seventy-two years. | F83: J 1050 | G83: Sewter | H83: n. 135 | I83: [I merged four subsequent entries in PBW about Zoe death from Chronographia into one as they all refer to the same passage from Psellos' Chronographia (VI 160.1-13)] Psellos here just mentions that Zoe died at the age of seventy-two, without a reference to any date. The English translator of Chronographia notes that Zoe died in 1050, see n. 135. | L83: =_xlfn.XLOOKUP(_xlfn.CONCAT(A83, " ", B83), Persons!B:B, Persons!S:S) -> Zoe 1 / Empress Zoe | M83: Death | N83: =F83 -> J 1050 | P83: 9429963 / Sewter, Edgar Robert Ashton | S83: Psellos: Chronographia (English) | T83: =H83 -> n. 135
A84: Zoe | B84: 1 | C84: Psellos: Chronographia | D84: VI 183.1-13 | E84: When she died at a great age, grief for her persisted deep in <Konstantinos 9>'s heart: not only did he mourn her, pour libations of tears on her tomb and propitiate heaven on her behalf, but he wished to accord her God-like honour. One of the little silver-plated columns around her tomb took in moisture in a part where the precious metal had split and in accordance with natural laws produced a little mushroom. <Konstantinos 9>, full of enthusiasm, filled the palace with the cry that the Lord had wrought a miracle at her tomb, so that all might know that her soul was numbered among the angels. | F84: J 1050 | G84: Sewter | H84: n. 142 | I84: [I merged three subsequent entries from PBW about Zoe death from Chronographia into one as they all refer to the same passage from Psellos' Chronographia (VI 183.1-13)] Psellos here does not refer to any year nor date. The English translator of Chronographia notes that "Zoe was seventy-two when she died in 1050," see n. 142. | L84: =_xlfn.XLOOKUP(_xlfn.CONCAT(A84, " ", B84), Persons!B:B, Persons!S:S) -> Zoe 1 / Empress Zoe | M84: Death | N84: =F84 -> J 1050 | P84: 9429963 / Sewter, Edgar Robert Ashton | S84: Psellos: Chronographia (English) | T84: =H84 -> n. 142
A85: Zoe | B85: 1 | C85: Anonymus Barensis | D85: 151 | E85: She died | F85: J 1050 | G85: Source | I85: "Mill. L. Ind. III obiit Tioy Imperati." Tioy in Anonymus Barensis is Zoe, see n. 25 on the same page. | L85: =_xlfn.XLOOKUP(_xlfn.CONCAT(A85, " ", B85), Persons!B:B, Persons!S:S) -> Zoe 1 / Empress Zoe | M85: Death | N85: =F85 -> J 1050 | P85: =_xlfn.XLOOKUP(C85,'Text publications'!A:A,'Text publications'!D:D,"") -> 13129565 / Anonymus Barensis | S85: =C85 -> Anonymus Barensis | T85: =D85 -> 151
A86: Zoe | B86: 1 | C86: Lupus protospatharius | D86: 59.9-13 | E86: She died, having reigned with three imperial husbands, <Romanos 3>, <Michael 4> and <Konstantinos 9>, a total of 22 years; after her death Konstantinos reigned on with (?) Theodora, for 9 years [5 years for Konstantinos, <Theodora 107> years more] | F86: J 1050 | G86: Source | L86: =_xlfn.XLOOKUP(_xlfn.CONCAT(A86, " ", B86), Persons!B:B, Persons!S:S) -> Zoe 1 / Empress Zoe | M86: Death | N86: =F86 -> J 1050 | P86: =_xlfn.XLOOKUP(C86,'Text publications'!A:A,'Text publications'!D:D,"") -> 84485715 / Lupus Protospatharius | S86: =C86 -> Lupus protospatharius | T86: =D86 -> 59.9-13
A87: Zoe | B87: 1 | C87: Skylitzes | D87: 478.89-90 | E87: Died before (her husband) <Konstantinos 9> | F87: J 1050 | G87: Wortley | H87: p. 445, n. 207 | I87: Skylitzes does not provide the date but themost recent English translator notes that Zoe died towards 1050, see p. 445, n. 207. | L87: =_xlfn.XLOOKUP(_xlfn.CONCAT(A87, " ", B87), Persons!B:B, Persons!S:S) -> Zoe 1 / Empress Zoe | M87: Death | N87: =F87 -> J 1050 | P87: 54176097 / Wortley, John | S87: Skylitzes (English) | T87: =H87 -> p. 445, n. 207
